Compiled from "RenderPipelines.java"
public class net.minecraft.client.gl.RenderPipelines {
  public static final com.mojang.blaze3d.pipeline.RenderPipeline$Snippet TRANSFORMS_AND_PROJECTION_SNIPPET;

  public static final com.mojang.blaze3d.pipeline.RenderPipeline$Snippet FOG_SNIPPET;

  public static final com.mojang.blaze3d.pipeline.RenderPipeline$Snippet GLOBALS_SNIPPET;

  public static final com.mojang.blaze3d.pipeline.RenderPipeline$Snippet TRANSFORMS_PROJECTION_FOG_SNIPPET;

  public static final com.mojang.blaze3d.pipeline.RenderPipeline$Snippet TRANSFORMS_PROJECTION_FOG_LIGHTING_SNIPPET;

  public static final com.mojang.blaze3d.pipeline.RenderPipeline$Snippet TERRAIN_SNIPPET;

  public static final com.mojang.blaze3d.pipeline.RenderPipeline$Snippet ENTITY_SNIPPET;

  public static final com.mojang.blaze3d.pipeline.RenderPipeline$Snippet ENTITY_EMISSIVE_SNIPPET;

  public static final com.mojang.blaze3d.pipeline.RenderPipeline$Snippet RENDERTYPE_BEACON_BEAM_SNIPPET;

  public static final com.mojang.blaze3d.pipeline.RenderPipeline$Snippet TEXT_SNIPPET;

  public static final com.mojang.blaze3d.pipeline.RenderPipeline$Snippet RENDERTYPE_END_PORTAL_SNIPPET;

  public static final com.mojang.blaze3d.pipeline.RenderPipeline$Snippet RENDERTYPE_CLOUDS_SNIPPET;

  public static final com.mojang.blaze3d.pipeline.RenderPipeline$Snippet RENDERTYPE_LINES_SNIPPET;

  public static final com.mojang.blaze3d.pipeline.RenderPipeline$Snippet POSITION_COLOR_SNIPPET;

  public static final com.mojang.blaze3d.pipeline.RenderPipeline$Snippet PARTICLE_SNIPPET;

  public static final com.mojang.blaze3d.pipeline.RenderPipeline$Snippet WEATHER_SNIPPET;

  public static final com.mojang.blaze3d.pipeline.RenderPipeline$Snippet GUI_SNIPPET;

  public static final com.mojang.blaze3d.pipeline.RenderPipeline$Snippet POSITION_TEX_COLOR_SNIPPET;

  public static final com.mojang.blaze3d.pipeline.RenderPipeline$Snippet RENDERTYPE_OUTLINE_SNIPPET;

  public static final com.mojang.blaze3d.pipeline.RenderPipeline$Snippet POST_EFFECT_PROCESSOR_SNIPPET;

  public static final com.mojang.blaze3d.pipeline.RenderPipeline SOLID;

  public static final com.mojang.blaze3d.pipeline.RenderPipeline WIREFRAME;

  public static final com.mojang.blaze3d.pipeline.RenderPipeline CUTOUT_MIPPED;

  public static final com.mojang.blaze3d.pipeline.RenderPipeline CUTOUT;

  public static final com.mojang.blaze3d.pipeline.RenderPipeline TRANSLUCENT;

  public static final com.mojang.blaze3d.pipeline.RenderPipeline TRIPWIRE;

  public static final com.mojang.blaze3d.pipeline.RenderPipeline RENDERTYPE_TRANSLUCENT_MOVING_BLOCK;

  public static final com.mojang.blaze3d.pipeline.RenderPipeline ARMOR_CUTOUT_NO_CULL;

  public static final com.mojang.blaze3d.pipeline.RenderPipeline ARMOR_DECAL_CUTOUT_NO_CULL;

  public static final com.mojang.blaze3d.pipeline.RenderPipeline ARMOR_TRANSLUCENT;

  public static final com.mojang.blaze3d.pipeline.RenderPipeline ENTITY_SOLID;

  public static final com.mojang.blaze3d.pipeline.RenderPipeline ENTITY_SOLID_OFFSET_FORWARD;

  public static final com.mojang.blaze3d.pipeline.RenderPipeline ENTITY_CUTOUT;

  public static final com.mojang.blaze3d.pipeline.RenderPipeline ENTITY_CUTOUT_NO_CULL;

  public static final com.mojang.blaze3d.pipeline.RenderPipeline ENTITY_CUTOUT_NO_CULL_Z_OFFSET;

  public static final com.mojang.blaze3d.pipeline.RenderPipeline ENTITY_TRANSLUCENT;

  public static final com.mojang.blaze3d.pipeline.RenderPipeline ENTITY_TRANSLUCENT_EMISSIVE;

  public static final com.mojang.blaze3d.pipeline.RenderPipeline ENTITY_SMOOTH_CUTOUT;

  public static final com.mojang.blaze3d.pipeline.RenderPipeline ENTITY_NO_OUTLINE;

  public static final com.mojang.blaze3d.pipeline.RenderPipeline BREEZE_WIND;

  public static final com.mojang.blaze3d.pipeline.RenderPipeline ENTITY_ENERGY_SWIRL;

  public static final com.mojang.blaze3d.pipeline.RenderPipeline ENTITY_EYES;

  public static final com.mojang.blaze3d.pipeline.RenderPipeline RENDERTYPE_ENTITY_DECAL;

  public static final com.mojang.blaze3d.pipeline.RenderPipeline RENDERTYPE_ENTITY_SHADOW;

  public static final com.mojang.blaze3d.pipeline.RenderPipeline RENDERTYPE_ITEM_ENTITY_TRANSLUCENT_CULL;

  public static final com.mojang.blaze3d.pipeline.RenderPipeline BEACON_BEAM_OPAQUE;

  public static final com.mojang.blaze3d.pipeline.RenderPipeline BEACON_BEAM_TRANSLUCENT;

  public static final com.mojang.blaze3d.pipeline.RenderPipeline RENDERTYPE_ENTITY_ALPHA;

  public static final com.mojang.blaze3d.pipeline.RenderPipeline RENDERTYPE_LEASH;

  public static final com.mojang.blaze3d.pipeline.RenderPipeline RENDERTYPE_WATER_MASK;

  public static final com.mojang.blaze3d.pipeline.RenderPipeline GLINT;

  public static final com.mojang.blaze3d.pipeline.RenderPipeline RENDERTYPE_CRUMBLING;

  public static final com.mojang.blaze3d.pipeline.RenderPipeline RENDERTYPE_TEXT;

  public static final com.mojang.blaze3d.pipeline.RenderPipeline RENDERTYPE_TEXT_BG;

  public static final com.mojang.blaze3d.pipeline.RenderPipeline RENDERTYPE_TEXT_INTENSITY;

  public static final com.mojang.blaze3d.pipeline.RenderPipeline RENDERTYPE_TEXT_POLYGON_OFFSET;

  public static final com.mojang.blaze3d.pipeline.RenderPipeline RENDERTYPE_TEXT_SEETHROUGH;

  public static final com.mojang.blaze3d.pipeline.RenderPipeline RENDERTYPE_TEXT_BG_SEETHROUGH;

  public static final com.mojang.blaze3d.pipeline.RenderPipeline RENDERTYPE_TEXT_INTENSITY_SEETHROUGH;

  public static final com.mojang.blaze3d.pipeline.RenderPipeline RENDERTYPE_LIGHTNING;

  public static final com.mojang.blaze3d.pipeline.RenderPipeline RENDERTYPE_LIGHTNING_DRAGON_RAYS;

  public static final com.mojang.blaze3d.pipeline.RenderPipeline POSITION_DRAGON_RAYS_DEPTH;

  public static final com.mojang.blaze3d.pipeline.RenderPipeline END_PORTAL;

  public static final com.mojang.blaze3d.pipeline.RenderPipeline END_GATEWAY;

  public static final com.mojang.blaze3d.pipeline.RenderPipeline FLAT_CLOUDS;

  public static final com.mojang.blaze3d.pipeline.RenderPipeline CLOUDS;

  public static final com.mojang.blaze3d.pipeline.RenderPipeline LINES;

  public static final com.mojang.blaze3d.pipeline.RenderPipeline SECOND_BLOCK_OUTLINE;

  public static final com.mojang.blaze3d.pipeline.RenderPipeline LINE_STRIP;

  public static final com.mojang.blaze3d.pipeline.RenderPipeline DEBUG_LINE_STRIP;

  public static final com.mojang.blaze3d.pipeline.RenderPipeline DEBUG_FILLED_BOX;

  public static final com.mojang.blaze3d.pipeline.RenderPipeline DEBUG_QUADS;

  public static final com.mojang.blaze3d.pipeline.RenderPipeline DEBUG_TRIANGLE_FAN;

  public static final com.mojang.blaze3d.pipeline.RenderPipeline DEBUG_STRUCTURE_QUADS;

  public static final com.mojang.blaze3d.pipeline.RenderPipeline DEBUG_SECTION_QUADS;

  public static final com.mojang.blaze3d.pipeline.RenderPipeline RENDERTYPE_WORLD_BORDER;

  public static final com.mojang.blaze3d.pipeline.RenderPipeline OPAQUE_PARTICLE;

  public static final com.mojang.blaze3d.pipeline.RenderPipeline TRANSLUCENT_PARTICLE;

  public static final com.mojang.blaze3d.pipeline.RenderPipeline WEATHER_DEPTH;

  public static final com.mojang.blaze3d.pipeline.RenderPipeline WEATHER_NO_DEPTH;

  public static final com.mojang.blaze3d.pipeline.RenderPipeline POSITION_SKY;

  public static final com.mojang.blaze3d.pipeline.RenderPipeline POSITION_TEX_COLOR_END_SKY;

  public static final com.mojang.blaze3d.pipeline.RenderPipeline POSITION_COLOR_SUNRISE_SUNSET;

  public static final com.mojang.blaze3d.pipeline.RenderPipeline POSITION_STARS;

  public static final com.mojang.blaze3d.pipeline.RenderPipeline POSITION_TEX_COLOR_CELESTIAL;

  public static final com.mojang.blaze3d.pipeline.RenderPipeline GUI;

  public static final com.mojang.blaze3d.pipeline.RenderPipeline GUI_INVERT;

  public static final com.mojang.blaze3d.pipeline.RenderPipeline GUI_TEXT_HIGHLIGHT;

  public static final com.mojang.blaze3d.pipeline.RenderPipeline GUI_TEXTURED;

  public static final com.mojang.blaze3d.pipeline.RenderPipeline GUI_TEXTURED_PREMULTIPLIED_ALPHA;

  public static final com.mojang.blaze3d.pipeline.RenderPipeline BLOCK_SCREEN_EFFECT;

  public static final com.mojang.blaze3d.pipeline.RenderPipeline FIRE_SCREEN_EFFECT;

  public static final com.mojang.blaze3d.pipeline.RenderPipeline GUI_OPAQUE_TEX_BG;

  public static final com.mojang.blaze3d.pipeline.RenderPipeline GUI_NAUSEA_OVERLAY;

  public static final com.mojang.blaze3d.pipeline.RenderPipeline VIGNETTE;

  public static final com.mojang.blaze3d.pipeline.RenderPipeline CROSSHAIR;

  public static final com.mojang.blaze3d.pipeline.RenderPipeline MOJANG_LOGO;

  public static final com.mojang.blaze3d.pipeline.RenderPipeline ENTITY_OUTLINE_BLIT;

  public static final com.mojang.blaze3d.pipeline.RenderPipeline TRACY_BLIT;

  public static final com.mojang.blaze3d.pipeline.RenderPipeline POSITION_TEX_PANORAMA;

  public static final com.mojang.blaze3d.pipeline.RenderPipeline OUTLINE_CULL;

  public static final com.mojang.blaze3d.pipeline.RenderPipeline OUTLINE_NO_CULL;

  public static final com.mojang.blaze3d.pipeline.RenderPipeline BILT_SCREEN_LIGHTMAP;

  public net.minecraft.client.gl.RenderPipelines();
    Code:
       0: aload_0
       1: invokespecial #134                // Method java/lang/Object."<init>":()V
       4: return

  public static com.mojang.blaze3d.pipeline.RenderPipeline register(com.mojang.blaze3d.pipeline.RenderPipeline);
    Code:
       0: getstatic     #141                // Field PIPELINES:Ljava/util/Map;
       3: aload_0
       4: invokevirtual #145                // Method com/mojang/blaze3d/pipeline/RenderPipeline.getLocation:()Lnet/minecraft/util/Identifier;
       7: aload_0
       8: invokeinterface #151,  3          // InterfaceMethod java/util/Map.put:(Ljava/lang/Object;Ljava/lang/Object;)Ljava/lang/Object;
      13: pop
      14: aload_0
      15: areturn

  public static java.util.List<com.mojang.blaze3d.pipeline.RenderPipeline> getAll();
    Code:
       0: getstatic     #141                // Field PIPELINES:Ljava/util/Map;
       3: invokeinterface #158,  1          // InterfaceMethod java/util/Map.values:()Ljava/util/Collection;
       8: invokeinterface #164,  1          // InterfaceMethod java/util/Collection.stream:()Ljava/util/stream/Stream;
      13: invokeinterface #169,  1          // InterfaceMethod java/util/stream/Stream.toList:()Ljava/util/List;
      18: areturn

  static {};
    Code:
       0: new           #172                // class java/util/HashMap
       3: dup
       4: invokespecial #173                // Method java/util/HashMap."<init>":()V
       7: putstatic     #141                // Field PIPELINES:Ljava/util/Map;
      10: iconst_0
      11: anewarray     #11                 // class com/mojang/blaze3d/pipeline/RenderPipeline$Snippet
      14: invokestatic  #177                // Method com/mojang/blaze3d/pipeline/RenderPipeline.builder:([Lcom/mojang/blaze3d/pipeline/RenderPipeline$Snippet;)Lcom/mojang/blaze3d/pipeline/RenderPipeline$Builder;
      17: ldc           #179                // String DynamicTransforms
      19: getstatic     #185                // Field net/minecraft/client/gl/UniformType.UNIFORM_BUFFER:Lnet/minecraft/client/gl/UniformType;
      22: invokevirtual #189                // Method com/mojang/blaze3d/pipeline/RenderPipeline$Builder.withUniform:(Ljava/lang/String;Lnet/minecraft/client/gl/UniformType;)Lcom/mojang/blaze3d/pipeline/RenderPipeline$Builder;
      25: ldc           #191                // String Projection
      27: getstatic     #185                // Field net/minecraft/client/gl/UniformType.UNIFORM_BUFFER:Lnet/minecraft/client/gl/UniformType;
      30: invokevirtual #189                // Method com/mojang/blaze3d/pipeline/RenderPipeline$Builder.withUniform:(Ljava/lang/String;Lnet/minecraft/client/gl/UniformType;)Lcom/mojang/blaze3d/pipeline/RenderPipeline$Builder;
      33: invokevirtual #195                // Method com/mojang/blaze3d/pipeline/RenderPipeline$Builder.buildSnippet:()Lcom/mojang/blaze3d/pipeline/RenderPipeline$Snippet;
      36: putstatic     #197                // Field TRANSFORMS_AND_PROJECTION_SNIPPET:Lcom/mojang/blaze3d/pipeline/RenderPipeline$Snippet;
      39: iconst_0
      40: anewarray     #11                 // class com/mojang/blaze3d/pipeline/RenderPipeline$Snippet
      43: invokestatic  #177                // Method com/mojang/blaze3d/pipeline/RenderPipeline.builder:([Lcom/mojang/blaze3d/pipeline/RenderPipeline$Snippet;)Lcom/mojang/blaze3d/pipeline/RenderPipeline$Builder;
      46: ldc           #199                // String Fog
      48: getstatic     #185                // Field net/minecraft/client/gl/UniformType.UNIFORM_BUFFER:Lnet/minecraft/client/gl/UniformType;
      51: invokevirtual #189                // Method com/mojang/blaze3d/pipeline/RenderPipeline$Builder.withUniform:(Ljava/lang/String;Lnet/minecraft/client/gl/UniformType;)Lcom/mojang/blaze3d/pipeline/RenderPipeline$Builder;
      54: invokevirtual #195                // Method com/mojang/blaze3d/pipeline/RenderPipeline$Builder.buildSnippet:()Lcom/mojang/blaze3d/pipeline/RenderPipeline$Snippet;
      57: putstatic     #201                // Field FOG_SNIPPET:Lcom/mojang/blaze3d/pipeline/RenderPipeline$Snippet;
      60: iconst_0
      61: anewarray     #11                 // class com/mojang/blaze3d/pipeline/RenderPipeline$Snippet
      64: invokestatic  #177                // Method com/mojang/blaze3d/pipeline/RenderPipeline.builder:([Lcom/mojang/blaze3d/pipeline/RenderPipeline$Snippet;)Lcom/mojang/blaze3d/pipeline/RenderPipeline$Builder;
      67: ldc           #203                // String Globals
      69: getstatic     #185                // Field net/minecraft/client/gl/UniformType.UNIFORM_BUFFER:Lnet/minecraft/client/gl/UniformType;
      72: invokevirtual #189                // Method com/mojang/blaze3d/pipeline/RenderPipeline$Builder.withUniform:(Ljava/lang/String;Lnet/minecraft/client/gl/UniformType;)Lcom/mojang/blaze3d/pipeline/RenderPipeline$Builder;
      75: invokevirtual #195                // Method com/mojang/blaze3d/pipeline/RenderPipeline$Builder.buildSnippet:()Lcom/mojang/blaze3d/pipeline/RenderPipeline$Snippet;
      78: putstatic     #205                // Field GLOBALS_SNIPPET:Lcom/mojang/blaze3d/pipeline/RenderPipeline$Snippet;
      81: iconst_2
      82: anewarray     #11                 // class com/mojang/blaze3d/pipeline/RenderPipeline$Snippet
      85: dup
      86: iconst_0
      87: getstatic     #197                // Field TRANSFORMS_AND_PROJECTION_SNIPPET:Lcom/mojang/blaze3d/pipeline/RenderPipeline$Snippet;
      90: aastore
      91: dup
      92: iconst_1
      93: getstatic     #201                // Field FOG_SNIPPET:Lcom/mojang/blaze3d/pipeline/RenderPipeline$Snippet;
      96: aastore
      97: invokestatic  #177                // Method com/mojang/blaze3d/pipeline/RenderPipeline.builder:([Lcom/mojang/blaze3d/pipeline/RenderPipeline$Snippet;)Lcom/mojang/blaze3d/pipeline/RenderPipeline$Builder;
     100: invokevirtual #195                // Method com/mojang/blaze3d/pipeline/RenderPipeline$Builder.buildSnippet:()Lcom/mojang/blaze3d/pipeline/RenderPipeline$Snippet;
     103: putstatic     #207                // Field TRANSFORMS_PROJECTION_FOG_SNIPPET:Lcom/mojang/blaze3d/pipeline/RenderPipeline$Snippet;
     106: iconst_2
     107: anewarray     #11                 // class com/mojang/blaze3d/pipeline/RenderPipeline$Snippet
     110: dup
     111: iconst_0
     112: getstatic     #197                // Field TRANSFORMS_AND_PROJECTION_SNIPPET:Lcom/mojang/blaze3d/pipeline/RenderPipeline$Snippet;
     115: aastore
     116: dup
     117: iconst_1
     118: getstatic     #201                // Field FOG_SNIPPET:Lcom/mojang/blaze3d/pipeline/RenderPipeline$Snippet;
     121: aastore
     122: invokestatic  #177                // Method com/mojang/blaze3d/pipeline/RenderPipeline.builder:([Lcom/mojang/blaze3d/pipeline/RenderPipeline$Snippet;)Lcom/mojang/blaze3d/pipeline/RenderPipeline$Builder;
     125: ldc           #209                // String Lighting
     127: getstatic     #185                // Field net/minecraft/client/gl/UniformType.UNIFORM_BUFFER:Lnet/minecraft/client/gl/UniformType;
     130: invokevirtual #189                // Method com/mojang/blaze3d/pipeline/RenderPipeline$Builder.withUniform:(Ljava/lang/String;Lnet/minecraft/client/gl/UniformType;)Lcom/mojang/blaze3d/pipeline/RenderPipeline$Builder;
     133: invokevirtual #195                // Method com/mojang/blaze3d/pipeline/RenderPipeline$Builder.buildSnippet:()Lcom/mojang/blaze3d/pipeline/RenderPipeline$Snippet;
     136: putstatic     #211                // Field TRANSFORMS_PROJECTION_FOG_LIGHTING_SNIPPET:Lcom/mojang/blaze3d/pipeline/RenderPipeline$Snippet;
     139: iconst_1
     140: anewarray     #11                 // class com/mojang/blaze3d/pipeline/RenderPipeline$Snippet
     143: dup
     144: iconst_0
     145: getstatic     #207                // Field TRANSFORMS_PROJECTION_FOG_SNIPPET:Lcom/mojang/blaze3d/pipeline/RenderPipeline$Snippet;
     148: aastore
     149: invokestatic  #177                // Method com/mojang/blaze3d/pipeline/RenderPipeline.builder:([Lcom/mojang/blaze3d/pipeline/RenderPipeline$Snippet;)Lcom/mojang/blaze3d/pipeline/RenderPipeline$Builder;
     152: ldc           #213                // String core/terrain
     154: invokevirtual #217                // Method com/mojang/blaze3d/pipeline/RenderPipeline$Builder.withVertexShader:(Ljava/lang/String;)Lcom/mojang/blaze3d/pipeline/RenderPipeline$Builder;
     157: ldc           #213                // String core/terrain
     159: invokevirtual #220                // Method com/mojang/blaze3d/pipeline/RenderPipeline$Builder.withFragmentShader:(Ljava/lang/String;)Lcom/mojang/blaze3d/pipeline/RenderPipeline$Builder;
     162: ldc           #222                // String Sampler0
     164: invokevirtual #225                // Method com/mojang/blaze3d/pipeline/RenderPipeline$Builder.withSampler:(Ljava/lang/String;)Lcom/mojang/blaze3d/pipeline/RenderPipeline$Builder;
     167: ldc           #227                // String Sampler2
     169: invokevirtual #225                // Method com/mojang/blaze3d/pipeline/RenderPipeline$Builder.withSampler:(Ljava/lang/String;)Lcom/mojang/blaze3d/pipeline/RenderPipeline$Builder;
     172: getstatic     #233                // Field net/minecraft/client/render/VertexFormats.POSITION_COLOR_TEXTURE_LIGHT_NORMAL:Lcom/mojang/blaze3d/vertex/VertexFormat;
     175: getstatic     #237                // Field com/mojang/blaze3d/vertex/VertexFormat$DrawMode.QUADS:Lcom/mojang/blaze3d/vertex/VertexFormat$DrawMode;
     178: invokevirtual #241                // Method com/mojang/blaze3d/pipeline/RenderPipeline$Builder.withVertexFormat:(Lcom/mojang/blaze3d/vertex/VertexFormat;Lcom/mojang/blaze3d/vertex/VertexFormat$DrawMode;)Lcom/mojang/blaze3d/pipeline/RenderPipeline$Builder;
     181: invokevirtual #195                // Method com/mojang/blaze3d/pipeline/RenderPipeline$Builder.buildSnippet:()Lcom/mojang/blaze3d/pipeline/RenderPipeline$Snippet;
     184: putstatic     #243                // Field TERRAIN_SNIPPET:Lcom/mojang/blaze3d/pipeline/RenderPipeline$Snippet;
     187: iconst_1
     188: anewarray     #11                 // class com/mojang/blaze3d/pipeline/RenderPipeline$Snippet
     191: dup
     192: iconst_0
     193: getstatic     #211                // Field TRANSFORMS_PROJECTION_FOG_LIGHTING_SNIPPET:Lcom/mojang/blaze3d/pipeline/RenderPipeline$Snippet;
     196: aastore
     197: invokestatic  #177                // Method com/mojang/blaze3d/pipeline/RenderPipeline.builder:([Lcom/mojang/blaze3d/pipeline/RenderPipeline$Snippet;)Lcom/mojang/blaze3d/pipeline/RenderPipeline$Builder;
     200: ldc           #245                // String core/entity
     202: invokevirtual #217                // Method com/mojang/blaze3d/pipeline/RenderPipeline$Builder.withVertexShader:(Ljava/lang/String;)Lcom/mojang/blaze3d/pipeline/RenderPipeline$Builder;
     205: ldc           #245                // String core/entity
     207: invokevirtual #220                // Method com/mojang/blaze3d/pipeline/RenderPipeline$Builder.withFragmentShader:(Ljava/lang/String;)Lcom/mojang/blaze3d/pipeline/RenderPipeline$Builder;
     210: ldc           #222                // String Sampler0
     212: invokevirtual #225                // Method com/mojang/blaze3d/pipeline/RenderPipeline$Builder.withSampler:(Ljava/lang/String;)Lcom/mojang/blaze3d/pipeline/RenderPipeline$Builder;
     215: ldc           #227                // String Sampler2
     217: invokevirtual #225                // Method com/mojang/blaze3d/pipeline/RenderPipeline$Builder.withSampler:(Ljava/lang/String;)Lcom/mojang/blaze3d/pipeline/RenderPipeline$Builder;
     220: getstatic     #248                // Field net/minecraft/client/render/VertexFormats.POSITION_COLOR_TEXTURE_OVERLAY_LIGHT_NORMAL:Lcom/mojang/blaze3d/vertex/VertexFormat;
     223: getstatic     #237                // Field com/mojang/blaze3d/vertex/VertexFormat$DrawMode.QUADS:Lcom/mojang/blaze3d/vertex/VertexFormat$DrawMode;
     226: invokevirtual #241                // Method com/mojang/blaze3d/pipeline/RenderPipeline$Builder.withVertexFormat:(Lcom/mojang/blaze3d/vertex/VertexFormat;Lcom/mojang/blaze3d/vertex/VertexFormat$DrawMode;)Lcom/mojang/blaze3d/pipeline/RenderPipeline$Builder;
     229: invokevirtual #195                // Method com/mojang/blaze3d/pipeline/RenderPipeline$Builder.buildSnippet:()Lcom/mojang/blaze3d/pipeline/RenderPipeline$Snippet;
     232: putstatic     #250                // Field ENTITY_SNIPPET:Lcom/mojang/blaze3d/pipeline/RenderPipeline$Snippet;
     235: iconst_1
     236: anewarray     #11                 // class com/mojang/blaze3d/pipeline/RenderPipeline$Snippet
     239: dup
     240: iconst_0
     241: getstatic     #211                // Field TRANSFORMS_PROJECTION_FOG_LIGHTING_SNIPPET:Lcom/mojang/blaze3d/pipeline/RenderPipeline$Snippet;
     244: aastore
     245: invokestatic  #177                // Method com/mojang/blaze3d/pipeline/RenderPipeline.builder:([Lcom/mojang/blaze3d/pipeline/RenderPipeline$Snippet;)Lcom/mojang/blaze3d/pipeline/RenderPipeline$Builder;
     248: ldc           #245                // String core/entity
     250: invokevirtual #217                // Method com/mojang/blaze3d/pipeline/RenderPipeline$Builder.withVertexShader:(Ljava/lang/String;)Lcom/mojang/blaze3d/pipeline/RenderPipeline$Builder;
     253: ldc           #245                // String core/entity
     255: invokevirtual #220                // Method com/mojang/blaze3d/pipeline/RenderPipeline$Builder.withFragmentShader:(Ljava/lang/String;)Lcom/mojang/blaze3d/pipeline/RenderPipeline$Builder;
     258: ldc           #222                // String Sampler0
     260: invokevirtual #225                // Method com/mojang/blaze3d/pipeline/RenderPipeline$Builder.withSampler:(Ljava/lang/String;)Lcom/mojang/blaze3d/pipeline/RenderPipeline$Builder;
     263: getstatic     #248                // Field net/minecraft/client/render/VertexFormats.POSITION_COLOR_TEXTURE_OVERLAY_LIGHT_NORMAL:Lcom/mojang/blaze3d/vertex/VertexFormat;
     266: getstatic     #237                // Field com/mojang/blaze3d/vertex/VertexFormat$DrawMode.QUADS:Lcom/mojang/blaze3d/vertex/VertexFormat$DrawMode;
     269: invokevirtual #241                // Method com/mojang/blaze3d/pipeline/RenderPipeline$Builder.withVertexFormat:(Lcom/mojang/blaze3d/vertex/VertexFormat;Lcom/mojang/blaze3d/vertex/VertexFormat$DrawMode;)Lcom/mojang/blaze3d/pipeline/RenderPipeline$Builder;
     272: ldc           #252                // String EMISSIVE
     274: invokevirtual #255                // Method com/mojang/blaze3d/pipeline/RenderPipeline$Builder.withShaderDefine:(Ljava/lang/String;)Lcom/mojang/blaze3d/pipeline/RenderPipeline$Builder;
     277: invokevirtual #195                // Method com/mojang/blaze3d/pipeline/RenderPipeline$Builder.buildSnippet:()Lcom/mojang/blaze3d/pipeline/RenderPipeline$Snippet;
     280: putstatic     #257                // Field ENTITY_EMISSIVE_SNIPPET:Lcom/mojang/blaze3d/pipeline/RenderPipeline$Snippet;
     283: iconst_1
     284: anewarray     #11                 // class com/mojang/blaze3d/pipeline/RenderPipeline$Snippet
     287: dup
     288: iconst_0
     289: getstatic     #207                // Field TRANSFORMS_PROJECTION_FOG_SNIPPET:Lcom/mojang/blaze3d/pipeline/RenderPipeline$Snippet;
     292: aastore
     293: invokestatic  #177                // Method com/mojang/blaze3d/pipeline/RenderPipeline.builder:([Lcom/mojang/blaze3d/pipeline/RenderPipeline$Snippet;)Lcom/mojang/blaze3d/pipeline/RenderPipeline$Builder;
     296: ldc_w         #259                // String core/rendertype_beacon_beam
     299: invokevirtual #217                // Method com/mojang/blaze3d/pipeline/RenderPipeline$Builder.withVertexShader:(Ljava/lang/String;)Lcom/mojang/blaze3d/pipeline/RenderPipeline$Builder;
     302: ldc_w         #259                // String core/rendertype_beacon_beam
     305: invokevirtual #220                // Method com/mojang/blaze3d/pipeline/RenderPipeline$Builder.withFragmentShader:(Ljava/lang/String;)Lcom/mojang/blaze3d/pipeline/RenderPipeline$Builder;
     308: ldc           #222                // String Sampler0
     310: invokevirtual #225                // Method com/mojang/blaze3d/pipeline/RenderPipeline$Builder.withSampler:(Ljava/lang/String;)Lcom/mojang/blaze3d/pipeline/RenderPipeline$Builder;
     313: getstatic     #233                // Field net/minecraft/client/render/VertexFormats.POSITION_COLOR_TEXTURE_LIGHT_NORMAL:Lcom/mojang/blaze3d/vertex/VertexFormat;
     316: getstatic     #237                // Field com/mojang/blaze3d/vertex/VertexFormat$DrawMode.QUADS:Lcom/mojang/blaze3d/vertex/VertexFormat$DrawMode;
     319: invokevirtual #241                // Method com/mojang/blaze3d/pipeline/RenderPipeline$Builder.withVertexFormat:(Lcom/mojang/blaze3d/vertex/VertexFormat;Lcom/mojang/blaze3d/vertex/VertexFormat$DrawMode;)Lcom/mojang/blaze3d/pipeline/RenderPipeline$Builder;
     322: invokevirtual #195                // Method com/mojang/blaze3d/pipeline/RenderPipeline$Builder.buildSnippet:()Lcom/mojang/blaze3d/pipeline/RenderPipeline$Snippet;
     325: putstatic     #261                // Field RENDERTYPE_BEACON_BEAM_SNIPPET:Lcom/mojang/blaze3d/pipeline/RenderPipeline$Snippet;
     328: iconst_1
     329: anewarray     #11                 // class com/mojang/blaze3d/pipeline/RenderPipeline$Snippet
     332: dup
     333: iconst_0
     334: getstatic     #197                // Field TRANSFORMS_AND_PROJECTION_SNIPPET:Lcom/mojang/blaze3d/pipeline/RenderPipeline$Snippet;
     337: aastore
     338: invokestatic  #177                // Method com/mojang/blaze3d/pipeline/RenderPipeline.builder:([Lcom/mojang/blaze3d/pipeline/RenderPipeline$Snippet;)Lcom/mojang/blaze3d/pipeline/RenderPipeline$Builder;
     341: getstatic     #266                // Field com/mojang/blaze3d/pipeline/BlendFunction.TRANSLUCENT:Lcom/mojang/blaze3d/pipeline/BlendFunction;
     344: invokevirtual #270                // Method com/mojang/blaze3d/pipeline/RenderPipeline$Builder.withBlend:(Lcom/mojang/blaze3d/pipeline/BlendFunction;)Lcom/mojang/blaze3d/pipeline/RenderPipeline$Builder;
     347: getstatic     #273                // Field net/minecraft/client/render/VertexFormats.POSITION_COLOR_TEXTURE_LIGHT:Lcom/mojang/blaze3d/vertex/VertexFormat;
     350: getstatic     #237                // Field com/mojang/blaze3d/vertex/VertexFormat$DrawMode.QUADS:Lcom/mojang/blaze3d/vertex/VertexFormat$DrawMode;
     353: invokevirtual #241                // Method com/mojang/blaze3d/pipeline/RenderPipeline$Builder.withVertexFormat:(Lcom/mojang/blaze3d/vertex/VertexFormat;Lcom/mojang/blaze3d/vertex/VertexFormat$DrawMode;)Lcom/mojang/blaze3d/pipeline/RenderPipeline$Builder;
     356: invokevirtual #195                // Method com/mojang/blaze3d/pipeline/RenderPipeline$Builder.buildSnippet:()Lcom/mojang/blaze3d/pipeline/RenderPipeline$Snippet;
     359: putstatic     #275                // Field TEXT_SNIPPET:Lcom/mojang/blaze3d/pipeline/RenderPipeline$Snippet;
     362: iconst_3
     363: anewarray     #11                 // class com/mojang/blaze3d/pipeline/RenderPipeline$Snippet
     366: dup
     367: iconst_0
     368: getstatic     #197                // Field TRANSFORMS_AND_PROJECTION_SNIPPET:Lcom/mojang/blaze3d/pipeline/RenderPipeline$Snippet;
     371: aastore
     372: dup
     373: iconst_1
     374: getstatic     #201                // Field FOG_SNIPPET:Lcom/mojang/blaze3d/pipeline/RenderPipeline$Snippet;
     377: aastore
     378: dup
     379: iconst_2
     380: getstatic     #205                // Field GLOBALS_SNIPPET:Lcom/mojang/blaze3d/pipeline/RenderPipeline$Snippet;
     383: aastore
     384: invokestatic  #177                // Method com/mojang/blaze3d/pipeline/RenderPipeline.builder:([Lcom/mojang/blaze3d/pipeline/RenderPipeline$Snippet;)Lcom/mojang/blaze3d/pipeline/RenderPipeline$Builder;
     387: ldc_w         #277                // String core/rendertype_end_portal
     390: invokevirtual #217                // Method com/mojang/blaze3d/pipeline/RenderPipeline$Builder.withVertexShader:(Ljava/lang/String;)Lcom/mojang/blaze3d/pipeline/RenderPipeline$Builder;
     393: ldc_w         #277                // String core/rendertype_end_portal
     396: invokevirtual #220                // Method com/mojang/blaze3d/pipeline/RenderPipeline$Builder.withFragmentShader:(Ljava/lang/String;)Lcom/mojang/blaze3d/pipeline/RenderPipeline$Builder;
     399: ldc           #222                // String Sampler0
     401: invokevirtual #225                // Method com/mojang/blaze3d/pipeline/RenderPipeline$Builder.withSampler:(Ljava/lang/String;)Lcom/mojang/blaze3d/pipeline/RenderPipeline$Builder;
     404: ldc_w         #279                // String Sampler1
     407: invokevirtual #225                // Method com/mojang/blaze3d/pipeline/RenderPipeline$Builder.withSampler:(Ljava/lang/String;)Lcom/mojang/blaze3d/pipeline/RenderPipeline$Builder;
     410: getstatic     #282                // Field net/minecraft/client/render/VertexFormats.POSITION:Lcom/mojang/blaze3d/vertex/VertexFormat;
     413: getstatic     #237                // Field com/mojang/blaze3d/vertex/VertexFormat$DrawMode.QUADS:Lcom/mojang/blaze3d/vertex/VertexFormat$DrawMode;
     416: invokevirtual #241                // Method com/mojang/blaze3d/pipeline/RenderPipeline$Builder.withVertexFormat:(Lcom/mojang/blaze3d/vertex/VertexFormat;Lcom/mojang/blaze3d/vertex/VertexFormat$DrawMode;)Lcom/mojang/blaze3d/pipeline/RenderPipeline$Builder;
     419: invokevirtual #195                // Method com/mojang/blaze3d/pipeline/RenderPipeline$Builder.buildSnippet:()Lcom/mojang/blaze3d/pipeline/RenderPipeline$Snippet;
     422: putstatic     #284                // Field RENDERTYPE_END_PORTAL_SNIPPET:Lcom/mojang/blaze3d/pipeline/RenderPipeline$Snippet;
     425: iconst_1
     426: anewarray     #11                 // class com/mojang/blaze3d/pipeline/RenderPipeline$Snippet
     429: dup
     430: iconst_0
     431: getstatic     #207                // Field TRANSFORMS_PROJECTION_FOG_SNIPPET:Lcom/mojang/blaze3d/pipeline/RenderPipeline$Snippet;
     434: aastore
     435: invokestatic  #177                // Method com/mojang/blaze3d/pipeline/RenderPipeline.builder:([Lcom/mojang/blaze3d/pipeline/RenderPipeline$Snippet;)Lcom/mojang/blaze3d/pipeline/RenderPipeline$Builder;
     438: ldc_w         #286                // String core/rendertype_clouds
     441: invokevirtual #217                // Method com/mojang/blaze3d/pipeline/RenderPipeline$Builder.withVertexShader:(Ljava/lang/String;)Lcom/mojang/blaze3d/pipeline/RenderPipeline$Builder;
     444: ldc_w         #286                // String core/rendertype_clouds
     447: invokevirtual #220                // Method com/mojang/blaze3d/pipeline/RenderPipeline$Builder.withFragmentShader:(Ljava/lang/String;)Lcom/mojang/blaze3d/pipeline/RenderPipeline$Builder;
     450: getstatic     #266                // Field com/mojang/blaze3d/pipeline/BlendFunction.TRANSLUCENT:Lcom/mojang/blaze3d/pipeline/BlendFunction;
     453: invokevirtual #270                // Method com/mojang/blaze3d/pipeline/RenderPipeline$Builder.withBlend:(Lcom/mojang/blaze3d/pipeline/BlendFunction;)Lcom/mojang/blaze3d/pipeline/RenderPipeline$Builder;
     456: getstatic     #289                // Field net/minecraft/client/render/VertexFormats.EMPTY:Lcom/mojang/blaze3d/vertex/VertexFormat;
     459: getstatic     #237                // Field com/mojang/blaze3d/vertex/VertexFormat$DrawMode.QUADS:Lcom/mojang/blaze3d/vertex/VertexFormat$DrawMode;
     462: invokevirtual #241                // Method com/mojang/blaze3d/pipeline/RenderPipeline$Builder.withVertexFormat:(Lcom/mojang/blaze3d/vertex/VertexFormat;Lcom/mojang/blaze3d/vertex/VertexFormat$DrawMode;)Lcom/mojang/blaze3d/pipeline/RenderPipeline$Builder;
     465: ldc_w         #291                // String CloudInfo
     468: getstatic     #185                // Field net/minecraft/client/gl/UniformType.UNIFORM_BUFFER:Lnet/minecraft/client/gl/UniformType;
     471: invokevirtual #189                // Method com/mojang/blaze3d/pipeline/RenderPipeline$Builder.withUniform:(Ljava/lang/String;Lnet/minecraft/client/gl/UniformType;)Lcom/mojang/blaze3d/pipeline/RenderPipeline$Builder;
     474: ldc_w         #293                // String CloudFaces
     477: getstatic     #296                // Field net/minecraft/client/gl/UniformType.TEXEL_BUFFER:Lnet/minecraft/client/gl/UniformType;
     480: getstatic     #302                // Field com/mojang/blaze3d/textures/TextureFormat.RED8I:Lcom/mojang/blaze3d/textures/TextureFormat;
     483: invokevirtual #305                // Method com/mojang/blaze3d/pipeline/RenderPipeline$Builder.withUniform:(Ljava/lang/String;Lnet/minecraft/client/gl/UniformType;Lcom/mojang/blaze3d/textures/TextureFormat;)Lcom/mojang/blaze3d/pipeline/RenderPipeline$Builder;
     486: invokevirtual #195                // Method com/mojang/blaze3d/pipeline/RenderPipeline$Builder.buildSnippet:()Lcom/mojang/blaze3d/pipeline/RenderPipeline$Snippet;
     489: putstatic     #307                // Field RENDERTYPE_CLOUDS_SNIPPET:Lcom/mojang/blaze3d/pipeline/RenderPipeline$Snippet;
     492: iconst_2
     493: anewarray     #11                 // class com/mojang/blaze3d/pipeline/RenderPipeline$Snippet
     496: dup
     497: iconst_0
     498: getstatic     #207                // Field TRANSFORMS_PROJECTION_FOG_SNIPPET:Lcom/mojang/blaze3d/pipeline/RenderPipeline$Snippet;
     501: aastore
     502: dup
     503: iconst_1
     504: getstatic     #205                // Field GLOBALS_SNIPPET:Lcom/mojang/blaze3d/pipeline/RenderPipeline$Snippet;
     507: aastore
     508: invokestatic  #177                // Method com/mojang/blaze3d/pipeline/RenderPipeline.builder:([Lcom/mojang/blaze3d/pipeline/RenderPipeline$Snippet;)Lcom/mojang/blaze3d/pipeline/RenderPipeline$Builder;
     511: ldc_w         #309                // String core/rendertype_lines
     514: invokevirtual #217                // Method com/mojang/blaze3d/pipeline/RenderPipeline$Builder.withVertexShader:(Ljava/lang/String;)Lcom/mojang/blaze3d/pipeline/RenderPipeline$Builder;
     517: ldc_w         #309                // String core/rendertype_lines
     520: invokevirtual #220                // Method com/mojang/blaze3d/pipeline/RenderPipeline$Builder.withFragmentShader:(Ljava/lang/String;)Lcom/mojang/blaze3d/pipeline/RenderPipeline$Builder;
     523: getstatic     #266                // Field com/mojang/blaze3d/pipeline/BlendFunction.TRANSLUCENT:Lcom/mojang/blaze3d/pipeline/BlendFunction;
     526: invokevirtual #270                // Method com/mojang/blaze3d/pipeline/RenderPipeline$Builder.withBlend:(Lcom/mojang/blaze3d/pipeline/BlendFunction;)Lcom/mojang/blaze3d/pipeline/RenderPipeline$Builder;
     529: iconst_0
     530: invokevirtual #313                // Method com/mojang/blaze3d/pipeline/RenderPipeline$Builder.withCull:(Z)Lcom/mojang/blaze3d/pipeline/RenderPipeline$Builder;
     533: getstatic     #316                // Field net/minecraft/client/render/VertexFormats.POSITION_COLOR_NORMAL:Lcom/mojang/blaze3d/vertex/VertexFormat;
     536: getstatic     #318                // Field com/mojang/blaze3d/vertex/VertexFormat$DrawMode.LINES:Lcom/mojang/blaze3d/vertex/VertexFormat$DrawMode;
     539: invokevirtual #241                // Method com/mojang/blaze3d/pipeline/RenderPipeline$Builder.withVertexFormat:(Lcom/mojang/blaze3d/vertex/VertexFormat;Lcom/mojang/blaze3d/vertex/VertexFormat$DrawMode;)Lcom/mojang/blaze3d/pipeline/RenderPipeline$Builder;
     542: invokevirtual #195                // Method com/mojang/blaze3d/pipeline/RenderPipeline$Builder.buildSnippet:()Lcom/mojang/blaze3d/pipeline/RenderPipeline$Snippet;
     545: putstatic     #320                // Field RENDERTYPE_LINES_SNIPPET:Lcom/mojang/blaze3d/pipeline/RenderPipeline$Snippet;
     548: iconst_1
     549: anewarray     #11                 // class com/mojang/blaze3d/pipeline/RenderPipeline$Snippet
     552: dup
     553: iconst_0
     554: getstatic     #197                // Field TRANSFORMS_AND_PROJECTION_SNIPPET:Lcom/mojang/blaze3d/pipeline/RenderPipeline$Snippet;
     557: aastore
     558: invokestatic  #177                // Method com/mojang/blaze3d/pipeline/RenderPipeline.builder:([Lcom/mojang/blaze3d/pipeline/RenderPipeline$Snippet;)Lcom/mojang/blaze3d/pipeline/RenderPipeline$Builder;
     561: ldc_w         #322                // String core/position_color
     564: invokevirtual #217                // Method com/mojang/blaze3d/pipeline/RenderPipeline$Builder.withVertexShader:(Ljava/lang/String;)Lcom/mojang/blaze3d/pipeline/RenderPipeline$Builder;
     567: ldc_w         #322                // String core/position_color
     570: invokevirtual #220                // Method com/mojang/blaze3d/pipeline/RenderPipeline$Builder.withFragmentShader:(Ljava/lang/String;)Lcom/mojang/blaze3d/pipeline/RenderPipeline$Builder;
     573: getstatic     #266                // Field com/mojang/blaze3d/pipeline/BlendFunction.TRANSLUCENT:Lcom/mojang/blaze3d/pipeline/BlendFunction;
     576: invokevirtual #270                // Method com/mojang/blaze3d/pipeline/RenderPipeline$Builder.withBlend:(Lcom/mojang/blaze3d/pipeline/BlendFunction;)Lcom/mojang/blaze3d/pipeline/RenderPipeline$Builder;
     579: getstatic     #325                // Field net/minecraft/client/render/VertexFormats.POSITION_COLOR:Lcom/mojang/blaze3d/vertex/VertexFormat;
     582: getstatic     #237                // Field com/mojang/blaze3d/vertex/VertexFormat$DrawMode.QUADS:Lcom/mojang/blaze3d/vertex/VertexFormat$DrawMode;
     585: invokevirtual #241                // Method com/mojang/blaze3d/pipeline/RenderPipeline$Builder.withVertexFormat:(Lcom/mojang/blaze3d/vertex/VertexFormat;Lcom/mojang/blaze3d/vertex/VertexFormat$DrawMode;)Lcom/mojang/blaze3d/pipeline/RenderPipeline$Builder;
     588: invokevirtual #195                // Method com/mojang/blaze3d/pipeline/RenderPipeline$Builder.buildSnippet:()Lcom/mojang/blaze3d/pipeline/RenderPipeline$Snippet;
     591: putstatic     #327                // Field POSITION_COLOR_SNIPPET:Lcom/mojang/blaze3d/pipeline/RenderPipeline$Snippet;
     594: iconst_1
     595: anewarray     #11                 // class com/mojang/blaze3d/pipeline/RenderPipeline$Snippet
     598: dup
     599: iconst_0
     600: getstatic     #207                // Field TRANSFORMS_PROJECTION_FOG_SNIPPET:Lcom/mojang/blaze3d/pipeline/RenderPipeline$Snippet;
     603: aastore
     604: invokestatic  #177                // Method com/mojang/blaze3d/pipeline/RenderPipeline.builder:([Lcom/mojang/blaze3d/pipeline/RenderPipeline$Snippet;)Lcom/mojang/blaze3d/pipeline/RenderPipeline$Builder;
     607: ldc_w         #329                // String core/particle
     610: invokevirtual #217                // Method com/mojang/blaze3d/pipeline/RenderPipeline$Builder.withVertexShader:(Ljava/lang/String;)Lcom/mojang/blaze3d/pipeline/RenderPipeline$Builder;
     613: ldc_w         #329                // String core/particle
     616: invokevirtual #220                // Method com/mojang/blaze3d/pipeline/RenderPipeline$Builder.withFragmentShader:(Ljava/lang/String;)Lcom/mojang/blaze3d/pipeline/RenderPipeline$Builder;
     619: ldc           #222                // String Sampler0
     621: invokevirtual #225                // Method com/mojang/blaze3d/pipeline/RenderPipeline$Builder.withSampler:(Ljava/lang/String;)Lcom/mojang/blaze3d/pipeline/RenderPipeline$Builder;
     624: ldc           #227                // String Sampler2
     626: invokevirtual #225                // Method com/mojang/blaze3d/pipeline/RenderPipeline$Builder.withSampler:(Ljava/lang/String;)Lcom/mojang/blaze3d/pipeline/RenderPipeline$Builder;
     629: getstatic     #332                // Field net/minecraft/client/render/VertexFormats.POSITION_TEXTURE_COLOR_LIGHT:Lcom/mojang/blaze3d/vertex/VertexFormat;
     632: getstatic     #237                // Field com/mojang/blaze3d/vertex/VertexFormat$DrawMode.QUADS:Lcom/mojang/blaze3d/vertex/VertexFormat$DrawMode;
     635: invokevirtual #241                // Method com/mojang/blaze3d/pipeline/RenderPipeline$Builder.withVertexFormat:(Lcom/mojang/blaze3d/vertex/VertexFormat;Lcom/mojang/blaze3d/vertex/VertexFormat$DrawMode;)Lcom/mojang/blaze3d/pipeline/RenderPipeline$Builder;
     638: invokevirtual #195                // Method com/mojang/blaze3d/pipeline/RenderPipeline$Builder.buildSnippet:()Lcom/mojang/blaze3d/pipeline/RenderPipeline$Snippet;
     641: putstatic     #334                // Field PARTICLE_SNIPPET:Lcom/mojang/blaze3d/pipeline/RenderPipeline$Snippet;
     644: iconst_1
     645: anewarray     #11                 // class com/mojang/blaze3d/pipeline/RenderPipeline$Snippet
     648: dup
     649: iconst_0
     650: getstatic     #334                // Field PARTICLE_SNIPPET:Lcom/mojang/blaze3d/pipeline/RenderPipeline$Snippet;
     653: aastore
     654: invokestatic  #177                // Method com/mojang/blaze3d/pipeline/RenderPipeline.builder:([Lcom/mojang/blaze3d/pipeline/RenderPipeline$Snippet;)Lcom/mojang/blaze3d/pipeline/RenderPipeline$Builder;
     657: getstatic     #266                // Field com/mojang/blaze3d/pipeline/BlendFunction.TRANSLUCENT:Lcom/mojang/blaze3d/pipeline/BlendFunction;
     660: invokevirtual #270                // Method com/mojang/blaze3d/pipeline/RenderPipeline$Builder.withBlend:(Lcom/mojang/blaze3d/pipeline/BlendFunction;)Lcom/mojang/blaze3d/pipeline/RenderPipeline$Builder;
     663: iconst_0
     664: invokevirtual #313                // Method com/mojang/blaze3d/pipeline/RenderPipeline$Builder.withCull:(Z)Lcom/mojang/blaze3d/pipeline/RenderPipeline$Builder;
     667: invokevirtual #195                // Method com/mojang/blaze3d/pipeline/RenderPipeline$Builder.buildSnippet:()Lcom/mojang/blaze3d/pipeline/RenderPipeline$Snippet;
     670: putstatic     #336                // Field WEATHER_SNIPPET:Lcom/mojang/blaze3d/pipeline/RenderPipeline$Snippet;
     673: iconst_1
     674: anewarray     #11                 // class com/mojang/blaze3d/pipeline/RenderPipeline$Snippet
     677: dup
     678: iconst_0
     679: getstatic     #197                // Field TRANSFORMS_AND_PROJECTION_SNIPPET:Lcom/mojang/blaze3d/pipeline/RenderPipeline$Snippet;
     682: aastore
     683: invokestatic  #177                // Method com/mojang/blaze3d/pipeline/RenderPipeline.builder:([Lcom/mojang/blaze3d/pipeline/RenderPipeline$Snippet;)Lcom/mojang/blaze3d/pipeline/RenderPipeline$Builder;
     686: ldc_w         #338                // String core/gui
     689: invokevirtual #217                // Method com/mojang/blaze3d/pipeline/RenderPipeline$Builder.withVertexShader:(Ljava/lang/String;)Lcom/mojang/blaze3d/pipeline/RenderPipeline$Builder;
     692: ldc_w         #338                // String core/gui
     695: invokevirtual #220                // Method com/mojang/blaze3d/pipeline/RenderPipeline$Builder.withFragmentShader:(Ljava/lang/String;)Lcom/mojang/blaze3d/pipeline/RenderPipeline$Builder;
     698: getstatic     #266                // Field com/mojang/blaze3d/pipeline/BlendFunction.TRANSLUCENT:Lcom/mojang/blaze3d/pipeline/BlendFunction;
     701: invokevirtual #270                // Method com/mojang/blaze3d/pipeline/RenderPipeline$Builder.withBlend:(Lcom/mojang/blaze3d/pipeline/BlendFunction;)Lcom/mojang/blaze3d/pipeline/RenderPipeline$Builder;
     704: getstatic     #325                // Field net/minecraft/client/render/VertexFormats.POSITION_COLOR:Lcom/mojang/blaze3d/vertex/VertexFormat;
     707: getstatic     #237                // Field com/mojang/blaze3d/vertex/VertexFormat$DrawMode.QUADS:Lcom/mojang/blaze3d/vertex/VertexFormat$DrawMode;
     710: invokevirtual #241                // Method com/mojang/blaze3d/pipeline/RenderPipeline$Builder.withVertexFormat:(Lcom/mojang/blaze3d/vertex/VertexFormat;Lcom/mojang/blaze3d/vertex/VertexFormat$DrawMode;)Lcom/mojang/blaze3d/pipeline/RenderPipeline$Builder;
     713: invokevirtual #195                // Method com/mojang/blaze3d/pipeline/RenderPipeline$Builder.buildSnippet:()Lcom/mojang/blaze3d/pipeline/RenderPipeline$Snippet;
     716: putstatic     #340                // Field GUI_SNIPPET:Lcom/mojang/blaze3d/pipeline/RenderPipeline$Snippet;
     719: iconst_1
     720: anewarray     #11                 // class com/mojang/blaze3d/pipeline/RenderPipeline$Snippet
     723: dup
     724: iconst_0
     725: getstatic     #197                // Field TRANSFORMS_AND_PROJECTION_SNIPPET:Lcom/mojang/blaze3d/pipeline/RenderPipeline$Snippet;
     728: aastore
     729: invokestatic  #177                // Method com/mojang/blaze3d/pipeline/RenderPipeline.builder:([Lcom/mojang/blaze3d/pipeline/RenderPipeline$Snippet;)Lcom/mojang/blaze3d/pipeline/RenderPipeline$Builder;
     732: ldc_w         #342                // String core/position_tex_color
     735: invokevirtual #217                // Method com/mojang/blaze3d/pipeline/RenderPipeline$Builder.withVertexShader:(Ljava/lang/String;)Lcom/mojang/blaze3d/pipeline/RenderPipeline$Builder;
     738: ldc_w         #342                // String core/position_tex_color
     741: invokevirtual #220                // Method com/mojang/blaze3d/pipeline/RenderPipeline$Builder.withFragmentShader:(Ljava/lang/String;)Lcom/mojang/blaze3d/pipeline/RenderPipeline$Builder;
     744: ldc           #222                // String Sampler0
     746: invokevirtual #225                // Method com/mojang/blaze3d/pipeline/RenderPipeline$Builder.withSampler:(Ljava/lang/String;)Lcom/mojang/blaze3d/pipeline/RenderPipeline$Builder;
     749: getstatic     #266                // Field com/mojang/blaze3d/pipeline/BlendFunction.TRANSLUCENT:Lcom/mojang/blaze3d/pipeline/BlendFunction;
     752: invokevirtual #270                // Method com/mojang/blaze3d/pipeline/RenderPipeline$Builder.withBlend:(Lcom/mojang/blaze3d/pipeline/BlendFunction;)Lcom/mojang/blaze3d/pipeline/RenderPipeline$Builder;
     755: getstatic     #345                // Field net/minecraft/client/render/VertexFormats.POSITION_TEXTURE_COLOR:Lcom/mojang/blaze3d/vertex/VertexFormat;
     758: getstatic     #237                // Field com/mojang/blaze3d/vertex/VertexFormat$DrawMode.QUADS:Lcom/mojang/blaze3d/vertex/VertexFormat$DrawMode;
     761: invokevirtual #241                // Method com/mojang/blaze3d/pipeline/RenderPipeline$Builder.withVertexFormat:(Lcom/mojang/blaze3d/vertex/VertexFormat;Lcom/mojang/blaze3d/vertex/VertexFormat$DrawMode;)Lcom/mojang/blaze3d/pipeline/RenderPipeline$Builder;
     764: invokevirtual #195                // Method com/mojang/blaze3d/pipeline/RenderPipeline$Builder.buildSnippet:()Lcom/mojang/blaze3d/pipeline/RenderPipeline$Snippet;
     767: putstatic     #347                // Field POSITION_TEX_COLOR_SNIPPET:Lcom/mojang/blaze3d/pipeline/RenderPipeline$Snippet;
     770: iconst_1
     771: anewarray     #11                 // class com/mojang/blaze3d/pipeline/RenderPipeline$Snippet
     774: dup
     775: iconst_0
     776: getstatic     #197                // Field TRANSFORMS_AND_PROJECTION_SNIPPET:Lcom/mojang/blaze3d/pipeline/RenderPipeline$Snippet;
     779: aastore
     780: invokestatic  #177                // Method com/mojang/blaze3d/pipeline/RenderPipeline.builder:([Lcom/mojang/blaze3d/pipeline/RenderPipeline$Snippet;)Lcom/mojang/blaze3d/pipeline/RenderPipeline$Builder;
     783: ldc_w         #349                // String core/rendertype_outline
     786: invokevirtual #217                // Method com/mojang/blaze3d/pipeline/RenderPipeline$Builder.withVertexShader:(Ljava/lang/String;)Lcom/mojang/blaze3d/pipeline/RenderPipeline$Builder;
     789: ldc_w         #349                // String core/rendertype_outline
     792: invokevirtual #220                // Method com/mojang/blaze3d/pipeline/RenderPipeline$Builder.withFragmentShader:(Ljava/lang/String;)Lcom/mojang/blaze3d/pipeline/RenderPipeline$Builder;
     795: ldc           #222                // String Sampler0
     797: invokevirtual #225                // Method com/mojang/blaze3d/pipeline/RenderPipeline$Builder.withSampler:(Ljava/lang/String;)Lcom/mojang/blaze3d/pipeline/RenderPipeline$Builder;
     800: getstatic     #355                // Field com/mojang/blaze3d/platform/DepthTestFunction.NO_DEPTH_TEST:Lcom/mojang/blaze3d/platform/DepthTestFunction;
     803: invokevirtual #359                // Method com/mojang/blaze3d/pipeline/RenderPipeline$Builder.withDepthTestFunction:(Lcom/mojang/blaze3d/platform/DepthTestFunction;)Lcom/mojang/blaze3d/pipeline/RenderPipeline$Builder;
     806: iconst_0
     807: invokevirtual #362                // Method com/mojang/blaze3d/pipeline/RenderPipeline$Builder.withDepthWrite:(Z)Lcom/mojang/blaze3d/pipeline/RenderPipeline$Builder;
     810: getstatic     #345                // Field net/minecraft/client/render/VertexFormats.POSITION_TEXTURE_COLOR:Lcom/mojang/blaze3d/vertex/VertexFormat;
     813: getstatic     #237                // Field com/mojang/blaze3d/vertex/VertexFormat$DrawMode.QUADS:Lcom/mojang/blaze3d/vertex/VertexFormat$DrawMode;
     816: invokevirtual #241                // Method com/mojang/blaze3d/pipeline/RenderPipeline$Builder.withVertexFormat:(Lcom/mojang/blaze3d/vertex/VertexFormat;Lcom/mojang/blaze3d/vertex/VertexFormat$DrawMode;)Lcom/mojang/blaze3d/pipeline/RenderPipeline$Builder;
     819: invokevirtual #195                // Method com/mojang/blaze3d/pipeline/RenderPipeline$Builder.buildSnippet:()Lcom/mojang/blaze3d/pipeline/RenderPipeline$Snippet;
     822: putstatic     #364                // Field RENDERTYPE_OUTLINE_SNIPPET:Lcom/mojang/blaze3d/pipeline/RenderPipeline$Snippet;
     825: iconst_0
     826: anewarray     #11                 // class com/mojang/blaze3d/pipeline/RenderPipeline$Snippet
     829: invokestatic  #177                // Method com/mojang/blaze3d/pipeline/RenderPipeline.builder:([Lcom/mojang/blaze3d/pipeline/RenderPipeline$Snippet;)Lcom/mojang/blaze3d/pipeline/RenderPipeline$Builder;
     832: getstatic     #355                // Field com/mojang/blaze3d/platform/DepthTestFunction.NO_DEPTH_TEST:Lcom/mojang/blaze3d/platform/DepthTestFunction;
     835: invokevirtual #359                // Method com/mojang/blaze3d/pipeline/RenderPipeline$Builder.withDepthTestFunction:(Lcom/mojang/blaze3d/platform/DepthTestFunction;)Lcom/mojang/blaze3d/pipeline/RenderPipeline$Builder;
     838: iconst_0
     839: invokevirtual #362                // Method com/mojang/blaze3d/pipeline/RenderPipeline$Builder.withDepthWrite:(Z)Lcom/mojang/blaze3d/pipeline/RenderPipeline$Builder;
     842: getstatic     #282                // Field net/minecraft/client/render/VertexFormats.POSITION:Lcom/mojang/blaze3d/vertex/VertexFormat;
     845: getstatic     #237                // Field com/mojang/blaze3d/vertex/VertexFormat$DrawMode.QUADS:Lcom/mojang/blaze3d/vertex/VertexFormat$DrawMode;
     848: invokevirtual #241                // Method com/mojang/blaze3d/pipeline/RenderPipeline$Builder.withVertexFormat:(Lcom/mojang/blaze3d/vertex/VertexFormat;Lcom/mojang/blaze3d/vertex/VertexFormat$DrawMode;)Lcom/mojang/blaze3d/pipeline/RenderPipeline$Builder;
     851: ldc           #191                // String Projection
     853: getstatic     #185                // Field net/minecraft/client/gl/UniformType.UNIFORM_BUFFER:Lnet/minecraft/client/gl/UniformType;
     856: invokevirtual #189                // Method com/mojang/blaze3d/pipeline/RenderPipeline$Builder.withUniform:(Ljava/lang/String;Lnet/minecraft/client/gl/UniformType;)Lcom/mojang/blaze3d/pipeline/RenderPipeline$Builder;
     859: invokevirtual #195                // Method com/mojang/blaze3d/pipeline/RenderPipeline$Builder.buildSnippet:()Lcom/mojang/blaze3d/pipeline/RenderPipeline$Snippet;
     862: putstatic     #366                // Field POST_EFFECT_PROCESSOR_SNIPPET:Lcom/mojang/blaze3d/pipeline/RenderPipeline$Snippet;
     865: iconst_1
     866: anewarray     #11                 // class com/mojang/blaze3d/pipeline/RenderPipeline$Snippet
     869: dup
     870: iconst_0
     871: getstatic     #243                // Field TERRAIN_SNIPPET:Lcom/mojang/blaze3d/pipeline/RenderPipeline$Snippet;
     874: aastore
     875: invokestatic  #177                // Method com/mojang/blaze3d/pipeline/RenderPipeline.builder:([Lcom/mojang/blaze3d/pipeline/RenderPipeline$Snippet;)Lcom/mojang/blaze3d/pipeline/RenderPipeline$Builder;
     878: ldc_w         #368                // String pipeline/solid
     881: invokevirtual #371                // Method com/mojang/blaze3d/pipeline/RenderPipeline$Builder.withLocation:(Ljava/lang/String;)Lcom/mojang/blaze3d/pipeline/RenderPipeline$Builder;
     884: invokevirtual #375                // Method com/mojang/blaze3d/pipeline/RenderPipeline$Builder.build:()Lcom/mojang/blaze3d/pipeline/RenderPipeline;
     887: invokestatic  #377                // Method register:(Lcom/mojang/blaze3d/pipeline/RenderPipeline;)Lcom/mojang/blaze3d/pipeline/RenderPipeline;
     890: putstatic     #379                // Field SOLID:Lcom/mojang/blaze3d/pipeline/RenderPipeline;
     893: iconst_1
     894: anewarray     #11                 // class com/mojang/blaze3d/pipeline/RenderPipeline$Snippet
     897: dup
     898: iconst_0
     899: getstatic     #243                // Field TERRAIN_SNIPPET:Lcom/mojang/blaze3d/pipeline/RenderPipeline$Snippet;
     902: aastore
     903: invokestatic  #177                // Method com/mojang/blaze3d/pipeline/RenderPipeline.builder:([Lcom/mojang/blaze3d/pipeline/RenderPipeline$Snippet;)Lcom/mojang/blaze3d/pipeline/RenderPipeline$Builder;
     906: ldc_w         #381                // String pipeline/wireframe
     909: invokevirtual #371                // Method com/mojang/blaze3d/pipeline/RenderPipeline$Builder.withLocation:(Ljava/lang/String;)Lcom/mojang/blaze3d/pipeline/RenderPipeline$Builder;
     912: getstatic     #386                // Field com/mojang/blaze3d/platform/PolygonMode.WIREFRAME:Lcom/mojang/blaze3d/platform/PolygonMode;
     915: invokevirtual #390                // Method com/mojang/blaze3d/pipeline/RenderPipeline$Builder.withPolygonMode:(Lcom/mojang/blaze3d/platform/PolygonMode;)Lcom/mojang/blaze3d/pipeline/RenderPipeline$Builder;
     918: invokevirtual #375                // Method com/mojang/blaze3d/pipeline/RenderPipeline$Builder.build:()Lcom/mojang/blaze3d/pipeline/RenderPipeline;
     921: invokestatic  #377                // Method register:(Lcom/mojang/blaze3d/pipeline/RenderPipeline;)Lcom/mojang/blaze3d/pipeline/RenderPipeline;
     924: putstatic     #392                // Field WIREFRAME:Lcom/mojang/blaze3d/pipeline/RenderPipeline;
     927: iconst_1
     928: anewarray     #11                 // class com/mojang/blaze3d/pipeline/RenderPipeline$Snippet
     931: dup
     932: iconst_0
     933: getstatic     #243                // Field TERRAIN_SNIPPET:Lcom/mojang/blaze3d/pipeline/RenderPipeline$Snippet;
     936: aastore
     937: invokestatic  #177                // Method com/mojang/blaze3d/pipeline/RenderPipeline.builder:([Lcom/mojang/blaze3d/pipeline/RenderPipeline$Snippet;)Lcom/mojang/blaze3d/pipeline/RenderPipeline$Builder;
     940: ldc_w         #394                // String pipeline/cutout_mipped
     943: invokevirtual #371                // Method com/mojang/blaze3d/pipeline/RenderPipeline$Builder.withLocation:(Ljava/lang/String;)Lcom/mojang/blaze3d/pipeline/RenderPipeline$Builder;
     946: ldc_w         #396                // String ALPHA_CUTOUT
     949: ldc_w         #397                // float 0.5f
     952: invokevirtual #400                // Method com/mojang/blaze3d/pipeline/RenderPipeline$Builder.withShaderDefine:(Ljava/lang/String;F)Lcom/mojang/blaze3d/pipeline/RenderPipeline$Builder;
     955: invokevirtual #375                // Method com/mojang/blaze3d/pipeline/RenderPipeline$Builder.build:()Lcom/mojang/blaze3d/pipeline/RenderPipeline;
     958: invokestatic  #377                // Method register:(Lcom/mojang/blaze3d/pipeline/RenderPipeline;)Lcom/mojang/blaze3d/pipeline/RenderPipeline;
     961: putstatic     #402                // Field CUTOUT_MIPPED:Lcom/mojang/blaze3d/pipeline/RenderPipeline;
     964: iconst_1
     965: anewarray     #11                 // class com/mojang/blaze3d/pipeline/RenderPipeline$Snippet
     968: dup
     969: iconst_0
     970: getstatic     #243                // Field TERRAIN_SNIPPET:Lcom/mojang/blaze3d/pipeline/RenderPipeline$Snippet;
     973: aastore
     974: invokestatic  #177                // Method com/mojang/blaze3d/pipeline/RenderPipeline.builder:([Lcom/mojang/blaze3d/pipeline/RenderPipeline$Snippet;)Lcom/mojang/blaze3d/pipeline/RenderPipeline$Builder;
     977: ldc_w         #404                // String pipeline/cutout
     980: invokevirtual #371                // Method com/mojang/blaze3d/pipeline/RenderPipeline$Builder.withLocation:(Ljava/lang/String;)Lcom/mojang/blaze3d/pipeline/RenderPipeline$Builder;
     983: ldc_w         #396                // String ALPHA_CUTOUT
     986: ldc_w         #405                // float 0.1f
     989: invokevirtual #400                // Method com/mojang/blaze3d/pipeline/RenderPipeline$Builder.withShaderDefine:(Ljava/lang/String;F)Lcom/mojang/blaze3d/pipeline/RenderPipeline$Builder;
     992: invokevirtual #375                // Method com/mojang/blaze3d/pipeline/RenderPipeline$Builder.build:()Lcom/mojang/blaze3d/pipeline/RenderPipeline;
     995: invokestatic  #377                // Method register:(Lcom/mojang/blaze3d/pipeline/RenderPipeline;)Lcom/mojang/blaze3d/pipeline/RenderPipeline;
     998: putstatic     #407                // Field CUTOUT:Lcom/mojang/blaze3d/pipeline/RenderPipeline;
    1001: iconst_1
    1002: anewarray     #11                 // class com/mojang/blaze3d/pipeline/RenderPipeline$Snippet
    1005: dup
    1006: iconst_0
    1007: getstatic     #243                // Field TERRAIN_SNIPPET:Lcom/mojang/blaze3d/pipeline/RenderPipeline$Snippet;
    1010: aastore
    1011: invokestatic  #177                // Method com/mojang/blaze3d/pipeline/RenderPipeline.builder:([Lcom/mojang/blaze3d/pipeline/RenderPipeline$Snippet;)Lcom/mojang/blaze3d/pipeline/RenderPipeline$Builder;
    1014: ldc_w         #409                // String pipeline/translucent
    1017: invokevirtual #371                // Method com/mojang/blaze3d/pipeline/RenderPipeline$Builder.withLocation:(Ljava/lang/String;)Lcom/mojang/blaze3d/pipeline/RenderPipeline$Builder;
    1020: getstatic     #266                // Field com/mojang/blaze3d/pipeline/BlendFunction.TRANSLUCENT:Lcom/mojang/blaze3d/pipeline/BlendFunction;
    1023: invokevirtual #270                // Method com/mojang/blaze3d/pipeline/RenderPipeline$Builder.withBlend:(Lcom/mojang/blaze3d/pipeline/BlendFunction;)Lcom/mojang/blaze3d/pipeline/RenderPipeline$Builder;
    1026: invokevirtual #375                // Method com/mojang/blaze3d/pipeline/RenderPipeline$Builder.build:()Lcom/mojang/blaze3d/pipeline/RenderPipeline;
    1029: invokestatic  #377                // Method register:(Lcom/mojang/blaze3d/pipeline/RenderPipeline;)Lcom/mojang/blaze3d/pipeline/RenderPipeline;
    1032: putstatic     #411                // Field TRANSLUCENT:Lcom/mojang/blaze3d/pipeline/RenderPipeline;
    1035: iconst_1
    1036: anewarray     #11                 // class com/mojang/blaze3d/pipeline/RenderPipeline$Snippet
    1039: dup
    1040: iconst_0
    1041: getstatic     #243                // Field TERRAIN_SNIPPET:Lcom/mojang/blaze3d/pipeline/RenderPipeline$Snippet;
    1044: aastore
    1045: invokestatic  #177                // Method com/mojang/blaze3d/pipeline/RenderPipeline.builder:([Lcom/mojang/blaze3d/pipeline/RenderPipeline$Snippet;)Lcom/mojang/blaze3d/pipeline/RenderPipeline$Builder;
    1048: ldc_w         #413                // String pipeline/tripwire
    1051: invokevirtual #371                // Method com/mojang/blaze3d/pipeline/RenderPipeline$Builder.withLocation:(Ljava/lang/String;)Lcom/mojang/blaze3d/pipeline/RenderPipeline$Builder;
    1054: ldc_w         #396                // String ALPHA_CUTOUT
    1057: ldc_w         #405                // float 0.1f
    1060: invokevirtual #400                // Method com/mojang/blaze3d/pipeline/RenderPipeline$Builder.withShaderDefine:(Ljava/lang/String;F)Lcom/mojang/blaze3d/pipeline/RenderPipeline$Builder;
    1063: getstatic     #266                // Field com/mojang/blaze3d/pipeline/BlendFunction.TRANSLUCENT:Lcom/mojang/blaze3d/pipeline/BlendFunction;
    1066: invokevirtual #270                // Method com/mojang/blaze3d/pipeline/RenderPipeline$Builder.withBlend:(Lcom/mojang/blaze3d/pipeline/BlendFunction;)Lcom/mojang/blaze3d/pipeline/RenderPipeline$Builder;
    1069: invokevirtual #375                // Method com/mojang/blaze3d/pipeline/RenderPipeline$Builder.build:()Lcom/mojang/blaze3d/pipeline/RenderPipeline;
    1072: invokestatic  #377                // Method register:(Lcom/mojang/blaze3d/pipeline/RenderPipeline;)Lcom/mojang/blaze3d/pipeline/RenderPipeline;
    1075: putstatic     #415                // Field TRIPWIRE:Lcom/mojang/blaze3d/pipeline/RenderPipeline;
    1078: iconst_1
    1079: anewarray     #11                 // class com/mojang/blaze3d/pipeline/RenderPipeline$Snippet
    1082: dup
    1083: iconst_0
    1084: getstatic     #197                // Field TRANSFORMS_AND_PROJECTION_SNIPPET:Lcom/mojang/blaze3d/pipeline/RenderPipeline$Snippet;
    1087: aastore
    1088: invokestatic  #177                // Method com/mojang/blaze3d/pipeline/RenderPipeline.builder:([Lcom/mojang/blaze3d/pipeline/RenderPipeline$Snippet;)Lcom/mojang/blaze3d/pipeline/RenderPipeline$Builder;
    1091: ldc_w         #417                // String pipeline/translucent_moving_block
    1094: invokevirtual #371                // Method com/mojang/blaze3d/pipeline/RenderPipeline$Builder.withLocation:(Ljava/lang/String;)Lcom/mojang/blaze3d/pipeline/RenderPipeline$Builder;
    1097: ldc_w         #419                // String core/rendertype_translucent_moving_block
    1100: invokevirtual #217                // Method com/mojang/blaze3d/pipeline/RenderPipeline$Builder.withVertexShader:(Ljava/lang/String;)Lcom/mojang/blaze3d/pipeline/RenderPipeline$Builder;
    1103: ldc_w         #419                // String core/rendertype_translucent_moving_block
    1106: invokevirtual #220                // Method com/mojang/blaze3d/pipeline/RenderPipeline$Builder.withFragmentShader:(Ljava/lang/String;)Lcom/mojang/blaze3d/pipeline/RenderPipeline$Builder;
    1109: ldc           #222                // String Sampler0
    1111: invokevirtual #225                // Method com/mojang/blaze3d/pipeline/RenderPipeline$Builder.withSampler:(Ljava/lang/String;)Lcom/mojang/blaze3d/pipeline/RenderPipeline$Builder;
    1114: ldc           #227                // String Sampler2
    1116: invokevirtual #225                // Method com/mojang/blaze3d/pipeline/RenderPipeline$Builder.withSampler:(Ljava/lang/String;)Lcom/mojang/blaze3d/pipeline/RenderPipeline$Builder;
    1119: getstatic     #266                // Field com/mojang/blaze3d/pipeline/BlendFunction.TRANSLUCENT:Lcom/mojang/blaze3d/pipeline/BlendFunction;
    1122: invokevirtual #270                // Method com/mojang/blaze3d/pipeline/RenderPipeline$Builder.withBlend:(Lcom/mojang/blaze3d/pipeline/BlendFunction;)Lcom/mojang/blaze3d/pipeline/RenderPipeline$Builder;
    1125: getstatic     #233                // Field net/minecraft/client/render/VertexFormats.POSITION_COLOR_TEXTURE_LIGHT_NORMAL:Lcom/mojang/blaze3d/vertex/VertexFormat;
    1128: getstatic     #237                // Field com/mojang/blaze3d/vertex/VertexFormat$DrawMode.QUADS:Lcom/mojang/blaze3d/vertex/VertexFormat$DrawMode;
    1131: invokevirtual #241                // Method com/mojang/blaze3d/pipeline/RenderPipeline$Builder.withVertexFormat:(Lcom/mojang/blaze3d/vertex/VertexFormat;Lcom/mojang/blaze3d/vertex/VertexFormat$DrawMode;)Lcom/mojang/blaze3d/pipeline/RenderPipeline$Builder;
    1134: invokevirtual #375                // Method com/mojang/blaze3d/pipeline/RenderPipeline$Builder.build:()Lcom/mojang/blaze3d/pipeline/RenderPipeline;
    1137: invokestatic  #377                // Method register:(Lcom/mojang/blaze3d/pipeline/RenderPipeline;)Lcom/mojang/blaze3d/pipeline/RenderPipeline;
    1140: putstatic     #421                // Field RENDERTYPE_TRANSLUCENT_MOVING_BLOCK:Lcom/mojang/blaze3d/pipeline/RenderPipeline;
    1143: iconst_1
    1144: anewarray     #11                 // class com/mojang/blaze3d/pipeline/RenderPipeline$Snippet
    1147: dup
    1148: iconst_0
    1149: getstatic     #250                // Field ENTITY_SNIPPET:Lcom/mojang/blaze3d/pipeline/RenderPipeline$Snippet;
    1152: aastore
    1153: invokestatic  #177                // Method com/mojang/blaze3d/pipeline/RenderPipeline.builder:([Lcom/mojang/blaze3d/pipeline/RenderPipeline$Snippet;)Lcom/mojang/blaze3d/pipeline/RenderPipeline$Builder;
    1156: ldc_w         #423                // String pipeline/armor_cutout_no_cull
    1159: invokevirtual #371                // Method com/mojang/blaze3d/pipeline/RenderPipeline$Builder.withLocation:(Ljava/lang/String;)Lcom/mojang/blaze3d/pipeline/RenderPipeline$Builder;
    1162: ldc_w         #396                // String ALPHA_CUTOUT
    1165: ldc_w         #405                // float 0.1f
    1168: invokevirtual #400                // Method com/mojang/blaze3d/pipeline/RenderPipeline$Builder.withShaderDefine:(Ljava/lang/String;F)Lcom/mojang/blaze3d/pipeline/RenderPipeline$Builder;
    1171: ldc_w         #425                // String NO_OVERLAY
    1174: invokevirtual #255                // Method com/mojang/blaze3d/pipeline/RenderPipeline$Builder.withShaderDefine:(Ljava/lang/String;)Lcom/mojang/blaze3d/pipeline/RenderPipeline$Builder;
    1177: iconst_0
    1178: invokevirtual #313                // Method com/mojang/blaze3d/pipeline/RenderPipeline$Builder.withCull:(Z)Lcom/mojang/blaze3d/pipeline/RenderPipeline$Builder;
    1181: invokevirtual #375                // Method com/mojang/blaze3d/pipeline/RenderPipeline$Builder.build:()Lcom/mojang/blaze3d/pipeline/RenderPipeline;
    1184: invokestatic  #377                // Method register:(Lcom/mojang/blaze3d/pipeline/RenderPipeline;)Lcom/mojang/blaze3d/pipeline/RenderPipeline;
    1187: putstatic     #427                // Field ARMOR_CUTOUT_NO_CULL:Lcom/mojang/blaze3d/pipeline/RenderPipeline;
    1190: iconst_1
    1191: anewarray     #11                 // class com/mojang/blaze3d/pipeline/RenderPipeline$Snippet
    1194: dup
    1195: iconst_0
    1196: getstatic     #250                // Field ENTITY_SNIPPET:Lcom/mojang/blaze3d/pipeline/RenderPipeline$Snippet;
    1199: aastore
    1200: invokestatic  #177                // Method com/mojang/blaze3d/pipeline/RenderPipeline.builder:([Lcom/mojang/blaze3d/pipeline/RenderPipeline$Snippet;)Lcom/mojang/blaze3d/pipeline/RenderPipeline$Builder;
    1203: ldc_w         #429                // String pipeline/armor_decal_cutout_no_cull
    1206: invokevirtual #371                // Method com/mojang/blaze3d/pipeline/RenderPipeline$Builder.withLocation:(Ljava/lang/String;)Lcom/mojang/blaze3d/pipeline/RenderPipeline$Builder;
    1209: ldc_w         #396                // String ALPHA_CUTOUT
    1212: ldc_w         #405                // float 0.1f
    1215: invokevirtual #400                // Method com/mojang/blaze3d/pipeline/RenderPipeline$Builder.withShaderDefine:(Ljava/lang/String;F)Lcom/mojang/blaze3d/pipeline/RenderPipeline$Builder;
    1218: ldc_w         #425                // String NO_OVERLAY
    1221: invokevirtual #255                // Method com/mojang/blaze3d/pipeline/RenderPipeline$Builder.withShaderDefine:(Ljava/lang/String;)Lcom/mojang/blaze3d/pipeline/RenderPipeline$Builder;
    1224: iconst_0
    1225: invokevirtual #313                // Method com/mojang/blaze3d/pipeline/RenderPipeline$Builder.withCull:(Z)Lcom/mojang/blaze3d/pipeline/RenderPipeline$Builder;
    1228: getstatic     #432                // Field com/mojang/blaze3d/platform/DepthTestFunction.EQUAL_DEPTH_TEST:Lcom/mojang/blaze3d/platform/DepthTestFunction;
    1231: invokevirtual #359                // Method com/mojang/blaze3d/pipeline/RenderPipeline$Builder.withDepthTestFunction:(Lcom/mojang/blaze3d/platform/DepthTestFunction;)Lcom/mojang/blaze3d/pipeline/RenderPipeline$Builder;
    1234: invokevirtual #375                // Method com/mojang/blaze3d/pipeline/RenderPipeline$Builder.build:()Lcom/mojang/blaze3d/pipeline/RenderPipeline;
    1237: invokestatic  #377                // Method register:(Lcom/mojang/blaze3d/pipeline/RenderPipeline;)Lcom/mojang/blaze3d/pipeline/RenderPipeline;
    1240: putstatic     #434                // Field ARMOR_DECAL_CUTOUT_NO_CULL:Lcom/mojang/blaze3d/pipeline/RenderPipeline;
    1243: iconst_1
    1244: anewarray     #11                 // class com/mojang/blaze3d/pipeline/RenderPipeline$Snippet
    1247: dup
    1248: iconst_0
    1249: getstatic     #250                // Field ENTITY_SNIPPET:Lcom/mojang/blaze3d/pipeline/RenderPipeline$Snippet;
    1252: aastore
    1253: invokestatic  #177                // Method com/mojang/blaze3d/pipeline/RenderPipeline.builder:([Lcom/mojang/blaze3d/pipeline/RenderPipeline$Snippet;)Lcom/mojang/blaze3d/pipeline/RenderPipeline$Builder;
    1256: ldc_w         #436                // String pipeline/armor_translucent
    1259: invokevirtual #371                // Method com/mojang/blaze3d/pipeline/RenderPipeline$Builder.withLocation:(Ljava/lang/String;)Lcom/mojang/blaze3d/pipeline/RenderPipeline$Builder;
    1262: ldc_w         #396                // String ALPHA_CUTOUT
    1265: ldc_w         #405                // float 0.1f
    1268: invokevirtual #400                // Method com/mojang/blaze3d/pipeline/RenderPipeline$Builder.withShaderDefine:(Ljava/lang/String;F)Lcom/mojang/blaze3d/pipeline/RenderPipeline$Builder;
    1271: ldc_w         #425                // String NO_OVERLAY
    1274: invokevirtual #255                // Method com/mojang/blaze3d/pipeline/RenderPipeline$Builder.withShaderDefine:(Ljava/lang/String;)Lcom/mojang/blaze3d/pipeline/RenderPipeline$Builder;
    1277: getstatic     #266                // Field com/mojang/blaze3d/pipeline/BlendFunction.TRANSLUCENT:Lcom/mojang/blaze3d/pipeline/BlendFunction;
    1280: invokevirtual #270                // Method com/mojang/blaze3d/pipeline/RenderPipeline$Builder.withBlend:(Lcom/mojang/blaze3d/pipeline/BlendFunction;)Lcom/mojang/blaze3d/pipeline/RenderPipeline$Builder;
    1283: iconst_0
    1284: invokevirtual #313                // Method com/mojang/blaze3d/pipeline/RenderPipeline$Builder.withCull:(Z)Lcom/mojang/blaze3d/pipeline/RenderPipeline$Builder;
    1287: invokevirtual #375                // Method com/mojang/blaze3d/pipeline/RenderPipeline$Builder.build:()Lcom/mojang/blaze3d/pipeline/RenderPipeline;
    1290: invokestatic  #377                // Method register:(Lcom/mojang/blaze3d/pipeline/RenderPipeline;)Lcom/mojang/blaze3d/pipeline/RenderPipeline;
    1293: putstatic     #438                // Field ARMOR_TRANSLUCENT:Lcom/mojang/blaze3d/pipeline/RenderPipeline;
    1296: iconst_1
    1297: anewarray     #11                 // class com/mojang/blaze3d/pipeline/RenderPipeline$Snippet
    1300: dup
    1301: iconst_0
    1302: getstatic     #250                // Field ENTITY_SNIPPET:Lcom/mojang/blaze3d/pipeline/RenderPipeline$Snippet;
    1305: aastore
    1306: invokestatic  #177                // Method com/mojang/blaze3d/pipeline/RenderPipeline.builder:([Lcom/mojang/blaze3d/pipeline/RenderPipeline$Snippet;)Lcom/mojang/blaze3d/pipeline/RenderPipeline$Builder;
    1309: ldc_w         #440                // String pipeline/entity_solid
    1312: invokevirtual #371                // Method com/mojang/blaze3d/pipeline/RenderPipeline$Builder.withLocation:(Ljava/lang/String;)Lcom/mojang/blaze3d/pipeline/RenderPipeline$Builder;
    1315: ldc_w         #279                // String Sampler1
    1318: invokevirtual #225                // Method com/mojang/blaze3d/pipeline/RenderPipeline$Builder.withSampler:(Ljava/lang/String;)Lcom/mojang/blaze3d/pipeline/RenderPipeline$Builder;
    1321: invokevirtual #375                // Method com/mojang/blaze3d/pipeline/RenderPipeline$Builder.build:()Lcom/mojang/blaze3d/pipeline/RenderPipeline;
    1324: invokestatic  #377                // Method register:(Lcom/mojang/blaze3d/pipeline/RenderPipeline;)Lcom/mojang/blaze3d/pipeline/RenderPipeline;
    1327: putstatic     #442                // Field ENTITY_SOLID:Lcom/mojang/blaze3d/pipeline/RenderPipeline;
    1330: iconst_1
    1331: anewarray     #11                 // class com/mojang/blaze3d/pipeline/RenderPipeline$Snippet
    1334: dup
    1335: iconst_0
    1336: getstatic     #250                // Field ENTITY_SNIPPET:Lcom/mojang/blaze3d/pipeline/RenderPipeline$Snippet;
    1339: aastore
    1340: invokestatic  #177                // Method com/mojang/blaze3d/pipeline/RenderPipeline.builder:([Lcom/mojang/blaze3d/pipeline/RenderPipeline$Snippet;)Lcom/mojang/blaze3d/pipeline/RenderPipeline$Builder;
    1343: ldc_w         #444                // String pipeline/entity_solid_offset_forward
    1346: invokevirtual #371                // Method com/mojang/blaze3d/pipeline/RenderPipeline$Builder.withLocation:(Ljava/lang/String;)Lcom/mojang/blaze3d/pipeline/RenderPipeline$Builder;
    1349: ldc_w         #279                // String Sampler1
    1352: invokevirtual #225                // Method com/mojang/blaze3d/pipeline/RenderPipeline$Builder.withSampler:(Ljava/lang/String;)Lcom/mojang/blaze3d/pipeline/RenderPipeline$Builder;
    1355: invokevirtual #375                // Method com/mojang/blaze3d/pipeline/RenderPipeline$Builder.build:()Lcom/mojang/blaze3d/pipeline/RenderPipeline;
    1358: invokestatic  #377                // Method register:(Lcom/mojang/blaze3d/pipeline/RenderPipeline;)Lcom/mojang/blaze3d/pipeline/RenderPipeline;
    1361: putstatic     #446                // Field ENTITY_SOLID_OFFSET_FORWARD:Lcom/mojang/blaze3d/pipeline/RenderPipeline;
    1364: iconst_1
    1365: anewarray     #11                 // class com/mojang/blaze3d/pipeline/RenderPipeline$Snippet
    1368: dup
    1369: iconst_0
    1370: getstatic     #250                // Field ENTITY_SNIPPET:Lcom/mojang/blaze3d/pipeline/RenderPipeline$Snippet;
    1373: aastore
    1374: invokestatic  #177                // Method com/mojang/blaze3d/pipeline/RenderPipeline.builder:([Lcom/mojang/blaze3d/pipeline/RenderPipeline$Snippet;)Lcom/mojang/blaze3d/pipeline/RenderPipeline$Builder;
    1377: ldc_w         #448                // String pipeline/entity_cutout
    1380: invokevirtual #371                // Method com/mojang/blaze3d/pipeline/RenderPipeline$Builder.withLocation:(Ljava/lang/String;)Lcom/mojang/blaze3d/pipeline/RenderPipeline$Builder;
    1383: ldc_w         #396                // String ALPHA_CUTOUT
    1386: ldc_w         #405                // float 0.1f
    1389: invokevirtual #400                // Method com/mojang/blaze3d/pipeline/RenderPipeline$Builder.withShaderDefine:(Ljava/lang/String;F)Lcom/mojang/blaze3d/pipeline/RenderPipeline$Builder;
    1392: ldc_w         #279                // String Sampler1
    1395: invokevirtual #225                // Method com/mojang/blaze3d/pipeline/RenderPipeline$Builder.withSampler:(Ljava/lang/String;)Lcom/mojang/blaze3d/pipeline/RenderPipeline$Builder;
    1398: invokevirtual #375                // Method com/mojang/blaze3d/pipeline/RenderPipeline$Builder.build:()Lcom/mojang/blaze3d/pipeline/RenderPipeline;
    1401: invokestatic  #377                // Method register:(Lcom/mojang/blaze3d/pipeline/RenderPipeline;)Lcom/mojang/blaze3d/pipeline/RenderPipeline;
    1404: putstatic     #450                // Field ENTITY_CUTOUT:Lcom/mojang/blaze3d/pipeline/RenderPipeline;
    1407: iconst_1
    1408: anewarray     #11                 // class com/mojang/blaze3d/pipeline/RenderPipeline$Snippet
    1411: dup
    1412: iconst_0
    1413: getstatic     #250                // Field ENTITY_SNIPPET:Lcom/mojang/blaze3d/pipeline/RenderPipeline$Snippet;
    1416: aastore
    1417: invokestatic  #177                // Method com/mojang/blaze3d/pipeline/RenderPipeline.builder:([Lcom/mojang/blaze3d/pipeline/RenderPipeline$Snippet;)Lcom/mojang/blaze3d/pipeline/RenderPipeline$Builder;
    1420: ldc_w         #452                // String pipeline/entity_cutout_no_cull
    1423: invokevirtual #371                // Method com/mojang/blaze3d/pipeline/RenderPipeline$Builder.withLocation:(Ljava/lang/String;)Lcom/mojang/blaze3d/pipeline/RenderPipeline$Builder;
    1426: ldc_w         #396                // String ALPHA_CUTOUT
    1429: ldc_w         #405                // float 0.1f
    1432: invokevirtual #400                // Method com/mojang/blaze3d/pipeline/RenderPipeline$Builder.withShaderDefine:(Ljava/lang/String;F)Lcom/mojang/blaze3d/pipeline/RenderPipeline$Builder;
    1435: ldc_w         #279                // String Sampler1
    1438: invokevirtual #225                // Method com/mojang/blaze3d/pipeline/RenderPipeline$Builder.withSampler:(Ljava/lang/String;)Lcom/mojang/blaze3d/pipeline/RenderPipeline$Builder;
    1441: iconst_0
    1442: invokevirtual #313                // Method com/mojang/blaze3d/pipeline/RenderPipeline$Builder.withCull:(Z)Lcom/mojang/blaze3d/pipeline/RenderPipeline$Builder;
    1445: invokevirtual #375                // Method com/mojang/blaze3d/pipeline/RenderPipeline$Builder.build:()Lcom/mojang/blaze3d/pipeline/RenderPipeline;
    1448: invokestatic  #377                // Method register:(Lcom/mojang/blaze3d/pipeline/RenderPipeline;)Lcom/mojang/blaze3d/pipeline/RenderPipeline;
    1451: putstatic     #454                // Field ENTITY_CUTOUT_NO_CULL:Lcom/mojang/blaze3d/pipeline/RenderPipeline;
    1454: iconst_1
    1455: anewarray     #11                 // class com/mojang/blaze3d/pipeline/RenderPipeline$Snippet
    1458: dup
    1459: iconst_0
    1460: getstatic     #250                // Field ENTITY_SNIPPET:Lcom/mojang/blaze3d/pipeline/RenderPipeline$Snippet;
    1463: aastore
    1464: invokestatic  #177                // Method com/mojang/blaze3d/pipeline/RenderPipeline.builder:([Lcom/mojang/blaze3d/pipeline/RenderPipeline$Snippet;)Lcom/mojang/blaze3d/pipeline/RenderPipeline$Builder;
    1467: ldc_w         #456                // String pipeline/entity_cutout_no_cull_z_offset
    1470: invokevirtual #371                // Method com/mojang/blaze3d/pipeline/RenderPipeline$Builder.withLocation:(Ljava/lang/String;)Lcom/mojang/blaze3d/pipeline/RenderPipeline$Builder;
    1473: ldc_w         #396                // String ALPHA_CUTOUT
    1476: ldc_w         #405                // float 0.1f
    1479: invokevirtual #400                // Method com/mojang/blaze3d/pipeline/RenderPipeline$Builder.withShaderDefine:(Ljava/lang/String;F)Lcom/mojang/blaze3d/pipeline/RenderPipeline$Builder;
    1482: ldc_w         #279                // String Sampler1
    1485: invokevirtual #225                // Method com/mojang/blaze3d/pipeline/RenderPipeline$Builder.withSampler:(Ljava/lang/String;)Lcom/mojang/blaze3d/pipeline/RenderPipeline$Builder;
    1488: iconst_0
    1489: invokevirtual #313                // Method com/mojang/blaze3d/pipeline/RenderPipeline$Builder.withCull:(Z)Lcom/mojang/blaze3d/pipeline/RenderPipeline$Builder;
    1492: invokevirtual #375                // Method com/mojang/blaze3d/pipeline/RenderPipeline$Builder.build:()Lcom/mojang/blaze3d/pipeline/RenderPipeline;
    1495: invokestatic  #377                // Method register:(Lcom/mojang/blaze3d/pipeline/RenderPipeline;)Lcom/mojang/blaze3d/pipeline/RenderPipeline;
    1498: putstatic     #458                // Field ENTITY_CUTOUT_NO_CULL_Z_OFFSET:Lcom/mojang/blaze3d/pipeline/RenderPipeline;
    1501: iconst_1
    1502: anewarray     #11                 // class com/mojang/blaze3d/pipeline/RenderPipeline$Snippet
    1505: dup
    1506: iconst_0
    1507: getstatic     #250                // Field ENTITY_SNIPPET:Lcom/mojang/blaze3d/pipeline/RenderPipeline$Snippet;
    1510: aastore
    1511: invokestatic  #177                // Method com/mojang/blaze3d/pipeline/RenderPipeline.builder:([Lcom/mojang/blaze3d/pipeline/RenderPipeline$Snippet;)Lcom/mojang/blaze3d/pipeline/RenderPipeline$Builder;
    1514: ldc_w         #460                // String pipeline/entity_translucent
    1517: invokevirtual #371                // Method com/mojang/blaze3d/pipeline/RenderPipeline$Builder.withLocation:(Ljava/lang/String;)Lcom/mojang/blaze3d/pipeline/RenderPipeline$Builder;
    1520: ldc_w         #396                // String ALPHA_CUTOUT
    1523: ldc_w         #405                // float 0.1f
    1526: invokevirtual #400                // Method com/mojang/blaze3d/pipeline/RenderPipeline$Builder.withShaderDefine:(Ljava/lang/String;F)Lcom/mojang/blaze3d/pipeline/RenderPipeline$Builder;
    1529: ldc_w         #279                // String Sampler1
    1532: invokevirtual #225                // Method com/mojang/blaze3d/pipeline/RenderPipeline$Builder.withSampler:(Ljava/lang/String;)Lcom/mojang/blaze3d/pipeline/RenderPipeline$Builder;
    1535: getstatic     #266                // Field com/mojang/blaze3d/pipeline/BlendFunction.TRANSLUCENT:Lcom/mojang/blaze3d/pipeline/BlendFunction;
    1538: invokevirtual #270                // Method com/mojang/blaze3d/pipeline/RenderPipeline$Builder.withBlend:(Lcom/mojang/blaze3d/pipeline/BlendFunction;)Lcom/mojang/blaze3d/pipeline/RenderPipeline$Builder;
    1541: iconst_0
    1542: invokevirtual #313                // Method com/mojang/blaze3d/pipeline/RenderPipeline$Builder.withCull:(Z)Lcom/mojang/blaze3d/pipeline/RenderPipeline$Builder;
    1545: invokevirtual #375                // Method com/mojang/blaze3d/pipeline/RenderPipeline$Builder.build:()Lcom/mojang/blaze3d/pipeline/RenderPipeline;
    1548: invokestatic  #377                // Method register:(Lcom/mojang/blaze3d/pipeline/RenderPipeline;)Lcom/mojang/blaze3d/pipeline/RenderPipeline;
    1551: putstatic     #462                // Field ENTITY_TRANSLUCENT:Lcom/mojang/blaze3d/pipeline/RenderPipeline;
    1554: iconst_1
    1555: anewarray     #11                 // class com/mojang/blaze3d/pipeline/RenderPipeline$Snippet
    1558: dup
    1559: iconst_0
    1560: getstatic     #257                // Field ENTITY_EMISSIVE_SNIPPET:Lcom/mojang/blaze3d/pipeline/RenderPipeline$Snippet;
    1563: aastore
    1564: invokestatic  #177                // Method com/mojang/blaze3d/pipeline/RenderPipeline.builder:([Lcom/mojang/blaze3d/pipeline/RenderPipeline$Snippet;)Lcom/mojang/blaze3d/pipeline/RenderPipeline$Builder;
    1567: ldc_w         #464                // String pipeline/entity_translucent_emissive
    1570: invokevirtual #371                // Method com/mojang/blaze3d/pipeline/RenderPipeline$Builder.withLocation:(Ljava/lang/String;)Lcom/mojang/blaze3d/pipeline/RenderPipeline$Builder;
    1573: ldc_w         #396                // String ALPHA_CUTOUT
    1576: ldc_w         #405                // float 0.1f
    1579: invokevirtual #400                // Method com/mojang/blaze3d/pipeline/RenderPipeline$Builder.withShaderDefine:(Ljava/lang/String;F)Lcom/mojang/blaze3d/pipeline/RenderPipeline$Builder;
    1582: ldc_w         #279                // String Sampler1
    1585: invokevirtual #225                // Method com/mojang/blaze3d/pipeline/RenderPipeline$Builder.withSampler:(Ljava/lang/String;)Lcom/mojang/blaze3d/pipeline/RenderPipeline$Builder;
    1588: getstatic     #266                // Field com/mojang/blaze3d/pipeline/BlendFunction.TRANSLUCENT:Lcom/mojang/blaze3d/pipeline/BlendFunction;
    1591: invokevirtual #270                // Method com/mojang/blaze3d/pipeline/RenderPipeline$Builder.withBlend:(Lcom/mojang/blaze3d/pipeline/BlendFunction;)Lcom/mojang/blaze3d/pipeline/RenderPipeline$Builder;
    1594: iconst_0
    1595: invokevirtual #313                // Method com/mojang/blaze3d/pipeline/RenderPipeline$Builder.withCull:(Z)Lcom/mojang/blaze3d/pipeline/RenderPipeline$Builder;
    1598: iconst_0
    1599: invokevirtual #362                // Method com/mojang/blaze3d/pipeline/RenderPipeline$Builder.withDepthWrite:(Z)Lcom/mojang/blaze3d/pipeline/RenderPipeline$Builder;
    1602: invokevirtual #375                // Method com/mojang/blaze3d/pipeline/RenderPipeline$Builder.build:()Lcom/mojang/blaze3d/pipeline/RenderPipeline;
    1605: invokestatic  #377                // Method register:(Lcom/mojang/blaze3d/pipeline/RenderPipeline;)Lcom/mojang/blaze3d/pipeline/RenderPipeline;
    1608: putstatic     #466                // Field ENTITY_TRANSLUCENT_EMISSIVE:Lcom/mojang/blaze3d/pipeline/RenderPipeline;
    1611: iconst_1
    1612: anewarray     #11                 // class com/mojang/blaze3d/pipeline/RenderPipeline$Snippet
    1615: dup
    1616: iconst_0
    1617: getstatic     #250                // Field ENTITY_SNIPPET:Lcom/mojang/blaze3d/pipeline/RenderPipeline$Snippet;
    1620: aastore
    1621: invokestatic  #177                // Method com/mojang/blaze3d/pipeline/RenderPipeline.builder:([Lcom/mojang/blaze3d/pipeline/RenderPipeline$Snippet;)Lcom/mojang/blaze3d/pipeline/RenderPipeline$Builder;
    1624: ldc_w         #468                // String pipeline/entity_smooth_cutout
    1627: invokevirtual #371                // Method com/mojang/blaze3d/pipeline/RenderPipeline$Builder.withLocation:(Ljava/lang/String;)Lcom/mojang/blaze3d/pipeline/RenderPipeline$Builder;
    1630: ldc_w         #396                // String ALPHA_CUTOUT
    1633: ldc_w         #405                // float 0.1f
    1636: invokevirtual #400                // Method com/mojang/blaze3d/pipeline/RenderPipeline$Builder.withShaderDefine:(Ljava/lang/String;F)Lcom/mojang/blaze3d/pipeline/RenderPipeline$Builder;
    1639: ldc_w         #279                // String Sampler1
    1642: invokevirtual #225                // Method com/mojang/blaze3d/pipeline/RenderPipeline$Builder.withSampler:(Ljava/lang/String;)Lcom/mojang/blaze3d/pipeline/RenderPipeline$Builder;
    1645: iconst_0
    1646: invokevirtual #313                // Method com/mojang/blaze3d/pipeline/RenderPipeline$Builder.withCull:(Z)Lcom/mojang/blaze3d/pipeline/RenderPipeline$Builder;
    1649: invokevirtual #375                // Method com/mojang/blaze3d/pipeline/RenderPipeline$Builder.build:()Lcom/mojang/blaze3d/pipeline/RenderPipeline;
    1652: invokestatic  #377                // Method register:(Lcom/mojang/blaze3d/pipeline/RenderPipeline;)Lcom/mojang/blaze3d/pipeline/RenderPipeline;
    1655: putstatic     #470                // Field ENTITY_SMOOTH_CUTOUT:Lcom/mojang/blaze3d/pipeline/RenderPipeline;
    1658: iconst_1
    1659: anewarray     #11                 // class com/mojang/blaze3d/pipeline/RenderPipeline$Snippet
    1662: dup
    1663: iconst_0
    1664: getstatic     #250                // Field ENTITY_SNIPPET:Lcom/mojang/blaze3d/pipeline/RenderPipeline$Snippet;
    1667: aastore
    1668: invokestatic  #177                // Method com/mojang/blaze3d/pipeline/RenderPipeline.builder:([Lcom/mojang/blaze3d/pipeline/RenderPipeline$Snippet;)Lcom/mojang/blaze3d/pipeline/RenderPipeline$Builder;
    1671: ldc_w         #472                // String pipeline/entity_no_outline
    1674: invokevirtual #371                // Method com/mojang/blaze3d/pipeline/RenderPipeline$Builder.withLocation:(Ljava/lang/String;)Lcom/mojang/blaze3d/pipeline/RenderPipeline$Builder;
    1677: ldc_w         #425                // String NO_OVERLAY
    1680: invokevirtual #255                // Method com/mojang/blaze3d/pipeline/RenderPipeline$Builder.withShaderDefine:(Ljava/lang/String;)Lcom/mojang/blaze3d/pipeline/RenderPipeline$Builder;
    1683: getstatic     #266                // Field com/mojang/blaze3d/pipeline/BlendFunction.TRANSLUCENT:Lcom/mojang/blaze3d/pipeline/BlendFunction;
    1686: invokevirtual #270                // Method com/mojang/blaze3d/pipeline/RenderPipeline$Builder.withBlend:(Lcom/mojang/blaze3d/pipeline/BlendFunction;)Lcom/mojang/blaze3d/pipeline/RenderPipeline$Builder;
    1689: iconst_0
    1690: invokevirtual #313                // Method com/mojang/blaze3d/pipeline/RenderPipeline$Builder.withCull:(Z)Lcom/mojang/blaze3d/pipeline/RenderPipeline$Builder;
    1693: iconst_0
    1694: invokevirtual #362                // Method com/mojang/blaze3d/pipeline/RenderPipeline$Builder.withDepthWrite:(Z)Lcom/mojang/blaze3d/pipeline/RenderPipeline$Builder;
    1697: invokevirtual #375                // Method com/mojang/blaze3d/pipeline/RenderPipeline$Builder.build:()Lcom/mojang/blaze3d/pipeline/RenderPipeline;
    1700: invokestatic  #377                // Method register:(Lcom/mojang/blaze3d/pipeline/RenderPipeline;)Lcom/mojang/blaze3d/pipeline/RenderPipeline;
    1703: putstatic     #474                // Field ENTITY_NO_OUTLINE:Lcom/mojang/blaze3d/pipeline/RenderPipeline;
    1706: iconst_1
    1707: anewarray     #11                 // class com/mojang/blaze3d/pipeline/RenderPipeline$Snippet
    1710: dup
    1711: iconst_0
    1712: getstatic     #250                // Field ENTITY_SNIPPET:Lcom/mojang/blaze3d/pipeline/RenderPipeline$Snippet;
    1715: aastore
    1716: invokestatic  #177                // Method com/mojang/blaze3d/pipeline/RenderPipeline.builder:([Lcom/mojang/blaze3d/pipeline/RenderPipeline$Snippet;)Lcom/mojang/blaze3d/pipeline/RenderPipeline$Builder;
    1719: ldc_w         #476                // String pipeline/breeze_wind
    1722: invokevirtual #371                // Method com/mojang/blaze3d/pipeline/RenderPipeline$Builder.withLocation:(Ljava/lang/String;)Lcom/mojang/blaze3d/pipeline/RenderPipeline$Builder;
    1725: ldc_w         #396                // String ALPHA_CUTOUT
    1728: ldc_w         #405                // float 0.1f
    1731: invokevirtual #400                // Method com/mojang/blaze3d/pipeline/RenderPipeline$Builder.withShaderDefine:(Ljava/lang/String;F)Lcom/mojang/blaze3d/pipeline/RenderPipeline$Builder;
    1734: ldc_w         #478                // String APPLY_TEXTURE_MATRIX
    1737: invokevirtual #255                // Method com/mojang/blaze3d/pipeline/RenderPipeline$Builder.withShaderDefine:(Ljava/lang/String;)Lcom/mojang/blaze3d/pipeline/RenderPipeline$Builder;
    1740: ldc_w         #425                // String NO_OVERLAY
    1743: invokevirtual #255                // Method com/mojang/blaze3d/pipeline/RenderPipeline$Builder.withShaderDefine:(Ljava/lang/String;)Lcom/mojang/blaze3d/pipeline/RenderPipeline$Builder;
    1746: ldc_w         #480                // String NO_CARDINAL_LIGHTING
    1749: invokevirtual #255                // Method com/mojang/blaze3d/pipeline/RenderPipeline$Builder.withShaderDefine:(Ljava/lang/String;)Lcom/mojang/blaze3d/pipeline/RenderPipeline$Builder;
    1752: getstatic     #266                // Field com/mojang/blaze3d/pipeline/BlendFunction.TRANSLUCENT:Lcom/mojang/blaze3d/pipeline/BlendFunction;
    1755: invokevirtual #270                // Method com/mojang/blaze3d/pipeline/RenderPipeline$Builder.withBlend:(Lcom/mojang/blaze3d/pipeline/BlendFunction;)Lcom/mojang/blaze3d/pipeline/RenderPipeline$Builder;
    1758: iconst_0
    1759: invokevirtual #313                // Method com/mojang/blaze3d/pipeline/RenderPipeline$Builder.withCull:(Z)Lcom/mojang/blaze3d/pipeline/RenderPipeline$Builder;
    1762: invokevirtual #375                // Method com/mojang/blaze3d/pipeline/RenderPipeline$Builder.build:()Lcom/mojang/blaze3d/pipeline/RenderPipeline;
    1765: invokestatic  #377                // Method register:(Lcom/mojang/blaze3d/pipeline/RenderPipeline;)Lcom/mojang/blaze3d/pipeline/RenderPipeline;
    1768: putstatic     #482                // Field BREEZE_WIND:Lcom/mojang/blaze3d/pipeline/RenderPipeline;
    1771: iconst_1
    1772: anewarray     #11                 // class com/mojang/blaze3d/pipeline/RenderPipeline$Snippet
    1775: dup
    1776: iconst_0
    1777: getstatic     #207                // Field TRANSFORMS_PROJECTION_FOG_SNIPPET:Lcom/mojang/blaze3d/pipeline/RenderPipeline$Snippet;
    1780: aastore
    1781: invokestatic  #177                // Method com/mojang/blaze3d/pipeline/RenderPipeline.builder:([Lcom/mojang/blaze3d/pipeline/RenderPipeline$Snippet;)Lcom/mojang/blaze3d/pipeline/RenderPipeline$Builder;
    1784: ldc_w         #484                // String pipeline/energy_swirl
    1787: invokevirtual #371                // Method com/mojang/blaze3d/pipeline/RenderPipeline$Builder.withLocation:(Ljava/lang/String;)Lcom/mojang/blaze3d/pipeline/RenderPipeline$Builder;
    1790: ldc           #245                // String core/entity
    1792: invokevirtual #217                // Method com/mojang/blaze3d/pipeline/RenderPipeline$Builder.withVertexShader:(Ljava/lang/String;)Lcom/mojang/blaze3d/pipeline/RenderPipeline$Builder;
    1795: ldc           #245                // String core/entity
    1797: invokevirtual #220                // Method com/mojang/blaze3d/pipeline/RenderPipeline$Builder.withFragmentShader:(Ljava/lang/String;)Lcom/mojang/blaze3d/pipeline/RenderPipeline$Builder;
    1800: ldc_w         #396                // String ALPHA_CUTOUT
    1803: ldc_w         #405                // float 0.1f
    1806: invokevirtual #400                // Method com/mojang/blaze3d/pipeline/RenderPipeline$Builder.withShaderDefine:(Ljava/lang/String;F)Lcom/mojang/blaze3d/pipeline/RenderPipeline$Builder;
    1809: ldc           #252                // String EMISSIVE
    1811: invokevirtual #255                // Method com/mojang/blaze3d/pipeline/RenderPipeline$Builder.withShaderDefine:(Ljava/lang/String;)Lcom/mojang/blaze3d/pipeline/RenderPipeline$Builder;
    1814: ldc_w         #425                // String NO_OVERLAY
    1817: invokevirtual #255                // Method com/mojang/blaze3d/pipeline/RenderPipeline$Builder.withShaderDefine:(Ljava/lang/String;)Lcom/mojang/blaze3d/pipeline/RenderPipeline$Builder;
    1820: ldc_w         #480                // String NO_CARDINAL_LIGHTING
    1823: invokevirtual #255                // Method com/mojang/blaze3d/pipeline/RenderPipeline$Builder.withShaderDefine:(Ljava/lang/String;)Lcom/mojang/blaze3d/pipeline/RenderPipeline$Builder;
    1826: ldc_w         #478                // String APPLY_TEXTURE_MATRIX
    1829: invokevirtual #255                // Method com/mojang/blaze3d/pipeline/RenderPipeline$Builder.withShaderDefine:(Ljava/lang/String;)Lcom/mojang/blaze3d/pipeline/RenderPipeline$Builder;
    1832: ldc           #222                // String Sampler0
    1834: invokevirtual #225                // Method com/mojang/blaze3d/pipeline/RenderPipeline$Builder.withSampler:(Ljava/lang/String;)Lcom/mojang/blaze3d/pipeline/RenderPipeline$Builder;
    1837: getstatic     #487                // Field com/mojang/blaze3d/pipeline/BlendFunction.ADDITIVE:Lcom/mojang/blaze3d/pipeline/BlendFunction;
    1840: invokevirtual #270                // Method com/mojang/blaze3d/pipeline/RenderPipeline$Builder.withBlend:(Lcom/mojang/blaze3d/pipeline/BlendFunction;)Lcom/mojang/blaze3d/pipeline/RenderPipeline$Builder;
    1843: iconst_0
    1844: invokevirtual #313                // Method com/mojang/blaze3d/pipeline/RenderPipeline$Builder.withCull:(Z)Lcom/mojang/blaze3d/pipeline/RenderPipeline$Builder;
    1847: getstatic     #248                // Field net/minecraft/client/render/VertexFormats.POSITION_COLOR_TEXTURE_OVERLAY_LIGHT_NORMAL:Lcom/mojang/blaze3d/vertex/VertexFormat;
    1850: getstatic     #237                // Field com/mojang/blaze3d/vertex/VertexFormat$DrawMode.QUADS:Lcom/mojang/blaze3d/vertex/VertexFormat$DrawMode;
    1853: invokevirtual #241                // Method com/mojang/blaze3d/pipeline/RenderPipeline$Builder.withVertexFormat:(Lcom/mojang/blaze3d/vertex/VertexFormat;Lcom/mojang/blaze3d/vertex/VertexFormat$DrawMode;)Lcom/mojang/blaze3d/pipeline/RenderPipeline$Builder;
    1856: invokevirtual #375                // Method com/mojang/blaze3d/pipeline/RenderPipeline$Builder.build:()Lcom/mojang/blaze3d/pipeline/RenderPipeline;
    1859: invokestatic  #377                // Method register:(Lcom/mojang/blaze3d/pipeline/RenderPipeline;)Lcom/mojang/blaze3d/pipeline/RenderPipeline;
    1862: putstatic     #489                // Field ENTITY_ENERGY_SWIRL:Lcom/mojang/blaze3d/pipeline/RenderPipeline;
    1865: iconst_1
    1866: anewarray     #11                 // class com/mojang/blaze3d/pipeline/RenderPipeline$Snippet
    1869: dup
    1870: iconst_0
    1871: getstatic     #207                // Field TRANSFORMS_PROJECTION_FOG_SNIPPET:Lcom/mojang/blaze3d/pipeline/RenderPipeline$Snippet;
    1874: aastore
    1875: invokestatic  #177                // Method com/mojang/blaze3d/pipeline/RenderPipeline.builder:([Lcom/mojang/blaze3d/pipeline/RenderPipeline$Snippet;)Lcom/mojang/blaze3d/pipeline/RenderPipeline$Builder;
    1878: ldc_w         #491                // String pipeline/eyes
    1881: invokevirtual #371                // Method com/mojang/blaze3d/pipeline/RenderPipeline$Builder.withLocation:(Ljava/lang/String;)Lcom/mojang/blaze3d/pipeline/RenderPipeline$Builder;
    1884: ldc           #245                // String core/entity
    1886: invokevirtual #217                // Method com/mojang/blaze3d/pipeline/RenderPipeline$Builder.withVertexShader:(Ljava/lang/String;)Lcom/mojang/blaze3d/pipeline/RenderPipeline$Builder;
    1889: ldc           #245                // String core/entity
    1891: invokevirtual #220                // Method com/mojang/blaze3d/pipeline/RenderPipeline$Builder.withFragmentShader:(Ljava/lang/String;)Lcom/mojang/blaze3d/pipeline/RenderPipeline$Builder;
    1894: ldc           #252                // String EMISSIVE
    1896: invokevirtual #255                // Method com/mojang/blaze3d/pipeline/RenderPipeline$Builder.withShaderDefine:(Ljava/lang/String;)Lcom/mojang/blaze3d/pipeline/RenderPipeline$Builder;
    1899: ldc_w         #425                // String NO_OVERLAY
    1902: invokevirtual #255                // Method com/mojang/blaze3d/pipeline/RenderPipeline$Builder.withShaderDefine:(Ljava/lang/String;)Lcom/mojang/blaze3d/pipeline/RenderPipeline$Builder;
    1905: ldc_w         #480                // String NO_CARDINAL_LIGHTING
    1908: invokevirtual #255                // Method com/mojang/blaze3d/pipeline/RenderPipeline$Builder.withShaderDefine:(Ljava/lang/String;)Lcom/mojang/blaze3d/pipeline/RenderPipeline$Builder;
    1911: ldc           #222                // String Sampler0
    1913: invokevirtual #225                // Method com/mojang/blaze3d/pipeline/RenderPipeline$Builder.withSampler:(Ljava/lang/String;)Lcom/mojang/blaze3d/pipeline/RenderPipeline$Builder;
    1916: getstatic     #266                // Field com/mojang/blaze3d/pipeline/BlendFunction.TRANSLUCENT:Lcom/mojang/blaze3d/pipeline/BlendFunction;
    1919: invokevirtual #270                // Method com/mojang/blaze3d/pipeline/RenderPipeline$Builder.withBlend:(Lcom/mojang/blaze3d/pipeline/BlendFunction;)Lcom/mojang/blaze3d/pipeline/RenderPipeline$Builder;
    1922: iconst_0
    1923: invokevirtual #362                // Method com/mojang/blaze3d/pipeline/RenderPipeline$Builder.withDepthWrite:(Z)Lcom/mojang/blaze3d/pipeline/RenderPipeline$Builder;
    1926: getstatic     #248                // Field net/minecraft/client/render/VertexFormats.POSITION_COLOR_TEXTURE_OVERLAY_LIGHT_NORMAL:Lcom/mojang/blaze3d/vertex/VertexFormat;
    1929: getstatic     #237                // Field com/mojang/blaze3d/vertex/VertexFormat$DrawMode.QUADS:Lcom/mojang/blaze3d/vertex/VertexFormat$DrawMode;
    1932: invokevirtual #241                // Method com/mojang/blaze3d/pipeline/RenderPipeline$Builder.withVertexFormat:(Lcom/mojang/blaze3d/vertex/VertexFormat;Lcom/mojang/blaze3d/vertex/VertexFormat$DrawMode;)Lcom/mojang/blaze3d/pipeline/RenderPipeline$Builder;
    1935: invokevirtual #375                // Method com/mojang/blaze3d/pipeline/RenderPipeline$Builder.build:()Lcom/mojang/blaze3d/pipeline/RenderPipeline;
    1938: invokestatic  #377                // Method register:(Lcom/mojang/blaze3d/pipeline/RenderPipeline;)Lcom/mojang/blaze3d/pipeline/RenderPipeline;
    1941: putstatic     #493                // Field ENTITY_EYES:Lcom/mojang/blaze3d/pipeline/RenderPipeline;
    1944: iconst_1
    1945: anewarray     #11                 // class com/mojang/blaze3d/pipeline/RenderPipeline$Snippet
    1948: dup
    1949: iconst_0
    1950: getstatic     #211                // Field TRANSFORMS_PROJECTION_FOG_LIGHTING_SNIPPET:Lcom/mojang/blaze3d/pipeline/RenderPipeline$Snippet;
    1953: aastore
    1954: invokestatic  #177                // Method com/mojang/blaze3d/pipeline/RenderPipeline.builder:([Lcom/mojang/blaze3d/pipeline/RenderPipeline$Snippet;)Lcom/mojang/blaze3d/pipeline/RenderPipeline$Builder;
    1957: ldc_w         #495                // String pipeline/entity_decal
    1960: invokevirtual #371                // Method com/mojang/blaze3d/pipeline/RenderPipeline$Builder.withLocation:(Ljava/lang/String;)Lcom/mojang/blaze3d/pipeline/RenderPipeline$Builder;
    1963: ldc_w         #497                // String core/rendertype_entity_decal
    1966: invokevirtual #217                // Method com/mojang/blaze3d/pipeline/RenderPipeline$Builder.withVertexShader:(Ljava/lang/String;)Lcom/mojang/blaze3d/pipeline/RenderPipeline$Builder;
    1969: ldc_w         #497                // String core/rendertype_entity_decal
    1972: invokevirtual #220                // Method com/mojang/blaze3d/pipeline/RenderPipeline$Builder.withFragmentShader:(Ljava/lang/String;)Lcom/mojang/blaze3d/pipeline/RenderPipeline$Builder;
    1975: ldc           #222                // String Sampler0
    1977: invokevirtual #225                // Method com/mojang/blaze3d/pipeline/RenderPipeline$Builder.withSampler:(Ljava/lang/String;)Lcom/mojang/blaze3d/pipeline/RenderPipeline$Builder;
    1980: ldc_w         #279                // String Sampler1
    1983: invokevirtual #225                // Method com/mojang/blaze3d/pipeline/RenderPipeline$Builder.withSampler:(Ljava/lang/String;)Lcom/mojang/blaze3d/pipeline/RenderPipeline$Builder;
    1986: ldc           #227                // String Sampler2
    1988: invokevirtual #225                // Method com/mojang/blaze3d/pipeline/RenderPipeline$Builder.withSampler:(Ljava/lang/String;)Lcom/mojang/blaze3d/pipeline/RenderPipeline$Builder;
    1991: getstatic     #432                // Field com/mojang/blaze3d/platform/DepthTestFunction.EQUAL_DEPTH_TEST:Lcom/mojang/blaze3d/platform/DepthTestFunction;
    1994: invokevirtual #359                // Method com/mojang/blaze3d/pipeline/RenderPipeline$Builder.withDepthTestFunction:(Lcom/mojang/blaze3d/platform/DepthTestFunction;)Lcom/mojang/blaze3d/pipeline/RenderPipeline$Builder;
    1997: iconst_0
    1998: invokevirtual #313                // Method com/mojang/blaze3d/pipeline/RenderPipeline$Builder.withCull:(Z)Lcom/mojang/blaze3d/pipeline/RenderPipeline$Builder;
    2001: getstatic     #248                // Field net/minecraft/client/render/VertexFormats.POSITION_COLOR_TEXTURE_OVERLAY_LIGHT_NORMAL:Lcom/mojang/blaze3d/vertex/VertexFormat;
    2004: getstatic     #237                // Field com/mojang/blaze3d/vertex/VertexFormat$DrawMode.QUADS:Lcom/mojang/blaze3d/vertex/VertexFormat$DrawMode;
    2007: invokevirtual #241                // Method com/mojang/blaze3d/pipeline/RenderPipeline$Builder.withVertexFormat:(Lcom/mojang/blaze3d/vertex/VertexFormat;Lcom/mojang/blaze3d/vertex/VertexFormat$DrawMode;)Lcom/mojang/blaze3d/pipeline/RenderPipeline$Builder;
    2010: invokevirtual #375                // Method com/mojang/blaze3d/pipeline/RenderPipeline$Builder.build:()Lcom/mojang/blaze3d/pipeline/RenderPipeline;
    2013: invokestatic  #377                // Method register:(Lcom/mojang/blaze3d/pipeline/RenderPipeline;)Lcom/mojang/blaze3d/pipeline/RenderPipeline;
    2016: putstatic     #499                // Field RENDERTYPE_ENTITY_DECAL:Lcom/mojang/blaze3d/pipeline/RenderPipeline;
    2019: iconst_1
    2020: anewarray     #11                 // class com/mojang/blaze3d/pipeline/RenderPipeline$Snippet
    2023: dup
    2024: iconst_0
    2025: getstatic     #207                // Field TRANSFORMS_PROJECTION_FOG_SNIPPET:Lcom/mojang/blaze3d/pipeline/RenderPipeline$Snippet;
    2028: aastore
    2029: invokestatic  #177                // Method com/mojang/blaze3d/pipeline/RenderPipeline.builder:([Lcom/mojang/blaze3d/pipeline/RenderPipeline$Snippet;)Lcom/mojang/blaze3d/pipeline/RenderPipeline$Builder;
    2032: ldc_w         #501                // String pipeline/entity_shadow
    2035: invokevirtual #371                // Method com/mojang/blaze3d/pipeline/RenderPipeline$Builder.withLocation:(Ljava/lang/String;)Lcom/mojang/blaze3d/pipeline/RenderPipeline$Builder;
    2038: ldc_w         #503                // String core/rendertype_entity_shadow
    2041: invokevirtual #217                // Method com/mojang/blaze3d/pipeline/RenderPipeline$Builder.withVertexShader:(Ljava/lang/String;)Lcom/mojang/blaze3d/pipeline/RenderPipeline$Builder;
    2044: ldc_w         #503                // String core/rendertype_entity_shadow
    2047: invokevirtual #220                // Method com/mojang/blaze3d/pipeline/RenderPipeline$Builder.withFragmentShader:(Ljava/lang/String;)Lcom/mojang/blaze3d/pipeline/RenderPipeline$Builder;
    2050: ldc           #222                // String Sampler0
    2052: invokevirtual #225                // Method com/mojang/blaze3d/pipeline/RenderPipeline$Builder.withSampler:(Ljava/lang/String;)Lcom/mojang/blaze3d/pipeline/RenderPipeline$Builder;
    2055: getstatic     #266                // Field com/mojang/blaze3d/pipeline/BlendFunction.TRANSLUCENT:Lcom/mojang/blaze3d/pipeline/BlendFunction;
    2058: invokevirtual #270                // Method com/mojang/blaze3d/pipeline/RenderPipeline$Builder.withBlend:(Lcom/mojang/blaze3d/pipeline/BlendFunction;)Lcom/mojang/blaze3d/pipeline/RenderPipeline$Builder;
    2061: iconst_0
    2062: invokevirtual #362                // Method com/mojang/blaze3d/pipeline/RenderPipeline$Builder.withDepthWrite:(Z)Lcom/mojang/blaze3d/pipeline/RenderPipeline$Builder;
    2065: getstatic     #248                // Field net/minecraft/client/render/VertexFormats.POSITION_COLOR_TEXTURE_OVERLAY_LIGHT_NORMAL:Lcom/mojang/blaze3d/vertex/VertexFormat;
    2068: getstatic     #237                // Field com/mojang/blaze3d/vertex/VertexFormat$DrawMode.QUADS:Lcom/mojang/blaze3d/vertex/VertexFormat$DrawMode;
    2071: invokevirtual #241                // Method com/mojang/blaze3d/pipeline/RenderPipeline$Builder.withVertexFormat:(Lcom/mojang/blaze3d/vertex/VertexFormat;Lcom/mojang/blaze3d/vertex/VertexFormat$DrawMode;)Lcom/mojang/blaze3d/pipeline/RenderPipeline$Builder;
    2074: invokevirtual #375                // Method com/mojang/blaze3d/pipeline/RenderPipeline$Builder.build:()Lcom/mojang/blaze3d/pipeline/RenderPipeline;
    2077: invokestatic  #377                // Method register:(Lcom/mojang/blaze3d/pipeline/RenderPipeline;)Lcom/mojang/blaze3d/pipeline/RenderPipeline;
    2080: putstatic     #505                // Field RENDERTYPE_ENTITY_SHADOW:Lcom/mojang/blaze3d/pipeline/RenderPipeline;
    2083: iconst_1
    2084: anewarray     #11                 // class com/mojang/blaze3d/pipeline/RenderPipeline$Snippet
    2087: dup
    2088: iconst_0
    2089: getstatic     #211                // Field TRANSFORMS_PROJECTION_FOG_LIGHTING_SNIPPET:Lcom/mojang/blaze3d/pipeline/RenderPipeline$Snippet;
    2092: aastore
    2093: invokestatic  #177                // Method com/mojang/blaze3d/pipeline/RenderPipeline.builder:([Lcom/mojang/blaze3d/pipeline/RenderPipeline$Snippet;)Lcom/mojang/blaze3d/pipeline/RenderPipeline$Builder;
    2096: ldc_w         #507                // String pipeline/item_entity_translucent_cull
    2099: invokevirtual #371                // Method com/mojang/blaze3d/pipeline/RenderPipeline$Builder.withLocation:(Ljava/lang/String;)Lcom/mojang/blaze3d/pipeline/RenderPipeline$Builder;
    2102: ldc_w         #509                // String core/rendertype_item_entity_translucent_cull
    2105: invokevirtual #217                // Method com/mojang/blaze3d/pipeline/RenderPipeline$Builder.withVertexShader:(Ljava/lang/String;)Lcom/mojang/blaze3d/pipeline/RenderPipeline$Builder;
    2108: ldc_w         #509                // String core/rendertype_item_entity_translucent_cull
    2111: invokevirtual #220                // Method com/mojang/blaze3d/pipeline/RenderPipeline$Builder.withFragmentShader:(Ljava/lang/String;)Lcom/mojang/blaze3d/pipeline/RenderPipeline$Builder;
    2114: ldc           #222                // String Sampler0
    2116: invokevirtual #225                // Method com/mojang/blaze3d/pipeline/RenderPipeline$Builder.withSampler:(Ljava/lang/String;)Lcom/mojang/blaze3d/pipeline/RenderPipeline$Builder;
    2119: ldc           #227                // String Sampler2
    2121: invokevirtual #225                // Method com/mojang/blaze3d/pipeline/RenderPipeline$Builder.withSampler:(Ljava/lang/String;)Lcom/mojang/blaze3d/pipeline/RenderPipeline$Builder;
    2124: getstatic     #266                // Field com/mojang/blaze3d/pipeline/BlendFunction.TRANSLUCENT:Lcom/mojang/blaze3d/pipeline/BlendFunction;
    2127: invokevirtual #270                // Method com/mojang/blaze3d/pipeline/RenderPipeline$Builder.withBlend:(Lcom/mojang/blaze3d/pipeline/BlendFunction;)Lcom/mojang/blaze3d/pipeline/RenderPipeline$Builder;
    2130: getstatic     #248                // Field net/minecraft/client/render/VertexFormats.POSITION_COLOR_TEXTURE_OVERLAY_LIGHT_NORMAL:Lcom/mojang/blaze3d/vertex/VertexFormat;
    2133: getstatic     #237                // Field com/mojang/blaze3d/vertex/VertexFormat$DrawMode.QUADS:Lcom/mojang/blaze3d/vertex/VertexFormat$DrawMode;
    2136: invokevirtual #241                // Method com/mojang/blaze3d/pipeline/RenderPipeline$Builder.withVertexFormat:(Lcom/mojang/blaze3d/vertex/VertexFormat;Lcom/mojang/blaze3d/vertex/VertexFormat$DrawMode;)Lcom/mojang/blaze3d/pipeline/RenderPipeline$Builder;
    2139: invokevirtual #375                // Method com/mojang/blaze3d/pipeline/RenderPipeline$Builder.build:()Lcom/mojang/blaze3d/pipeline/RenderPipeline;
    2142: invokestatic  #377                // Method register:(Lcom/mojang/blaze3d/pipeline/RenderPipeline;)Lcom/mojang/blaze3d/pipeline/RenderPipeline;
    2145: putstatic     #511                // Field RENDERTYPE_ITEM_ENTITY_TRANSLUCENT_CULL:Lcom/mojang/blaze3d/pipeline/RenderPipeline;
    2148: iconst_1
    2149: anewarray     #11                 // class com/mojang/blaze3d/pipeline/RenderPipeline$Snippet
    2152: dup
    2153: iconst_0
    2154: getstatic     #261                // Field RENDERTYPE_BEACON_BEAM_SNIPPET:Lcom/mojang/blaze3d/pipeline/RenderPipeline$Snippet;
    2157: aastore
    2158: invokestatic  #177                // Method com/mojang/blaze3d/pipeline/RenderPipeline.builder:([Lcom/mojang/blaze3d/pipeline/RenderPipeline$Snippet;)Lcom/mojang/blaze3d/pipeline/RenderPipeline$Builder;
    2161: ldc_w         #513                // String pipeline/beacon_beam_opaque
    2164: invokevirtual #371                // Method com/mojang/blaze3d/pipeline/RenderPipeline$Builder.withLocation:(Ljava/lang/String;)Lcom/mojang/blaze3d/pipeline/RenderPipeline$Builder;
    2167: invokevirtual #375                // Method com/mojang/blaze3d/pipeline/RenderPipeline$Builder.build:()Lcom/mojang/blaze3d/pipeline/RenderPipeline;
    2170: invokestatic  #377                // Method register:(Lcom/mojang/blaze3d/pipeline/RenderPipeline;)Lcom/mojang/blaze3d/pipeline/RenderPipeline;
    2173: putstatic     #515                // Field BEACON_BEAM_OPAQUE:Lcom/mojang/blaze3d/pipeline/RenderPipeline;
    2176: iconst_1
    2177: anewarray     #11                 // class com/mojang/blaze3d/pipeline/RenderPipeline$Snippet
    2180: dup
    2181: iconst_0
    2182: getstatic     #261                // Field RENDERTYPE_BEACON_BEAM_SNIPPET:Lcom/mojang/blaze3d/pipeline/RenderPipeline$Snippet;
    2185: aastore
    2186: invokestatic  #177                // Method com/mojang/blaze3d/pipeline/RenderPipeline.builder:([Lcom/mojang/blaze3d/pipeline/RenderPipeline$Snippet;)Lcom/mojang/blaze3d/pipeline/RenderPipeline$Builder;
    2189: ldc_w         #517                // String pipeline/beacon_beam_translucent
    2192: invokevirtual #371                // Method com/mojang/blaze3d/pipeline/RenderPipeline$Builder.withLocation:(Ljava/lang/String;)Lcom/mojang/blaze3d/pipeline/RenderPipeline$Builder;
    2195: iconst_0
    2196: invokevirtual #362                // Method com/mojang/blaze3d/pipeline/RenderPipeline$Builder.withDepthWrite:(Z)Lcom/mojang/blaze3d/pipeline/RenderPipeline$Builder;
    2199: getstatic     #266                // Field com/mojang/blaze3d/pipeline/BlendFunction.TRANSLUCENT:Lcom/mojang/blaze3d/pipeline/BlendFunction;
    2202: invokevirtual #270                // Method com/mojang/blaze3d/pipeline/RenderPipeline$Builder.withBlend:(Lcom/mojang/blaze3d/pipeline/BlendFunction;)Lcom/mojang/blaze3d/pipeline/RenderPipeline$Builder;
    2205: invokevirtual #375                // Method com/mojang/blaze3d/pipeline/RenderPipeline$Builder.build:()Lcom/mojang/blaze3d/pipeline/RenderPipeline;
    2208: invokestatic  #377                // Method register:(Lcom/mojang/blaze3d/pipeline/RenderPipeline;)Lcom/mojang/blaze3d/pipeline/RenderPipeline;
    2211: putstatic     #519                // Field BEACON_BEAM_TRANSLUCENT:Lcom/mojang/blaze3d/pipeline/RenderPipeline;
    2214: iconst_1
    2215: anewarray     #11                 // class com/mojang/blaze3d/pipeline/RenderPipeline$Snippet
    2218: dup
    2219: iconst_0
    2220: getstatic     #197                // Field TRANSFORMS_AND_PROJECTION_SNIPPET:Lcom/mojang/blaze3d/pipeline/RenderPipeline$Snippet;
    2223: aastore
    2224: invokestatic  #177                // Method com/mojang/blaze3d/pipeline/RenderPipeline.builder:([Lcom/mojang/blaze3d/pipeline/RenderPipeline$Snippet;)Lcom/mojang/blaze3d/pipeline/RenderPipeline$Builder;
    2227: ldc_w         #521                // String pipeline/dragon_explosion_alpha
    2230: invokevirtual #371                // Method com/mojang/blaze3d/pipeline/RenderPipeline$Builder.withLocation:(Ljava/lang/String;)Lcom/mojang/blaze3d/pipeline/RenderPipeline$Builder;
    2233: ldc_w         #523                // String core/rendertype_entity_alpha
    2236: invokevirtual #217                // Method com/mojang/blaze3d/pipeline/RenderPipeline$Builder.withVertexShader:(Ljava/lang/String;)Lcom/mojang/blaze3d/pipeline/RenderPipeline$Builder;
    2239: ldc_w         #523                // String core/rendertype_entity_alpha
    2242: invokevirtual #220                // Method com/mojang/blaze3d/pipeline/RenderPipeline$Builder.withFragmentShader:(Ljava/lang/String;)Lcom/mojang/blaze3d/pipeline/RenderPipeline$Builder;
    2245: ldc           #222                // String Sampler0
    2247: invokevirtual #225                // Method com/mojang/blaze3d/pipeline/RenderPipeline$Builder.withSampler:(Ljava/lang/String;)Lcom/mojang/blaze3d/pipeline/RenderPipeline$Builder;
    2250: iconst_0
    2251: invokevirtual #313                // Method com/mojang/blaze3d/pipeline/RenderPipeline$Builder.withCull:(Z)Lcom/mojang/blaze3d/pipeline/RenderPipeline$Builder;
    2254: getstatic     #248                // Field net/minecraft/client/render/VertexFormats.POSITION_COLOR_TEXTURE_OVERLAY_LIGHT_NORMAL:Lcom/mojang/blaze3d/vertex/VertexFormat;
    2257: getstatic     #237                // Field com/mojang/blaze3d/vertex/VertexFormat$DrawMode.QUADS:Lcom/mojang/blaze3d/vertex/VertexFormat$DrawMode;
    2260: invokevirtual #241                // Method com/mojang/blaze3d/pipeline/RenderPipeline$Builder.withVertexFormat:(Lcom/mojang/blaze3d/vertex/VertexFormat;Lcom/mojang/blaze3d/vertex/VertexFormat$DrawMode;)Lcom/mojang/blaze3d/pipeline/RenderPipeline$Builder;
    2263: invokevirtual #375                // Method com/mojang/blaze3d/pipeline/RenderPipeline$Builder.build:()Lcom/mojang/blaze3d/pipeline/RenderPipeline;
    2266: invokestatic  #377                // Method register:(Lcom/mojang/blaze3d/pipeline/RenderPipeline;)Lcom/mojang/blaze3d/pipeline/RenderPipeline;
    2269: putstatic     #525                // Field RENDERTYPE_ENTITY_ALPHA:Lcom/mojang/blaze3d/pipeline/RenderPipeline;
    2272: iconst_1
    2273: anewarray     #11                 // class com/mojang/blaze3d/pipeline/RenderPipeline$Snippet
    2276: dup
    2277: iconst_0
    2278: getstatic     #207                // Field TRANSFORMS_PROJECTION_FOG_SNIPPET:Lcom/mojang/blaze3d/pipeline/RenderPipeline$Snippet;
    2281: aastore
    2282: invokestatic  #177                // Method com/mojang/blaze3d/pipeline/RenderPipeline.builder:([Lcom/mojang/blaze3d/pipeline/RenderPipeline$Snippet;)Lcom/mojang/blaze3d/pipeline/RenderPipeline$Builder;
    2285: ldc_w         #527                // String pipeline/leash
    2288: invokevirtual #371                // Method com/mojang/blaze3d/pipeline/RenderPipeline$Builder.withLocation:(Ljava/lang/String;)Lcom/mojang/blaze3d/pipeline/RenderPipeline$Builder;
    2291: ldc_w         #529                // String core/rendertype_leash
    2294: invokevirtual #217                // Method com/mojang/blaze3d/pipeline/RenderPipeline$Builder.withVertexShader:(Ljava/lang/String;)Lcom/mojang/blaze3d/pipeline/RenderPipeline$Builder;
    2297: ldc_w         #529                // String core/rendertype_leash
    2300: invokevirtual #220                // Method com/mojang/blaze3d/pipeline/RenderPipeline$Builder.withFragmentShader:(Ljava/lang/String;)Lcom/mojang/blaze3d/pipeline/RenderPipeline$Builder;
    2303: ldc           #227                // String Sampler2
    2305: invokevirtual #225                // Method com/mojang/blaze3d/pipeline/RenderPipeline$Builder.withSampler:(Ljava/lang/String;)Lcom/mojang/blaze3d/pipeline/RenderPipeline$Builder;
    2308: iconst_0
    2309: invokevirtual #313                // Method com/mojang/blaze3d/pipeline/RenderPipeline$Builder.withCull:(Z)Lcom/mojang/blaze3d/pipeline/RenderPipeline$Builder;
    2312: getstatic     #532                // Field net/minecraft/client/render/VertexFormats.POSITION_COLOR_LIGHT:Lcom/mojang/blaze3d/vertex/VertexFormat;
    2315: getstatic     #535                // Field com/mojang/blaze3d/vertex/VertexFormat$DrawMode.TRIANGLE_STRIP:Lcom/mojang/blaze3d/vertex/VertexFormat$DrawMode;
    2318: invokevirtual #241                // Method com/mojang/blaze3d/pipeline/RenderPipeline$Builder.withVertexFormat:(Lcom/mojang/blaze3d/vertex/VertexFormat;Lcom/mojang/blaze3d/vertex/VertexFormat$DrawMode;)Lcom/mojang/blaze3d/pipeline/RenderPipeline$Builder;
    2321: invokevirtual #375                // Method com/mojang/blaze3d/pipeline/RenderPipeline$Builder.build:()Lcom/mojang/blaze3d/pipeline/RenderPipeline;
    2324: invokestatic  #377                // Method register:(Lcom/mojang/blaze3d/pipeline/RenderPipeline;)Lcom/mojang/blaze3d/pipeline/RenderPipeline;
    2327: putstatic     #537                // Field RENDERTYPE_LEASH:Lcom/mojang/blaze3d/pipeline/RenderPipeline;
    2330: iconst_1
    2331: anewarray     #11                 // class com/mojang/blaze3d/pipeline/RenderPipeline$Snippet
    2334: dup
    2335: iconst_0
    2336: getstatic     #197                // Field TRANSFORMS_AND_PROJECTION_SNIPPET:Lcom/mojang/blaze3d/pipeline/RenderPipeline$Snippet;
    2339: aastore
    2340: invokestatic  #177                // Method com/mojang/blaze3d/pipeline/RenderPipeline.builder:([Lcom/mojang/blaze3d/pipeline/RenderPipeline$Snippet;)Lcom/mojang/blaze3d/pipeline/RenderPipeline$Builder;
    2343: ldc_w         #539                // String pipeline/water_mask
    2346: invokevirtual #371                // Method com/mojang/blaze3d/pipeline/RenderPipeline$Builder.withLocation:(Ljava/lang/String;)Lcom/mojang/blaze3d/pipeline/RenderPipeline$Builder;
    2349: ldc_w         #541                // String core/rendertype_water_mask
    2352: invokevirtual #217                // Method com/mojang/blaze3d/pipeline/RenderPipeline$Builder.withVertexShader:(Ljava/lang/String;)Lcom/mojang/blaze3d/pipeline/RenderPipeline$Builder;
    2355: ldc_w         #541                // String core/rendertype_water_mask
    2358: invokevirtual #220                // Method com/mojang/blaze3d/pipeline/RenderPipeline$Builder.withFragmentShader:(Ljava/lang/String;)Lcom/mojang/blaze3d/pipeline/RenderPipeline$Builder;
    2361: iconst_0
    2362: invokevirtual #544                // Method com/mojang/blaze3d/pipeline/RenderPipeline$Builder.withColorWrite:(Z)Lcom/mojang/blaze3d/pipeline/RenderPipeline$Builder;
    2365: getstatic     #282                // Field net/minecraft/client/render/VertexFormats.POSITION:Lcom/mojang/blaze3d/vertex/VertexFormat;
    2368: getstatic     #237                // Field com/mojang/blaze3d/vertex/VertexFormat$DrawMode.QUADS:Lcom/mojang/blaze3d/vertex/VertexFormat$DrawMode;
    2371: invokevirtual #241                // Method com/mojang/blaze3d/pipeline/RenderPipeline$Builder.withVertexFormat:(Lcom/mojang/blaze3d/vertex/VertexFormat;Lcom/mojang/blaze3d/vertex/VertexFormat$DrawMode;)Lcom/mojang/blaze3d/pipeline/RenderPipeline$Builder;
    2374: invokevirtual #375                // Method com/mojang/blaze3d/pipeline/RenderPipeline$Builder.build:()Lcom/mojang/blaze3d/pipeline/RenderPipeline;
    2377: invokestatic  #377                // Method register:(Lcom/mojang/blaze3d/pipeline/RenderPipeline;)Lcom/mojang/blaze3d/pipeline/RenderPipeline;
    2380: putstatic     #546                // Field RENDERTYPE_WATER_MASK:Lcom/mojang/blaze3d/pipeline/RenderPipeline;
    2383: iconst_3
    2384: anewarray     #11                 // class com/mojang/blaze3d/pipeline/RenderPipeline$Snippet
    2387: dup
    2388: iconst_0
    2389: getstatic     #197                // Field TRANSFORMS_AND_PROJECTION_SNIPPET:Lcom/mojang/blaze3d/pipeline/RenderPipeline$Snippet;
    2392: aastore
    2393: dup
    2394: iconst_1
    2395: getstatic     #201                // Field FOG_SNIPPET:Lcom/mojang/blaze3d/pipeline/RenderPipeline$Snippet;
    2398: aastore
    2399: dup
    2400: iconst_2
    2401: getstatic     #205                // Field GLOBALS_SNIPPET:Lcom/mojang/blaze3d/pipeline/RenderPipeline$Snippet;
    2404: aastore
    2405: invokestatic  #177                // Method com/mojang/blaze3d/pipeline/RenderPipeline.builder:([Lcom/mojang/blaze3d/pipeline/RenderPipeline$Snippet;)Lcom/mojang/blaze3d/pipeline/RenderPipeline$Builder;
    2408: ldc_w         #548                // String pipeline/glint
    2411: invokevirtual #371                // Method com/mojang/blaze3d/pipeline/RenderPipeline$Builder.withLocation:(Ljava/lang/String;)Lcom/mojang/blaze3d/pipeline/RenderPipeline$Builder;
    2414: ldc_w         #550                // String core/glint
    2417: invokevirtual #217                // Method com/mojang/blaze3d/pipeline/RenderPipeline$Builder.withVertexShader:(Ljava/lang/String;)Lcom/mojang/blaze3d/pipeline/RenderPipeline$Builder;
    2420: ldc_w         #550                // String core/glint
    2423: invokevirtual #220                // Method com/mojang/blaze3d/pipeline/RenderPipeline$Builder.withFragmentShader:(Ljava/lang/String;)Lcom/mojang/blaze3d/pipeline/RenderPipeline$Builder;
    2426: ldc           #222                // String Sampler0
    2428: invokevirtual #225                // Method com/mojang/blaze3d/pipeline/RenderPipeline$Builder.withSampler:(Ljava/lang/String;)Lcom/mojang/blaze3d/pipeline/RenderPipeline$Builder;
    2431: iconst_0
    2432: invokevirtual #362                // Method com/mojang/blaze3d/pipeline/RenderPipeline$Builder.withDepthWrite:(Z)Lcom/mojang/blaze3d/pipeline/RenderPipeline$Builder;
    2435: iconst_0
    2436: invokevirtual #313                // Method com/mojang/blaze3d/pipeline/RenderPipeline$Builder.withCull:(Z)Lcom/mojang/blaze3d/pipeline/RenderPipeline$Builder;
    2439: getstatic     #432                // Field com/mojang/blaze3d/platform/DepthTestFunction.EQUAL_DEPTH_TEST:Lcom/mojang/blaze3d/platform/DepthTestFunction;
    2442: invokevirtual #359                // Method com/mojang/blaze3d/pipeline/RenderPipeline$Builder.withDepthTestFunction:(Lcom/mojang/blaze3d/platform/DepthTestFunction;)Lcom/mojang/blaze3d/pipeline/RenderPipeline$Builder;
    2445: getstatic     #552                // Field com/mojang/blaze3d/pipeline/BlendFunction.GLINT:Lcom/mojang/blaze3d/pipeline/BlendFunction;
    2448: invokevirtual #270                // Method com/mojang/blaze3d/pipeline/RenderPipeline$Builder.withBlend:(Lcom/mojang/blaze3d/pipeline/BlendFunction;)Lcom/mojang/blaze3d/pipeline/RenderPipeline$Builder;
    2451: getstatic     #555                // Field net/minecraft/client/render/VertexFormats.POSITION_TEXTURE:Lcom/mojang/blaze3d/vertex/VertexFormat;
    2454: getstatic     #237                // Field com/mojang/blaze3d/vertex/VertexFormat$DrawMode.QUADS:Lcom/mojang/blaze3d/vertex/VertexFormat$DrawMode;
    2457: invokevirtual #241                // Method com/mojang/blaze3d/pipeline/RenderPipeline$Builder.withVertexFormat:(Lcom/mojang/blaze3d/vertex/VertexFormat;Lcom/mojang/blaze3d/vertex/VertexFormat$DrawMode;)Lcom/mojang/blaze3d/pipeline/RenderPipeline$Builder;
    2460: invokevirtual #375                // Method com/mojang/blaze3d/pipeline/RenderPipeline$Builder.build:()Lcom/mojang/blaze3d/pipeline/RenderPipeline;
    2463: invokestatic  #377                // Method register:(Lcom/mojang/blaze3d/pipeline/RenderPipeline;)Lcom/mojang/blaze3d/pipeline/RenderPipeline;
    2466: putstatic     #557                // Field GLINT:Lcom/mojang/blaze3d/pipeline/RenderPipeline;
    2469: iconst_1
    2470: anewarray     #11                 // class com/mojang/blaze3d/pipeline/RenderPipeline$Snippet
    2473: dup
    2474: iconst_0
    2475: getstatic     #197                // Field TRANSFORMS_AND_PROJECTION_SNIPPET:Lcom/mojang/blaze3d/pipeline/RenderPipeline$Snippet;
    2478: aastore
    2479: invokestatic  #177                // Method com/mojang/blaze3d/pipeline/RenderPipeline.builder:([Lcom/mojang/blaze3d/pipeline/RenderPipeline$Snippet;)Lcom/mojang/blaze3d/pipeline/RenderPipeline$Builder;
    2482: ldc_w         #559                // String pipeline/crumbling
    2485: invokevirtual #371                // Method com/mojang/blaze3d/pipeline/RenderPipeline$Builder.withLocation:(Ljava/lang/String;)Lcom/mojang/blaze3d/pipeline/RenderPipeline$Builder;
    2488: ldc_w         #561                // String core/rendertype_crumbling
    2491: invokevirtual #217                // Method com/mojang/blaze3d/pipeline/RenderPipeline$Builder.withVertexShader:(Ljava/lang/String;)Lcom/mojang/blaze3d/pipeline/RenderPipeline$Builder;
    2494: ldc_w         #561                // String core/rendertype_crumbling
    2497: invokevirtual #220                // Method com/mojang/blaze3d/pipeline/RenderPipeline$Builder.withFragmentShader:(Ljava/lang/String;)Lcom/mojang/blaze3d/pipeline/RenderPipeline$Builder;
    2500: ldc           #222                // String Sampler0
    2502: invokevirtual #225                // Method com/mojang/blaze3d/pipeline/RenderPipeline$Builder.withSampler:(Ljava/lang/String;)Lcom/mojang/blaze3d/pipeline/RenderPipeline$Builder;
    2505: new           #263                // class com/mojang/blaze3d/pipeline/BlendFunction
    2508: dup
    2509: getstatic     #567                // Field com/mojang/blaze3d/platform/SourceFactor.DST_COLOR:Lcom/mojang/blaze3d/platform/SourceFactor;
    2512: getstatic     #573                // Field com/mojang/blaze3d/platform/DestFactor.SRC_COLOR:Lcom/mojang/blaze3d/platform/DestFactor;
    2515: getstatic     #576                // Field com/mojang/blaze3d/platform/SourceFactor.ONE:Lcom/mojang/blaze3d/platform/SourceFactor;
    2518: getstatic     #579                // Field com/mojang/blaze3d/platform/DestFactor.ZERO:Lcom/mojang/blaze3d/platform/DestFactor;
    2521: invokespecial #582                // Method com/mojang/blaze3d/pipeline/BlendFunction."<init>":(Lcom/mojang/blaze3d/platform/SourceFactor;Lcom/mojang/blaze3d/platform/DestFactor;Lcom/mojang/blaze3d/platform/SourceFactor;Lcom/mojang/blaze3d/platform/DestFactor;)V
    2524: invokevirtual #270                // Method com/mojang/blaze3d/pipeline/RenderPipeline$Builder.withBlend:(Lcom/mojang/blaze3d/pipeline/BlendFunction;)Lcom/mojang/blaze3d/pipeline/RenderPipeline$Builder;
    2527: iconst_0
    2528: invokevirtual #362                // Method com/mojang/blaze3d/pipeline/RenderPipeline$Builder.withDepthWrite:(Z)Lcom/mojang/blaze3d/pipeline/RenderPipeline$Builder;
    2531: getstatic     #233                // Field net/minecraft/client/render/VertexFormats.POSITION_COLOR_TEXTURE_LIGHT_NORMAL:Lcom/mojang/blaze3d/vertex/VertexFormat;
    2534: getstatic     #237                // Field com/mojang/blaze3d/vertex/VertexFormat$DrawMode.QUADS:Lcom/mojang/blaze3d/vertex/VertexFormat$DrawMode;
    2537: invokevirtual #241                // Method com/mojang/blaze3d/pipeline/RenderPipeline$Builder.withVertexFormat:(Lcom/mojang/blaze3d/vertex/VertexFormat;Lcom/mojang/blaze3d/vertex/VertexFormat$DrawMode;)Lcom/mojang/blaze3d/pipeline/RenderPipeline$Builder;
    2540: ldc_w         #583                // float -1.0f
    2543: ldc_w         #584                // float -10.0f
    2546: invokevirtual #588                // Method com/mojang/blaze3d/pipeline/RenderPipeline$Builder.withDepthBias:(FF)Lcom/mojang/blaze3d/pipeline/RenderPipeline$Builder;
    2549: invokevirtual #375                // Method com/mojang/blaze3d/pipeline/RenderPipeline$Builder.build:()Lcom/mojang/blaze3d/pipeline/RenderPipeline;
    2552: invokestatic  #377                // Method register:(Lcom/mojang/blaze3d/pipeline/RenderPipeline;)Lcom/mojang/blaze3d/pipeline/RenderPipeline;
    2555: putstatic     #590                // Field RENDERTYPE_CRUMBLING:Lcom/mojang/blaze3d/pipeline/RenderPipeline;
    2558: iconst_2
    2559: anewarray     #11                 // class com/mojang/blaze3d/pipeline/RenderPipeline$Snippet
    2562: dup
    2563: iconst_0
    2564: getstatic     #275                // Field TEXT_SNIPPET:Lcom/mojang/blaze3d/pipeline/RenderPipeline$Snippet;
    2567: aastore
    2568: dup
    2569: iconst_1
    2570: getstatic     #201                // Field FOG_SNIPPET:Lcom/mojang/blaze3d/pipeline/RenderPipeline$Snippet;
    2573: aastore
    2574: invokestatic  #177                // Method com/mojang/blaze3d/pipeline/RenderPipeline.builder:([Lcom/mojang/blaze3d/pipeline/RenderPipeline$Snippet;)Lcom/mojang/blaze3d/pipeline/RenderPipeline$Builder;
    2577: ldc_w         #592                // String pipeline/text
    2580: invokevirtual #371                // Method com/mojang/blaze3d/pipeline/RenderPipeline$Builder.withLocation:(Ljava/lang/String;)Lcom/mojang/blaze3d/pipeline/RenderPipeline$Builder;
    2583: ldc_w         #594                // String core/rendertype_text
    2586: invokevirtual #217                // Method com/mojang/blaze3d/pipeline/RenderPipeline$Builder.withVertexShader:(Ljava/lang/String;)Lcom/mojang/blaze3d/pipeline/RenderPipeline$Builder;
    2589: ldc_w         #594                // String core/rendertype_text
    2592: invokevirtual #220                // Method com/mojang/blaze3d/pipeline/RenderPipeline$Builder.withFragmentShader:(Ljava/lang/String;)Lcom/mojang/blaze3d/pipeline/RenderPipeline$Builder;
    2595: ldc           #222                // String Sampler0
    2597: invokevirtual #225                // Method com/mojang/blaze3d/pipeline/RenderPipeline$Builder.withSampler:(Ljava/lang/String;)Lcom/mojang/blaze3d/pipeline/RenderPipeline$Builder;
    2600: ldc           #227                // String Sampler2
    2602: invokevirtual #225                // Method com/mojang/blaze3d/pipeline/RenderPipeline$Builder.withSampler:(Ljava/lang/String;)Lcom/mojang/blaze3d/pipeline/RenderPipeline$Builder;
    2605: invokevirtual #375                // Method com/mojang/blaze3d/pipeline/RenderPipeline$Builder.build:()Lcom/mojang/blaze3d/pipeline/RenderPipeline;
    2608: invokestatic  #377                // Method register:(Lcom/mojang/blaze3d/pipeline/RenderPipeline;)Lcom/mojang/blaze3d/pipeline/RenderPipeline;
    2611: putstatic     #596                // Field RENDERTYPE_TEXT:Lcom/mojang/blaze3d/pipeline/RenderPipeline;
    2614: iconst_2
    2615: anewarray     #11                 // class com/mojang/blaze3d/pipeline/RenderPipeline$Snippet
    2618: dup
    2619: iconst_0
    2620: getstatic     #275                // Field TEXT_SNIPPET:Lcom/mojang/blaze3d/pipeline/RenderPipeline$Snippet;
    2623: aastore
    2624: dup
    2625: iconst_1
    2626: getstatic     #201                // Field FOG_SNIPPET:Lcom/mojang/blaze3d/pipeline/RenderPipeline$Snippet;
    2629: aastore
    2630: invokestatic  #177                // Method com/mojang/blaze3d/pipeline/RenderPipeline.builder:([Lcom/mojang/blaze3d/pipeline/RenderPipeline$Snippet;)Lcom/mojang/blaze3d/pipeline/RenderPipeline$Builder;
    2633: ldc_w         #598                // String pipeline/text_background
    2636: invokevirtual #371                // Method com/mojang/blaze3d/pipeline/RenderPipeline$Builder.withLocation:(Ljava/lang/String;)Lcom/mojang/blaze3d/pipeline/RenderPipeline$Builder;
    2639: ldc_w         #600                // String core/rendertype_text_background
    2642: invokevirtual #217                // Method com/mojang/blaze3d/pipeline/RenderPipeline$Builder.withVertexShader:(Ljava/lang/String;)Lcom/mojang/blaze3d/pipeline/RenderPipeline$Builder;
    2645: ldc_w         #600                // String core/rendertype_text_background
    2648: invokevirtual #220                // Method com/mojang/blaze3d/pipeline/RenderPipeline$Builder.withFragmentShader:(Ljava/lang/String;)Lcom/mojang/blaze3d/pipeline/RenderPipeline$Builder;
    2651: ldc           #227                // String Sampler2
    2653: invokevirtual #225                // Method com/mojang/blaze3d/pipeline/RenderPipeline$Builder.withSampler:(Ljava/lang/String;)Lcom/mojang/blaze3d/pipeline/RenderPipeline$Builder;
    2656: getstatic     #532                // Field net/minecraft/client/render/VertexFormats.POSITION_COLOR_LIGHT:Lcom/mojang/blaze3d/vertex/VertexFormat;
    2659: getstatic     #237                // Field com/mojang/blaze3d/vertex/VertexFormat$DrawMode.QUADS:Lcom/mojang/blaze3d/vertex/VertexFormat$DrawMode;
    2662: invokevirtual #241                // Method com/mojang/blaze3d/pipeline/RenderPipeline$Builder.withVertexFormat:(Lcom/mojang/blaze3d/vertex/VertexFormat;Lcom/mojang/blaze3d/vertex/VertexFormat$DrawMode;)Lcom/mojang/blaze3d/pipeline/RenderPipeline$Builder;
    2665: invokevirtual #375                // Method com/mojang/blaze3d/pipeline/RenderPipeline$Builder.build:()Lcom/mojang/blaze3d/pipeline/RenderPipeline;
    2668: invokestatic  #377                // Method register:(Lcom/mojang/blaze3d/pipeline/RenderPipeline;)Lcom/mojang/blaze3d/pipeline/RenderPipeline;
    2671: putstatic     #602                // Field RENDERTYPE_TEXT_BG:Lcom/mojang/blaze3d/pipeline/RenderPipeline;
    2674: iconst_2
    2675: anewarray     #11                 // class com/mojang/blaze3d/pipeline/RenderPipeline$Snippet
    2678: dup
    2679: iconst_0
    2680: getstatic     #275                // Field TEXT_SNIPPET:Lcom/mojang/blaze3d/pipeline/RenderPipeline$Snippet;
    2683: aastore
    2684: dup
    2685: iconst_1
    2686: getstatic     #201                // Field FOG_SNIPPET:Lcom/mojang/blaze3d/pipeline/RenderPipeline$Snippet;
    2689: aastore
    2690: invokestatic  #177                // Method com/mojang/blaze3d/pipeline/RenderPipeline.builder:([Lcom/mojang/blaze3d/pipeline/RenderPipeline$Snippet;)Lcom/mojang/blaze3d/pipeline/RenderPipeline$Builder;
    2693: ldc_w         #604                // String pipeline/text_intensity
    2696: invokevirtual #371                // Method com/mojang/blaze3d/pipeline/RenderPipeline$Builder.withLocation:(Ljava/lang/String;)Lcom/mojang/blaze3d/pipeline/RenderPipeline$Builder;
    2699: ldc_w         #606                // String core/rendertype_text_intensity
    2702: invokevirtual #217                // Method com/mojang/blaze3d/pipeline/RenderPipeline$Builder.withVertexShader:(Ljava/lang/String;)Lcom/mojang/blaze3d/pipeline/RenderPipeline$Builder;
    2705: ldc_w         #606                // String core/rendertype_text_intensity
    2708: invokevirtual #220                // Method com/mojang/blaze3d/pipeline/RenderPipeline$Builder.withFragmentShader:(Ljava/lang/String;)Lcom/mojang/blaze3d/pipeline/RenderPipeline$Builder;
    2711: ldc           #222                // String Sampler0
    2713: invokevirtual #225                // Method com/mojang/blaze3d/pipeline/RenderPipeline$Builder.withSampler:(Ljava/lang/String;)Lcom/mojang/blaze3d/pipeline/RenderPipeline$Builder;
    2716: ldc           #227                // String Sampler2
    2718: invokevirtual #225                // Method com/mojang/blaze3d/pipeline/RenderPipeline$Builder.withSampler:(Ljava/lang/String;)Lcom/mojang/blaze3d/pipeline/RenderPipeline$Builder;
    2721: ldc_w         #583                // float -1.0f
    2724: ldc_w         #584                // float -10.0f
    2727: invokevirtual #588                // Method com/mojang/blaze3d/pipeline/RenderPipeline$Builder.withDepthBias:(FF)Lcom/mojang/blaze3d/pipeline/RenderPipeline$Builder;
    2730: invokevirtual #375                // Method com/mojang/blaze3d/pipeline/RenderPipeline$Builder.build:()Lcom/mojang/blaze3d/pipeline/RenderPipeline;
    2733: invokestatic  #377                // Method register:(Lcom/mojang/blaze3d/pipeline/RenderPipeline;)Lcom/mojang/blaze3d/pipeline/RenderPipeline;
    2736: putstatic     #608                // Field RENDERTYPE_TEXT_INTENSITY:Lcom/mojang/blaze3d/pipeline/RenderPipeline;
    2739: iconst_2
    2740: anewarray     #11                 // class com/mojang/blaze3d/pipeline/RenderPipeline$Snippet
    2743: dup
    2744: iconst_0
    2745: getstatic     #275                // Field TEXT_SNIPPET:Lcom/mojang/blaze3d/pipeline/RenderPipeline$Snippet;
    2748: aastore
    2749: dup
    2750: iconst_1
    2751: getstatic     #201                // Field FOG_SNIPPET:Lcom/mojang/blaze3d/pipeline/RenderPipeline$Snippet;
    2754: aastore
    2755: invokestatic  #177                // Method com/mojang/blaze3d/pipeline/RenderPipeline.builder:([Lcom/mojang/blaze3d/pipeline/RenderPipeline$Snippet;)Lcom/mojang/blaze3d/pipeline/RenderPipeline$Builder;
    2758: ldc_w         #610                // String pipeline/text_polygon_offset
    2761: invokevirtual #371                // Method com/mojang/blaze3d/pipeline/RenderPipeline$Builder.withLocation:(Ljava/lang/String;)Lcom/mojang/blaze3d/pipeline/RenderPipeline$Builder;
    2764: ldc_w         #594                // String core/rendertype_text
    2767: invokevirtual #217                // Method com/mojang/blaze3d/pipeline/RenderPipeline$Builder.withVertexShader:(Ljava/lang/String;)Lcom/mojang/blaze3d/pipeline/RenderPipeline$Builder;
    2770: ldc_w         #594                // String core/rendertype_text
    2773: invokevirtual #220                // Method com/mojang/blaze3d/pipeline/RenderPipeline$Builder.withFragmentShader:(Ljava/lang/String;)Lcom/mojang/blaze3d/pipeline/RenderPipeline$Builder;
    2776: ldc           #222                // String Sampler0
    2778: invokevirtual #225                // Method com/mojang/blaze3d/pipeline/RenderPipeline$Builder.withSampler:(Ljava/lang/String;)Lcom/mojang/blaze3d/pipeline/RenderPipeline$Builder;
    2781: ldc           #227                // String Sampler2
    2783: invokevirtual #225                // Method com/mojang/blaze3d/pipeline/RenderPipeline$Builder.withSampler:(Ljava/lang/String;)Lcom/mojang/blaze3d/pipeline/RenderPipeline$Builder;
    2786: ldc_w         #583                // float -1.0f
    2789: ldc_w         #584                // float -10.0f
    2792: invokevirtual #588                // Method com/mojang/blaze3d/pipeline/RenderPipeline$Builder.withDepthBias:(FF)Lcom/mojang/blaze3d/pipeline/RenderPipeline$Builder;
    2795: invokevirtual #375                // Method com/mojang/blaze3d/pipeline/RenderPipeline$Builder.build:()Lcom/mojang/blaze3d/pipeline/RenderPipeline;
    2798: invokestatic  #377                // Method register:(Lcom/mojang/blaze3d/pipeline/RenderPipeline;)Lcom/mojang/blaze3d/pipeline/RenderPipeline;
    2801: putstatic     #612                // Field RENDERTYPE_TEXT_POLYGON_OFFSET:Lcom/mojang/blaze3d/pipeline/RenderPipeline;
    2804: iconst_1
    2805: anewarray     #11                 // class com/mojang/blaze3d/pipeline/RenderPipeline$Snippet
    2808: dup
    2809: iconst_0
    2810: getstatic     #275                // Field TEXT_SNIPPET:Lcom/mojang/blaze3d/pipeline/RenderPipeline$Snippet;
    2813: aastore
    2814: invokestatic  #177                // Method com/mojang/blaze3d/pipeline/RenderPipeline.builder:([Lcom/mojang/blaze3d/pipeline/RenderPipeline$Snippet;)Lcom/mojang/blaze3d/pipeline/RenderPipeline$Builder;
    2817: ldc_w         #614                // String pipeline/text_see_through
    2820: invokevirtual #371                // Method com/mojang/blaze3d/pipeline/RenderPipeline$Builder.withLocation:(Ljava/lang/String;)Lcom/mojang/blaze3d/pipeline/RenderPipeline$Builder;
    2823: ldc_w         #616                // String core/rendertype_text_see_through
    2826: invokevirtual #217                // Method com/mojang/blaze3d/pipeline/RenderPipeline$Builder.withVertexShader:(Ljava/lang/String;)Lcom/mojang/blaze3d/pipeline/RenderPipeline$Builder;
    2829: ldc_w         #616                // String core/rendertype_text_see_through
    2832: invokevirtual #220                // Method com/mojang/blaze3d/pipeline/RenderPipeline$Builder.withFragmentShader:(Ljava/lang/String;)Lcom/mojang/blaze3d/pipeline/RenderPipeline$Builder;
    2835: ldc           #222                // String Sampler0
    2837: invokevirtual #225                // Method com/mojang/blaze3d/pipeline/RenderPipeline$Builder.withSampler:(Ljava/lang/String;)Lcom/mojang/blaze3d/pipeline/RenderPipeline$Builder;
    2840: iconst_0
    2841: invokevirtual #362                // Method com/mojang/blaze3d/pipeline/RenderPipeline$Builder.withDepthWrite:(Z)Lcom/mojang/blaze3d/pipeline/RenderPipeline$Builder;
    2844: getstatic     #355                // Field com/mojang/blaze3d/platform/DepthTestFunction.NO_DEPTH_TEST:Lcom/mojang/blaze3d/platform/DepthTestFunction;
    2847: invokevirtual #359                // Method com/mojang/blaze3d/pipeline/RenderPipeline$Builder.withDepthTestFunction:(Lcom/mojang/blaze3d/platform/DepthTestFunction;)Lcom/mojang/blaze3d/pipeline/RenderPipeline$Builder;
    2850: invokevirtual #375                // Method com/mojang/blaze3d/pipeline/RenderPipeline$Builder.build:()Lcom/mojang/blaze3d/pipeline/RenderPipeline;
    2853: invokestatic  #377                // Method register:(Lcom/mojang/blaze3d/pipeline/RenderPipeline;)Lcom/mojang/blaze3d/pipeline/RenderPipeline;
    2856: putstatic     #618                // Field RENDERTYPE_TEXT_SEETHROUGH:Lcom/mojang/blaze3d/pipeline/RenderPipeline;
    2859: iconst_1
    2860: anewarray     #11                 // class com/mojang/blaze3d/pipeline/RenderPipeline$Snippet
    2863: dup
    2864: iconst_0
    2865: getstatic     #275                // Field TEXT_SNIPPET:Lcom/mojang/blaze3d/pipeline/RenderPipeline$Snippet;
    2868: aastore
    2869: invokestatic  #177                // Method com/mojang/blaze3d/pipeline/RenderPipeline.builder:([Lcom/mojang/blaze3d/pipeline/RenderPipeline$Snippet;)Lcom/mojang/blaze3d/pipeline/RenderPipeline$Builder;
    2872: ldc_w         #620                // String pipeline/text_background_see_through
    2875: invokevirtual #371                // Method com/mojang/blaze3d/pipeline/RenderPipeline$Builder.withLocation:(Ljava/lang/String;)Lcom/mojang/blaze3d/pipeline/RenderPipeline$Builder;
    2878: ldc_w         #622                // String core/rendertype_text_background_see_through
    2881: invokevirtual #217                // Method com/mojang/blaze3d/pipeline/RenderPipeline$Builder.withVertexShader:(Ljava/lang/String;)Lcom/mojang/blaze3d/pipeline/RenderPipeline$Builder;
    2884: ldc_w         #622                // String core/rendertype_text_background_see_through
    2887: invokevirtual #220                // Method com/mojang/blaze3d/pipeline/RenderPipeline$Builder.withFragmentShader:(Ljava/lang/String;)Lcom/mojang/blaze3d/pipeline/RenderPipeline$Builder;
    2890: iconst_0
    2891: invokevirtual #362                // Method com/mojang/blaze3d/pipeline/RenderPipeline$Builder.withDepthWrite:(Z)Lcom/mojang/blaze3d/pipeline/RenderPipeline$Builder;
    2894: getstatic     #355                // Field com/mojang/blaze3d/platform/DepthTestFunction.NO_DEPTH_TEST:Lcom/mojang/blaze3d/platform/DepthTestFunction;
    2897: invokevirtual #359                // Method com/mojang/blaze3d/pipeline/RenderPipeline$Builder.withDepthTestFunction:(Lcom/mojang/blaze3d/platform/DepthTestFunction;)Lcom/mojang/blaze3d/pipeline/RenderPipeline$Builder;
    2900: getstatic     #532                // Field net/minecraft/client/render/VertexFormats.POSITION_COLOR_LIGHT:Lcom/mojang/blaze3d/vertex/VertexFormat;
    2903: getstatic     #237                // Field com/mojang/blaze3d/vertex/VertexFormat$DrawMode.QUADS:Lcom/mojang/blaze3d/vertex/VertexFormat$DrawMode;
    2906: invokevirtual #241                // Method com/mojang/blaze3d/pipeline/RenderPipeline$Builder.withVertexFormat:(Lcom/mojang/blaze3d/vertex/VertexFormat;Lcom/mojang/blaze3d/vertex/VertexFormat$DrawMode;)Lcom/mojang/blaze3d/pipeline/RenderPipeline$Builder;
    2909: invokevirtual #375                // Method com/mojang/blaze3d/pipeline/RenderPipeline$Builder.build:()Lcom/mojang/blaze3d/pipeline/RenderPipeline;
    2912: invokestatic  #377                // Method register:(Lcom/mojang/blaze3d/pipeline/RenderPipeline;)Lcom/mojang/blaze3d/pipeline/RenderPipeline;
    2915: putstatic     #624                // Field RENDERTYPE_TEXT_BG_SEETHROUGH:Lcom/mojang/blaze3d/pipeline/RenderPipeline;
    2918: iconst_1
    2919: anewarray     #11                 // class com/mojang/blaze3d/pipeline/RenderPipeline$Snippet
    2922: dup
    2923: iconst_0
    2924: getstatic     #275                // Field TEXT_SNIPPET:Lcom/mojang/blaze3d/pipeline/RenderPipeline$Snippet;
    2927: aastore
    2928: invokestatic  #177                // Method com/mojang/blaze3d/pipeline/RenderPipeline.builder:([Lcom/mojang/blaze3d/pipeline/RenderPipeline$Snippet;)Lcom/mojang/blaze3d/pipeline/RenderPipeline$Builder;
    2931: ldc_w         #626                // String pipeline/text_intensity_see_through
    2934: invokevirtual #371                // Method com/mojang/blaze3d/pipeline/RenderPipeline$Builder.withLocation:(Ljava/lang/String;)Lcom/mojang/blaze3d/pipeline/RenderPipeline$Builder;
    2937: ldc_w         #628                // String core/rendertype_text_intensity_see_through
    2940: invokevirtual #217                // Method com/mojang/blaze3d/pipeline/RenderPipeline$Builder.withVertexShader:(Ljava/lang/String;)Lcom/mojang/blaze3d/pipeline/RenderPipeline$Builder;
    2943: ldc_w         #628                // String core/rendertype_text_intensity_see_through
    2946: invokevirtual #220                // Method com/mojang/blaze3d/pipeline/RenderPipeline$Builder.withFragmentShader:(Ljava/lang/String;)Lcom/mojang/blaze3d/pipeline/RenderPipeline$Builder;
    2949: ldc           #222                // String Sampler0
    2951: invokevirtual #225                // Method com/mojang/blaze3d/pipeline/RenderPipeline$Builder.withSampler:(Ljava/lang/String;)Lcom/mojang/blaze3d/pipeline/RenderPipeline$Builder;
    2954: iconst_0
    2955: invokevirtual #362                // Method com/mojang/blaze3d/pipeline/RenderPipeline$Builder.withDepthWrite:(Z)Lcom/mojang/blaze3d/pipeline/RenderPipeline$Builder;
    2958: getstatic     #355                // Field com/mojang/blaze3d/platform/DepthTestFunction.NO_DEPTH_TEST:Lcom/mojang/blaze3d/platform/DepthTestFunction;
    2961: invokevirtual #359                // Method com/mojang/blaze3d/pipeline/RenderPipeline$Builder.withDepthTestFunction:(Lcom/mojang/blaze3d/platform/DepthTestFunction;)Lcom/mojang/blaze3d/pipeline/RenderPipeline$Builder;
    2964: invokevirtual #375                // Method com/mojang/blaze3d/pipeline/RenderPipeline$Builder.build:()Lcom/mojang/blaze3d/pipeline/RenderPipeline;
    2967: invokestatic  #377                // Method register:(Lcom/mojang/blaze3d/pipeline/RenderPipeline;)Lcom/mojang/blaze3d/pipeline/RenderPipeline;
    2970: putstatic     #630                // Field RENDERTYPE_TEXT_INTENSITY_SEETHROUGH:Lcom/mojang/blaze3d/pipeline/RenderPipeline;
    2973: iconst_1
    2974: anewarray     #11                 // class com/mojang/blaze3d/pipeline/RenderPipeline$Snippet
    2977: dup
    2978: iconst_0
    2979: getstatic     #207                // Field TRANSFORMS_PROJECTION_FOG_SNIPPET:Lcom/mojang/blaze3d/pipeline/RenderPipeline$Snippet;
    2982: aastore
    2983: invokestatic  #177                // Method com/mojang/blaze3d/pipeline/RenderPipeline.builder:([Lcom/mojang/blaze3d/pipeline/RenderPipeline$Snippet;)Lcom/mojang/blaze3d/pipeline/RenderPipeline$Builder;
    2986: ldc_w         #632                // String pipeline/lightning
    2989: invokevirtual #371                // Method com/mojang/blaze3d/pipeline/RenderPipeline$Builder.withLocation:(Ljava/lang/String;)Lcom/mojang/blaze3d/pipeline/RenderPipeline$Builder;
    2992: ldc_w         #634                // String core/rendertype_lightning
    2995: invokevirtual #217                // Method com/mojang/blaze3d/pipeline/RenderPipeline$Builder.withVertexShader:(Ljava/lang/String;)Lcom/mojang/blaze3d/pipeline/RenderPipeline$Builder;
    2998: ldc_w         #634                // String core/rendertype_lightning
    3001: invokevirtual #220                // Method com/mojang/blaze3d/pipeline/RenderPipeline$Builder.withFragmentShader:(Ljava/lang/String;)Lcom/mojang/blaze3d/pipeline/RenderPipeline$Builder;
    3004: getstatic     #637                // Field com/mojang/blaze3d/pipeline/BlendFunction.LIGHTNING:Lcom/mojang/blaze3d/pipeline/BlendFunction;
    3007: invokevirtual #270                // Method com/mojang/blaze3d/pipeline/RenderPipeline$Builder.withBlend:(Lcom/mojang/blaze3d/pipeline/BlendFunction;)Lcom/mojang/blaze3d/pipeline/RenderPipeline$Builder;
    3010: getstatic     #325                // Field net/minecraft/client/render/VertexFormats.POSITION_COLOR:Lcom/mojang/blaze3d/vertex/VertexFormat;
    3013: getstatic     #237                // Field com/mojang/blaze3d/vertex/VertexFormat$DrawMode.QUADS:Lcom/mojang/blaze3d/vertex/VertexFormat$DrawMode;
    3016: invokevirtual #241                // Method com/mojang/blaze3d/pipeline/RenderPipeline$Builder.withVertexFormat:(Lcom/mojang/blaze3d/vertex/VertexFormat;Lcom/mojang/blaze3d/vertex/VertexFormat$DrawMode;)Lcom/mojang/blaze3d/pipeline/RenderPipeline$Builder;
    3019: invokevirtual #375                // Method com/mojang/blaze3d/pipeline/RenderPipeline$Builder.build:()Lcom/mojang/blaze3d/pipeline/RenderPipeline;
    3022: invokestatic  #377                // Method register:(Lcom/mojang/blaze3d/pipeline/RenderPipeline;)Lcom/mojang/blaze3d/pipeline/RenderPipeline;
    3025: putstatic     #639                // Field RENDERTYPE_LIGHTNING:Lcom/mojang/blaze3d/pipeline/RenderPipeline;
    3028: iconst_1
    3029: anewarray     #11                 // class com/mojang/blaze3d/pipeline/RenderPipeline$Snippet
    3032: dup
    3033: iconst_0
    3034: getstatic     #207                // Field TRANSFORMS_PROJECTION_FOG_SNIPPET:Lcom/mojang/blaze3d/pipeline/RenderPipeline$Snippet;
    3037: aastore
    3038: invokestatic  #177                // Method com/mojang/blaze3d/pipeline/RenderPipeline.builder:([Lcom/mojang/blaze3d/pipeline/RenderPipeline$Snippet;)Lcom/mojang/blaze3d/pipeline/RenderPipeline$Builder;
    3041: ldc_w         #641                // String pipeline/dragon_rays
    3044: invokevirtual #371                // Method com/mojang/blaze3d/pipeline/RenderPipeline$Builder.withLocation:(Ljava/lang/String;)Lcom/mojang/blaze3d/pipeline/RenderPipeline$Builder;
    3047: ldc_w         #634                // String core/rendertype_lightning
    3050: invokevirtual #217                // Method com/mojang/blaze3d/pipeline/RenderPipeline$Builder.withVertexShader:(Ljava/lang/String;)Lcom/mojang/blaze3d/pipeline/RenderPipeline$Builder;
    3053: ldc_w         #634                // String core/rendertype_lightning
    3056: invokevirtual #220                // Method com/mojang/blaze3d/pipeline/RenderPipeline$Builder.withFragmentShader:(Ljava/lang/String;)Lcom/mojang/blaze3d/pipeline/RenderPipeline$Builder;
    3059: iconst_0
    3060: invokevirtual #362                // Method com/mojang/blaze3d/pipeline/RenderPipeline$Builder.withDepthWrite:(Z)Lcom/mojang/blaze3d/pipeline/RenderPipeline$Builder;
    3063: getstatic     #637                // Field com/mojang/blaze3d/pipeline/BlendFunction.LIGHTNING:Lcom/mojang/blaze3d/pipeline/BlendFunction;
    3066: invokevirtual #270                // Method com/mojang/blaze3d/pipeline/RenderPipeline$Builder.withBlend:(Lcom/mojang/blaze3d/pipeline/BlendFunction;)Lcom/mojang/blaze3d/pipeline/RenderPipeline$Builder;
    3069: getstatic     #325                // Field net/minecraft/client/render/VertexFormats.POSITION_COLOR:Lcom/mojang/blaze3d/vertex/VertexFormat;
    3072: getstatic     #644                // Field com/mojang/blaze3d/vertex/VertexFormat$DrawMode.TRIANGLES:Lcom/mojang/blaze3d/vertex/VertexFormat$DrawMode;
    3075: invokevirtual #241                // Method com/mojang/blaze3d/pipeline/RenderPipeline$Builder.withVertexFormat:(Lcom/mojang/blaze3d/vertex/VertexFormat;Lcom/mojang/blaze3d/vertex/VertexFormat$DrawMode;)Lcom/mojang/blaze3d/pipeline/RenderPipeline$Builder;
    3078: invokevirtual #375                // Method com/mojang/blaze3d/pipeline/RenderPipeline$Builder.build:()Lcom/mojang/blaze3d/pipeline/RenderPipeline;
    3081: invokestatic  #377                // Method register:(Lcom/mojang/blaze3d/pipeline/RenderPipeline;)Lcom/mojang/blaze3d/pipeline/RenderPipeline;
    3084: putstatic     #646                // Field RENDERTYPE_LIGHTNING_DRAGON_RAYS:Lcom/mojang/blaze3d/pipeline/RenderPipeline;
    3087: iconst_1
    3088: anewarray     #11                 // class com/mojang/blaze3d/pipeline/RenderPipeline$Snippet
    3091: dup
    3092: iconst_0
    3093: getstatic     #207                // Field TRANSFORMS_PROJECTION_FOG_SNIPPET:Lcom/mojang/blaze3d/pipeline/RenderPipeline$Snippet;
    3096: aastore
    3097: invokestatic  #177                // Method com/mojang/blaze3d/pipeline/RenderPipeline.builder:([Lcom/mojang/blaze3d/pipeline/RenderPipeline$Snippet;)Lcom/mojang/blaze3d/pipeline/RenderPipeline$Builder;
    3100: ldc_w         #648                // String pipeline/dragon_rays_depth
    3103: invokevirtual #371                // Method com/mojang/blaze3d/pipeline/RenderPipeline$Builder.withLocation:(Ljava/lang/String;)Lcom/mojang/blaze3d/pipeline/RenderPipeline$Builder;
    3106: ldc_w         #650                // String core/position
    3109: invokevirtual #217                // Method com/mojang/blaze3d/pipeline/RenderPipeline$Builder.withVertexShader:(Ljava/lang/String;)Lcom/mojang/blaze3d/pipeline/RenderPipeline$Builder;
    3112: ldc_w         #650                // String core/position
    3115: invokevirtual #220                // Method com/mojang/blaze3d/pipeline/RenderPipeline$Builder.withFragmentShader:(Ljava/lang/String;)Lcom/mojang/blaze3d/pipeline/RenderPipeline$Builder;
    3118: iconst_0
    3119: invokevirtual #544                // Method com/mojang/blaze3d/pipeline/RenderPipeline$Builder.withColorWrite:(Z)Lcom/mojang/blaze3d/pipeline/RenderPipeline$Builder;
    3122: getstatic     #282                // Field net/minecraft/client/render/VertexFormats.POSITION:Lcom/mojang/blaze3d/vertex/VertexFormat;
    3125: getstatic     #644                // Field com/mojang/blaze3d/vertex/VertexFormat$DrawMode.TRIANGLES:Lcom/mojang/blaze3d/vertex/VertexFormat$DrawMode;
    3128: invokevirtual #241                // Method com/mojang/blaze3d/pipeline/RenderPipeline$Builder.withVertexFormat:(Lcom/mojang/blaze3d/vertex/VertexFormat;Lcom/mojang/blaze3d/vertex/VertexFormat$DrawMode;)Lcom/mojang/blaze3d/pipeline/RenderPipeline$Builder;
    3131: invokevirtual #375                // Method com/mojang/blaze3d/pipeline/RenderPipeline$Builder.build:()Lcom/mojang/blaze3d/pipeline/RenderPipeline;
    3134: invokestatic  #377                // Method register:(Lcom/mojang/blaze3d/pipeline/RenderPipeline;)Lcom/mojang/blaze3d/pipeline/RenderPipeline;
    3137: putstatic     #652                // Field POSITION_DRAGON_RAYS_DEPTH:Lcom/mojang/blaze3d/pipeline/RenderPipeline;
    3140: iconst_1
    3141: anewarray     #11                 // class com/mojang/blaze3d/pipeline/RenderPipeline$Snippet
    3144: dup
    3145: iconst_0
    3146: getstatic     #284                // Field RENDERTYPE_END_PORTAL_SNIPPET:Lcom/mojang/blaze3d/pipeline/RenderPipeline$Snippet;
    3149: aastore
    3150: invokestatic  #177                // Method com/mojang/blaze3d/pipeline/RenderPipeline.builder:([Lcom/mojang/blaze3d/pipeline/RenderPipeline$Snippet;)Lcom/mojang/blaze3d/pipeline/RenderPipeline$Builder;
    3153: ldc_w         #654                // String pipeline/end_portal
    3156: invokevirtual #371                // Method com/mojang/blaze3d/pipeline/RenderPipeline$Builder.withLocation:(Ljava/lang/String;)Lcom/mojang/blaze3d/pipeline/RenderPipeline$Builder;
    3159: ldc_w         #656                // String PORTAL_LAYERS
    3162: bipush        15
    3164: invokevirtual #659                // Method com/mojang/blaze3d/pipeline/RenderPipeline$Builder.withShaderDefine:(Ljava/lang/String;I)Lcom/mojang/blaze3d/pipeline/RenderPipeline$Builder;
    3167: invokevirtual #375                // Method com/mojang/blaze3d/pipeline/RenderPipeline$Builder.build:()Lcom/mojang/blaze3d/pipeline/RenderPipeline;
    3170: invokestatic  #377                // Method register:(Lcom/mojang/blaze3d/pipeline/RenderPipeline;)Lcom/mojang/blaze3d/pipeline/RenderPipeline;
    3173: putstatic     #661                // Field END_PORTAL:Lcom/mojang/blaze3d/pipeline/RenderPipeline;
    3176: iconst_1
    3177: anewarray     #11                 // class com/mojang/blaze3d/pipeline/RenderPipeline$Snippet
    3180: dup
    3181: iconst_0
    3182: getstatic     #284                // Field RENDERTYPE_END_PORTAL_SNIPPET:Lcom/mojang/blaze3d/pipeline/RenderPipeline$Snippet;
    3185: aastore
    3186: invokestatic  #177                // Method com/mojang/blaze3d/pipeline/RenderPipeline.builder:([Lcom/mojang/blaze3d/pipeline/RenderPipeline$Snippet;)Lcom/mojang/blaze3d/pipeline/RenderPipeline$Builder;
    3189: ldc_w         #663                // String pipeline/end_gateway
    3192: invokevirtual #371                // Method com/mojang/blaze3d/pipeline/RenderPipeline$Builder.withLocation:(Ljava/lang/String;)Lcom/mojang/blaze3d/pipeline/RenderPipeline$Builder;
    3195: ldc_w         #656                // String PORTAL_LAYERS
    3198: bipush        16
    3200: invokevirtual #659                // Method com/mojang/blaze3d/pipeline/RenderPipeline$Builder.withShaderDefine:(Ljava/lang/String;I)Lcom/mojang/blaze3d/pipeline/RenderPipeline$Builder;
    3203: invokevirtual #375                // Method com/mojang/blaze3d/pipeline/RenderPipeline$Builder.build:()Lcom/mojang/blaze3d/pipeline/RenderPipeline;
    3206: invokestatic  #377                // Method register:(Lcom/mojang/blaze3d/pipeline/RenderPipeline;)Lcom/mojang/blaze3d/pipeline/RenderPipeline;
    3209: putstatic     #665                // Field END_GATEWAY:Lcom/mojang/blaze3d/pipeline/RenderPipeline;
    3212: iconst_1
    3213: anewarray     #11                 // class com/mojang/blaze3d/pipeline/RenderPipeline$Snippet
    3216: dup
    3217: iconst_0
    3218: getstatic     #307                // Field RENDERTYPE_CLOUDS_SNIPPET:Lcom/mojang/blaze3d/pipeline/RenderPipeline$Snippet;
    3221: aastore
    3222: invokestatic  #177                // Method com/mojang/blaze3d/pipeline/RenderPipeline.builder:([Lcom/mojang/blaze3d/pipeline/RenderPipeline$Snippet;)Lcom/mojang/blaze3d/pipeline/RenderPipeline$Builder;
    3225: ldc_w         #667                // String pipeline/flat_clouds
    3228: invokevirtual #371                // Method com/mojang/blaze3d/pipeline/RenderPipeline$Builder.withLocation:(Ljava/lang/String;)Lcom/mojang/blaze3d/pipeline/RenderPipeline$Builder;
    3231: iconst_0
    3232: invokevirtual #313                // Method com/mojang/blaze3d/pipeline/RenderPipeline$Builder.withCull:(Z)Lcom/mojang/blaze3d/pipeline/RenderPipeline$Builder;
    3235: invokevirtual #375                // Method com/mojang/blaze3d/pipeline/RenderPipeline$Builder.build:()Lcom/mojang/blaze3d/pipeline/RenderPipeline;
    3238: invokestatic  #377                // Method register:(Lcom/mojang/blaze3d/pipeline/RenderPipeline;)Lcom/mojang/blaze3d/pipeline/RenderPipeline;
    3241: putstatic     #669                // Field FLAT_CLOUDS:Lcom/mojang/blaze3d/pipeline/RenderPipeline;
    3244: iconst_1
    3245: anewarray     #11                 // class com/mojang/blaze3d/pipeline/RenderPipeline$Snippet
    3248: dup
    3249: iconst_0
    3250: getstatic     #307                // Field RENDERTYPE_CLOUDS_SNIPPET:Lcom/mojang/blaze3d/pipeline/RenderPipeline$Snippet;
    3253: aastore
    3254: invokestatic  #177                // Method com/mojang/blaze3d/pipeline/RenderPipeline.builder:([Lcom/mojang/blaze3d/pipeline/RenderPipeline$Snippet;)Lcom/mojang/blaze3d/pipeline/RenderPipeline$Builder;
    3257: ldc_w         #671                // String pipeline/clouds
    3260: invokevirtual #371                // Method com/mojang/blaze3d/pipeline/RenderPipeline$Builder.withLocation:(Ljava/lang/String;)Lcom/mojang/blaze3d/pipeline/RenderPipeline$Builder;
    3263: invokevirtual #375                // Method com/mojang/blaze3d/pipeline/RenderPipeline$Builder.build:()Lcom/mojang/blaze3d/pipeline/RenderPipeline;
    3266: invokestatic  #377                // Method register:(Lcom/mojang/blaze3d/pipeline/RenderPipeline;)Lcom/mojang/blaze3d/pipeline/RenderPipeline;
    3269: putstatic     #673                // Field CLOUDS:Lcom/mojang/blaze3d/pipeline/RenderPipeline;
    3272: iconst_1
    3273: anewarray     #11                 // class com/mojang/blaze3d/pipeline/RenderPipeline$Snippet
    3276: dup
    3277: iconst_0
    3278: getstatic     #320                // Field RENDERTYPE_LINES_SNIPPET:Lcom/mojang/blaze3d/pipeline/RenderPipeline$Snippet;
    3281: aastore
    3282: invokestatic  #177                // Method com/mojang/blaze3d/pipeline/RenderPipeline.builder:([Lcom/mojang/blaze3d/pipeline/RenderPipeline$Snippet;)Lcom/mojang/blaze3d/pipeline/RenderPipeline$Builder;
    3285: ldc_w         #675                // String pipeline/lines
    3288: invokevirtual #371                // Method com/mojang/blaze3d/pipeline/RenderPipeline$Builder.withLocation:(Ljava/lang/String;)Lcom/mojang/blaze3d/pipeline/RenderPipeline$Builder;
    3291: invokevirtual #375                // Method com/mojang/blaze3d/pipeline/RenderPipeline$Builder.build:()Lcom/mojang/blaze3d/pipeline/RenderPipeline;
    3294: invokestatic  #377                // Method register:(Lcom/mojang/blaze3d/pipeline/RenderPipeline;)Lcom/mojang/blaze3d/pipeline/RenderPipeline;
    3297: putstatic     #677                // Field LINES:Lcom/mojang/blaze3d/pipeline/RenderPipeline;
    3300: iconst_1
    3301: anewarray     #11                 // class com/mojang/blaze3d/pipeline/RenderPipeline$Snippet
    3304: dup
    3305: iconst_0
    3306: getstatic     #320                // Field RENDERTYPE_LINES_SNIPPET:Lcom/mojang/blaze3d/pipeline/RenderPipeline$Snippet;
    3309: aastore
    3310: invokestatic  #177                // Method com/mojang/blaze3d/pipeline/RenderPipeline.builder:([Lcom/mojang/blaze3d/pipeline/RenderPipeline$Snippet;)Lcom/mojang/blaze3d/pipeline/RenderPipeline$Builder;
    3313: ldc_w         #679                // String pipeline/secondary_block_outline
    3316: invokevirtual #371                // Method com/mojang/blaze3d/pipeline/RenderPipeline$Builder.withLocation:(Ljava/lang/String;)Lcom/mojang/blaze3d/pipeline/RenderPipeline$Builder;
    3319: iconst_0
    3320: invokevirtual #362                // Method com/mojang/blaze3d/pipeline/RenderPipeline$Builder.withDepthWrite:(Z)Lcom/mojang/blaze3d/pipeline/RenderPipeline$Builder;
    3323: invokevirtual #375                // Method com/mojang/blaze3d/pipeline/RenderPipeline$Builder.build:()Lcom/mojang/blaze3d/pipeline/RenderPipeline;
    3326: invokestatic  #377                // Method register:(Lcom/mojang/blaze3d/pipeline/RenderPipeline;)Lcom/mojang/blaze3d/pipeline/RenderPipeline;
    3329: putstatic     #681                // Field SECOND_BLOCK_OUTLINE:Lcom/mojang/blaze3d/pipeline/RenderPipeline;
    3332: iconst_1
    3333: anewarray     #11                 // class com/mojang/blaze3d/pipeline/RenderPipeline$Snippet
    3336: dup
    3337: iconst_0
    3338: getstatic     #320                // Field RENDERTYPE_LINES_SNIPPET:Lcom/mojang/blaze3d/pipeline/RenderPipeline$Snippet;
    3341: aastore
    3342: invokestatic  #177                // Method com/mojang/blaze3d/pipeline/RenderPipeline.builder:([Lcom/mojang/blaze3d/pipeline/RenderPipeline$Snippet;)Lcom/mojang/blaze3d/pipeline/RenderPipeline$Builder;
    3345: ldc_w         #683                // String pipeline/line_strip
    3348: invokevirtual #371                // Method com/mojang/blaze3d/pipeline/RenderPipeline$Builder.withLocation:(Ljava/lang/String;)Lcom/mojang/blaze3d/pipeline/RenderPipeline$Builder;
    3351: getstatic     #316                // Field net/minecraft/client/render/VertexFormats.POSITION_COLOR_NORMAL:Lcom/mojang/blaze3d/vertex/VertexFormat;
    3354: getstatic     #685                // Field com/mojang/blaze3d/vertex/VertexFormat$DrawMode.LINE_STRIP:Lcom/mojang/blaze3d/vertex/VertexFormat$DrawMode;
    3357: invokevirtual #241                // Method com/mojang/blaze3d/pipeline/RenderPipeline$Builder.withVertexFormat:(Lcom/mojang/blaze3d/vertex/VertexFormat;Lcom/mojang/blaze3d/vertex/VertexFormat$DrawMode;)Lcom/mojang/blaze3d/pipeline/RenderPipeline$Builder;
    3360: invokevirtual #375                // Method com/mojang/blaze3d/pipeline/RenderPipeline$Builder.build:()Lcom/mojang/blaze3d/pipeline/RenderPipeline;
    3363: invokestatic  #377                // Method register:(Lcom/mojang/blaze3d/pipeline/RenderPipeline;)Lcom/mojang/blaze3d/pipeline/RenderPipeline;
    3366: putstatic     #687                // Field LINE_STRIP:Lcom/mojang/blaze3d/pipeline/RenderPipeline;
    3369: iconst_1
    3370: anewarray     #11                 // class com/mojang/blaze3d/pipeline/RenderPipeline$Snippet
    3373: dup
    3374: iconst_0
    3375: getstatic     #197                // Field TRANSFORMS_AND_PROJECTION_SNIPPET:Lcom/mojang/blaze3d/pipeline/RenderPipeline$Snippet;
    3378: aastore
    3379: invokestatic  #177                // Method com/mojang/blaze3d/pipeline/RenderPipeline.builder:([Lcom/mojang/blaze3d/pipeline/RenderPipeline$Snippet;)Lcom/mojang/blaze3d/pipeline/RenderPipeline$Builder;
    3382: ldc_w         #689                // String pipeline/debug_line_strip
    3385: invokevirtual #371                // Method com/mojang/blaze3d/pipeline/RenderPipeline$Builder.withLocation:(Ljava/lang/String;)Lcom/mojang/blaze3d/pipeline/RenderPipeline$Builder;
    3388: ldc_w         #322                // String core/position_color
    3391: invokevirtual #217                // Method com/mojang/blaze3d/pipeline/RenderPipeline$Builder.withVertexShader:(Ljava/lang/String;)Lcom/mojang/blaze3d/pipeline/RenderPipeline$Builder;
    3394: ldc_w         #322                // String core/position_color
    3397: invokevirtual #220                // Method com/mojang/blaze3d/pipeline/RenderPipeline$Builder.withFragmentShader:(Ljava/lang/String;)Lcom/mojang/blaze3d/pipeline/RenderPipeline$Builder;
    3400: iconst_0
    3401: invokevirtual #313                // Method com/mojang/blaze3d/pipeline/RenderPipeline$Builder.withCull:(Z)Lcom/mojang/blaze3d/pipeline/RenderPipeline$Builder;
    3404: getstatic     #325                // Field net/minecraft/client/render/VertexFormats.POSITION_COLOR:Lcom/mojang/blaze3d/vertex/VertexFormat;
    3407: getstatic     #691                // Field com/mojang/blaze3d/vertex/VertexFormat$DrawMode.DEBUG_LINE_STRIP:Lcom/mojang/blaze3d/vertex/VertexFormat$DrawMode;
    3410: invokevirtual #241                // Method com/mojang/blaze3d/pipeline/RenderPipeline$Builder.withVertexFormat:(Lcom/mojang/blaze3d/vertex/VertexFormat;Lcom/mojang/blaze3d/vertex/VertexFormat$DrawMode;)Lcom/mojang/blaze3d/pipeline/RenderPipeline$Builder;
    3413: invokevirtual #375                // Method com/mojang/blaze3d/pipeline/RenderPipeline$Builder.build:()Lcom/mojang/blaze3d/pipeline/RenderPipeline;
    3416: invokestatic  #377                // Method register:(Lcom/mojang/blaze3d/pipeline/RenderPipeline;)Lcom/mojang/blaze3d/pipeline/RenderPipeline;
    3419: putstatic     #693                // Field DEBUG_LINE_STRIP:Lcom/mojang/blaze3d/pipeline/RenderPipeline;
    3422: iconst_1
    3423: anewarray     #11                 // class com/mojang/blaze3d/pipeline/RenderPipeline$Snippet
    3426: dup
    3427: iconst_0
    3428: getstatic     #327                // Field POSITION_COLOR_SNIPPET:Lcom/mojang/blaze3d/pipeline/RenderPipeline$Snippet;
    3431: aastore
    3432: invokestatic  #177                // Method com/mojang/blaze3d/pipeline/RenderPipeline.builder:([Lcom/mojang/blaze3d/pipeline/RenderPipeline$Snippet;)Lcom/mojang/blaze3d/pipeline/RenderPipeline$Builder;
    3435: ldc_w         #695                // String pipeline/debug_filled_box
    3438: invokevirtual #371                // Method com/mojang/blaze3d/pipeline/RenderPipeline$Builder.withLocation:(Ljava/lang/String;)Lcom/mojang/blaze3d/pipeline/RenderPipeline$Builder;
    3441: getstatic     #325                // Field net/minecraft/client/render/VertexFormats.POSITION_COLOR:Lcom/mojang/blaze3d/vertex/VertexFormat;
    3444: getstatic     #535                // Field com/mojang/blaze3d/vertex/VertexFormat$DrawMode.TRIANGLE_STRIP:Lcom/mojang/blaze3d/vertex/VertexFormat$DrawMode;
    3447: invokevirtual #241                // Method com/mojang/blaze3d/pipeline/RenderPipeline$Builder.withVertexFormat:(Lcom/mojang/blaze3d/vertex/VertexFormat;Lcom/mojang/blaze3d/vertex/VertexFormat$DrawMode;)Lcom/mojang/blaze3d/pipeline/RenderPipeline$Builder;
    3450: invokevirtual #375                // Method com/mojang/blaze3d/pipeline/RenderPipeline$Builder.build:()Lcom/mojang/blaze3d/pipeline/RenderPipeline;
    3453: invokestatic  #377                // Method register:(Lcom/mojang/blaze3d/pipeline/RenderPipeline;)Lcom/mojang/blaze3d/pipeline/RenderPipeline;
    3456: putstatic     #697                // Field DEBUG_FILLED_BOX:Lcom/mojang/blaze3d/pipeline/RenderPipeline;
    3459: iconst_1
    3460: anewarray     #11                 // class com/mojang/blaze3d/pipeline/RenderPipeline$Snippet
    3463: dup
    3464: iconst_0
    3465: getstatic     #327                // Field POSITION_COLOR_SNIPPET:Lcom/mojang/blaze3d/pipeline/RenderPipeline$Snippet;
    3468: aastore
    3469: invokestatic  #177                // Method com/mojang/blaze3d/pipeline/RenderPipeline.builder:([Lcom/mojang/blaze3d/pipeline/RenderPipeline$Snippet;)Lcom/mojang/blaze3d/pipeline/RenderPipeline$Builder;
    3472: ldc_w         #699                // String pipeline/debug_quads
    3475: invokevirtual #371                // Method com/mojang/blaze3d/pipeline/RenderPipeline$Builder.withLocation:(Ljava/lang/String;)Lcom/mojang/blaze3d/pipeline/RenderPipeline$Builder;
    3478: iconst_0
    3479: invokevirtual #313                // Method com/mojang/blaze3d/pipeline/RenderPipeline$Builder.withCull:(Z)Lcom/mojang/blaze3d/pipeline/RenderPipeline$Builder;
    3482: invokevirtual #375                // Method com/mojang/blaze3d/pipeline/RenderPipeline$Builder.build:()Lcom/mojang/blaze3d/pipeline/RenderPipeline;
    3485: invokestatic  #377                // Method register:(Lcom/mojang/blaze3d/pipeline/RenderPipeline;)Lcom/mojang/blaze3d/pipeline/RenderPipeline;
    3488: putstatic     #701                // Field DEBUG_QUADS:Lcom/mojang/blaze3d/pipeline/RenderPipeline;
    3491: iconst_1
    3492: anewarray     #11                 // class com/mojang/blaze3d/pipeline/RenderPipeline$Snippet
    3495: dup
    3496: iconst_0
    3497: getstatic     #327                // Field POSITION_COLOR_SNIPPET:Lcom/mojang/blaze3d/pipeline/RenderPipeline$Snippet;
    3500: aastore
    3501: invokestatic  #177                // Method com/mojang/blaze3d/pipeline/RenderPipeline.builder:([Lcom/mojang/blaze3d/pipeline/RenderPipeline$Snippet;)Lcom/mojang/blaze3d/pipeline/RenderPipeline$Builder;
    3504: ldc_w         #703                // String pipeline/debug_triangle_fan
    3507: invokevirtual #371                // Method com/mojang/blaze3d/pipeline/RenderPipeline$Builder.withLocation:(Ljava/lang/String;)Lcom/mojang/blaze3d/pipeline/RenderPipeline$Builder;
    3510: iconst_0
    3511: invokevirtual #313                // Method com/mojang/blaze3d/pipeline/RenderPipeline$Builder.withCull:(Z)Lcom/mojang/blaze3d/pipeline/RenderPipeline$Builder;
    3514: getstatic     #325                // Field net/minecraft/client/render/VertexFormats.POSITION_COLOR:Lcom/mojang/blaze3d/vertex/VertexFormat;
    3517: getstatic     #706                // Field com/mojang/blaze3d/vertex/VertexFormat$DrawMode.TRIANGLE_FAN:Lcom/mojang/blaze3d/vertex/VertexFormat$DrawMode;
    3520: invokevirtual #241                // Method com/mojang/blaze3d/pipeline/RenderPipeline$Builder.withVertexFormat:(Lcom/mojang/blaze3d/vertex/VertexFormat;Lcom/mojang/blaze3d/vertex/VertexFormat$DrawMode;)Lcom/mojang/blaze3d/pipeline/RenderPipeline$Builder;
    3523: invokevirtual #375                // Method com/mojang/blaze3d/pipeline/RenderPipeline$Builder.build:()Lcom/mojang/blaze3d/pipeline/RenderPipeline;
    3526: invokestatic  #377                // Method register:(Lcom/mojang/blaze3d/pipeline/RenderPipeline;)Lcom/mojang/blaze3d/pipeline/RenderPipeline;
    3529: putstatic     #708                // Field DEBUG_TRIANGLE_FAN:Lcom/mojang/blaze3d/pipeline/RenderPipeline;
    3532: iconst_1
    3533: anewarray     #11                 // class com/mojang/blaze3d/pipeline/RenderPipeline$Snippet
    3536: dup
    3537: iconst_0
    3538: getstatic     #327                // Field POSITION_COLOR_SNIPPET:Lcom/mojang/blaze3d/pipeline/RenderPipeline$Snippet;
    3541: aastore
    3542: invokestatic  #177                // Method com/mojang/blaze3d/pipeline/RenderPipeline.builder:([Lcom/mojang/blaze3d/pipeline/RenderPipeline$Snippet;)Lcom/mojang/blaze3d/pipeline/RenderPipeline$Builder;
    3545: ldc_w         #710                // String pipeline/debug_structure_quads
    3548: invokevirtual #371                // Method com/mojang/blaze3d/pipeline/RenderPipeline$Builder.withLocation:(Ljava/lang/String;)Lcom/mojang/blaze3d/pipeline/RenderPipeline$Builder;
    3551: iconst_0
    3552: invokevirtual #313                // Method com/mojang/blaze3d/pipeline/RenderPipeline$Builder.withCull:(Z)Lcom/mojang/blaze3d/pipeline/RenderPipeline$Builder;
    3555: iconst_0
    3556: invokevirtual #362                // Method com/mojang/blaze3d/pipeline/RenderPipeline$Builder.withDepthWrite:(Z)Lcom/mojang/blaze3d/pipeline/RenderPipeline$Builder;
    3559: invokevirtual #375                // Method com/mojang/blaze3d/pipeline/RenderPipeline$Builder.build:()Lcom/mojang/blaze3d/pipeline/RenderPipeline;
    3562: invokestatic  #377                // Method register:(Lcom/mojang/blaze3d/pipeline/RenderPipeline;)Lcom/mojang/blaze3d/pipeline/RenderPipeline;
    3565: putstatic     #712                // Field DEBUG_STRUCTURE_QUADS:Lcom/mojang/blaze3d/pipeline/RenderPipeline;
    3568: iconst_1
    3569: anewarray     #11                 // class com/mojang/blaze3d/pipeline/RenderPipeline$Snippet
    3572: dup
    3573: iconst_0
    3574: getstatic     #327                // Field POSITION_COLOR_SNIPPET:Lcom/mojang/blaze3d/pipeline/RenderPipeline$Snippet;
    3577: aastore
    3578: invokestatic  #177                // Method com/mojang/blaze3d/pipeline/RenderPipeline.builder:([Lcom/mojang/blaze3d/pipeline/RenderPipeline$Snippet;)Lcom/mojang/blaze3d/pipeline/RenderPipeline$Builder;
    3581: ldc_w         #714                // String pipeline/debug_section_quads
    3584: invokevirtual #371                // Method com/mojang/blaze3d/pipeline/RenderPipeline$Builder.withLocation:(Ljava/lang/String;)Lcom/mojang/blaze3d/pipeline/RenderPipeline$Builder;
    3587: invokevirtual #375                // Method com/mojang/blaze3d/pipeline/RenderPipeline$Builder.build:()Lcom/mojang/blaze3d/pipeline/RenderPipeline;
    3590: invokestatic  #377                // Method register:(Lcom/mojang/blaze3d/pipeline/RenderPipeline;)Lcom/mojang/blaze3d/pipeline/RenderPipeline;
    3593: putstatic     #716                // Field DEBUG_SECTION_QUADS:Lcom/mojang/blaze3d/pipeline/RenderPipeline;
    3596: iconst_1
    3597: anewarray     #11                 // class com/mojang/blaze3d/pipeline/RenderPipeline$Snippet
    3600: dup
    3601: iconst_0
    3602: getstatic     #197                // Field TRANSFORMS_AND_PROJECTION_SNIPPET:Lcom/mojang/blaze3d/pipeline/RenderPipeline$Snippet;
    3605: aastore
    3606: invokestatic  #177                // Method com/mojang/blaze3d/pipeline/RenderPipeline.builder:([Lcom/mojang/blaze3d/pipeline/RenderPipeline$Snippet;)Lcom/mojang/blaze3d/pipeline/RenderPipeline$Builder;
    3609: ldc_w         #718                // String pipeline/world_border
    3612: invokevirtual #371                // Method com/mojang/blaze3d/pipeline/RenderPipeline$Builder.withLocation:(Ljava/lang/String;)Lcom/mojang/blaze3d/pipeline/RenderPipeline$Builder;
    3615: ldc_w         #720                // String core/rendertype_world_border
    3618: invokevirtual #217                // Method com/mojang/blaze3d/pipeline/RenderPipeline$Builder.withVertexShader:(Ljava/lang/String;)Lcom/mojang/blaze3d/pipeline/RenderPipeline$Builder;
    3621: ldc_w         #720                // String core/rendertype_world_border
    3624: invokevirtual #220                // Method com/mojang/blaze3d/pipeline/RenderPipeline$Builder.withFragmentShader:(Ljava/lang/String;)Lcom/mojang/blaze3d/pipeline/RenderPipeline$Builder;
    3627: ldc           #222                // String Sampler0
    3629: invokevirtual #225                // Method com/mojang/blaze3d/pipeline/RenderPipeline$Builder.withSampler:(Ljava/lang/String;)Lcom/mojang/blaze3d/pipeline/RenderPipeline$Builder;
    3632: getstatic     #723                // Field com/mojang/blaze3d/pipeline/BlendFunction.OVERLAY:Lcom/mojang/blaze3d/pipeline/BlendFunction;
    3635: invokevirtual #270                // Method com/mojang/blaze3d/pipeline/RenderPipeline$Builder.withBlend:(Lcom/mojang/blaze3d/pipeline/BlendFunction;)Lcom/mojang/blaze3d/pipeline/RenderPipeline$Builder;
    3638: iconst_0
    3639: invokevirtual #313                // Method com/mojang/blaze3d/pipeline/RenderPipeline$Builder.withCull:(Z)Lcom/mojang/blaze3d/pipeline/RenderPipeline$Builder;
    3642: getstatic     #555                // Field net/minecraft/client/render/VertexFormats.POSITION_TEXTURE:Lcom/mojang/blaze3d/vertex/VertexFormat;
    3645: getstatic     #237                // Field com/mojang/blaze3d/vertex/VertexFormat$DrawMode.QUADS:Lcom/mojang/blaze3d/vertex/VertexFormat$DrawMode;
    3648: invokevirtual #241                // Method com/mojang/blaze3d/pipeline/RenderPipeline$Builder.withVertexFormat:(Lcom/mojang/blaze3d/vertex/VertexFormat;Lcom/mojang/blaze3d/vertex/VertexFormat$DrawMode;)Lcom/mojang/blaze3d/pipeline/RenderPipeline$Builder;
    3651: ldc_w         #724                // float -3.0f
    3654: ldc_w         #724                // float -3.0f
    3657: invokevirtual #588                // Method com/mojang/blaze3d/pipeline/RenderPipeline$Builder.withDepthBias:(FF)Lcom/mojang/blaze3d/pipeline/RenderPipeline$Builder;
    3660: invokevirtual #375                // Method com/mojang/blaze3d/pipeline/RenderPipeline$Builder.build:()Lcom/mojang/blaze3d/pipeline/RenderPipeline;
    3663: invokestatic  #377                // Method register:(Lcom/mojang/blaze3d/pipeline/RenderPipeline;)Lcom/mojang/blaze3d/pipeline/RenderPipeline;
    3666: putstatic     #726                // Field RENDERTYPE_WORLD_BORDER:Lcom/mojang/blaze3d/pipeline/RenderPipeline;
    3669: iconst_1
    3670: anewarray     #11                 // class com/mojang/blaze3d/pipeline/RenderPipeline$Snippet
    3673: dup
    3674: iconst_0
    3675: getstatic     #334                // Field PARTICLE_SNIPPET:Lcom/mojang/blaze3d/pipeline/RenderPipeline$Snippet;
    3678: aastore
    3679: invokestatic  #177                // Method com/mojang/blaze3d/pipeline/RenderPipeline.builder:([Lcom/mojang/blaze3d/pipeline/RenderPipeline$Snippet;)Lcom/mojang/blaze3d/pipeline/RenderPipeline$Builder;
    3682: ldc_w         #728                // String pipeline/opaque_particle
    3685: invokevirtual #371                // Method com/mojang/blaze3d/pipeline/RenderPipeline$Builder.withLocation:(Ljava/lang/String;)Lcom/mojang/blaze3d/pipeline/RenderPipeline$Builder;
    3688: invokevirtual #375                // Method com/mojang/blaze3d/pipeline/RenderPipeline$Builder.build:()Lcom/mojang/blaze3d/pipeline/RenderPipeline;
    3691: invokestatic  #377                // Method register:(Lcom/mojang/blaze3d/pipeline/RenderPipeline;)Lcom/mojang/blaze3d/pipeline/RenderPipeline;
    3694: putstatic     #730                // Field OPAQUE_PARTICLE:Lcom/mojang/blaze3d/pipeline/RenderPipeline;
    3697: iconst_1
    3698: anewarray     #11                 // class com/mojang/blaze3d/pipeline/RenderPipeline$Snippet
    3701: dup
    3702: iconst_0
    3703: getstatic     #334                // Field PARTICLE_SNIPPET:Lcom/mojang/blaze3d/pipeline/RenderPipeline$Snippet;
    3706: aastore
    3707: invokestatic  #177                // Method com/mojang/blaze3d/pipeline/RenderPipeline.builder:([Lcom/mojang/blaze3d/pipeline/RenderPipeline$Snippet;)Lcom/mojang/blaze3d/pipeline/RenderPipeline$Builder;
    3710: ldc_w         #732                // String pipeline/translucent_particle
    3713: invokevirtual #371                // Method com/mojang/blaze3d/pipeline/RenderPipeline$Builder.withLocation:(Ljava/lang/String;)Lcom/mojang/blaze3d/pipeline/RenderPipeline$Builder;
    3716: getstatic     #266                // Field com/mojang/blaze3d/pipeline/BlendFunction.TRANSLUCENT:Lcom/mojang/blaze3d/pipeline/BlendFunction;
    3719: invokevirtual #270                // Method com/mojang/blaze3d/pipeline/RenderPipeline$Builder.withBlend:(Lcom/mojang/blaze3d/pipeline/BlendFunction;)Lcom/mojang/blaze3d/pipeline/RenderPipeline$Builder;
    3722: invokevirtual #375                // Method com/mojang/blaze3d/pipeline/RenderPipeline$Builder.build:()Lcom/mojang/blaze3d/pipeline/RenderPipeline;
    3725: invokestatic  #377                // Method register:(Lcom/mojang/blaze3d/pipeline/RenderPipeline;)Lcom/mojang/blaze3d/pipeline/RenderPipeline;
    3728: putstatic     #734                // Field TRANSLUCENT_PARTICLE:Lcom/mojang/blaze3d/pipeline/RenderPipeline;
    3731: iconst_1
    3732: anewarray     #11                 // class com/mojang/blaze3d/pipeline/RenderPipeline$Snippet
    3735: dup
    3736: iconst_0
    3737: getstatic     #336                // Field WEATHER_SNIPPET:Lcom/mojang/blaze3d/pipeline/RenderPipeline$Snippet;
    3740: aastore
    3741: invokestatic  #177                // Method com/mojang/blaze3d/pipeline/RenderPipeline.builder:([Lcom/mojang/blaze3d/pipeline/RenderPipeline$Snippet;)Lcom/mojang/blaze3d/pipeline/RenderPipeline$Builder;
    3744: ldc_w         #736                // String pipeline/weather_depth_write
    3747: invokevirtual #371                // Method com/mojang/blaze3d/pipeline/RenderPipeline$Builder.withLocation:(Ljava/lang/String;)Lcom/mojang/blaze3d/pipeline/RenderPipeline$Builder;
    3750: invokevirtual #375                // Method com/mojang/blaze3d/pipeline/RenderPipeline$Builder.build:()Lcom/mojang/blaze3d/pipeline/RenderPipeline;
    3753: invokestatic  #377                // Method register:(Lcom/mojang/blaze3d/pipeline/RenderPipeline;)Lcom/mojang/blaze3d/pipeline/RenderPipeline;
    3756: putstatic     #738                // Field WEATHER_DEPTH:Lcom/mojang/blaze3d/pipeline/RenderPipeline;
    3759: iconst_1
    3760: anewarray     #11                 // class com/mojang/blaze3d/pipeline/RenderPipeline$Snippet
    3763: dup
    3764: iconst_0
    3765: getstatic     #336                // Field WEATHER_SNIPPET:Lcom/mojang/blaze3d/pipeline/RenderPipeline$Snippet;
    3768: aastore
    3769: invokestatic  #177                // Method com/mojang/blaze3d/pipeline/RenderPipeline.builder:([Lcom/mojang/blaze3d/pipeline/RenderPipeline$Snippet;)Lcom/mojang/blaze3d/pipeline/RenderPipeline$Builder;
    3772: ldc_w         #740                // String pipeline/weather_no_depth_write
    3775: invokevirtual #371                // Method com/mojang/blaze3d/pipeline/RenderPipeline$Builder.withLocation:(Ljava/lang/String;)Lcom/mojang/blaze3d/pipeline/RenderPipeline$Builder;
    3778: iconst_0
    3779: invokevirtual #362                // Method com/mojang/blaze3d/pipeline/RenderPipeline$Builder.withDepthWrite:(Z)Lcom/mojang/blaze3d/pipeline/RenderPipeline$Builder;
    3782: invokevirtual #375                // Method com/mojang/blaze3d/pipeline/RenderPipeline$Builder.build:()Lcom/mojang/blaze3d/pipeline/RenderPipeline;
    3785: invokestatic  #377                // Method register:(Lcom/mojang/blaze3d/pipeline/RenderPipeline;)Lcom/mojang/blaze3d/pipeline/RenderPipeline;
    3788: putstatic     #742                // Field WEATHER_NO_DEPTH:Lcom/mojang/blaze3d/pipeline/RenderPipeline;
    3791: iconst_1
    3792: anewarray     #11                 // class com/mojang/blaze3d/pipeline/RenderPipeline$Snippet
    3795: dup
    3796: iconst_0
    3797: getstatic     #207                // Field TRANSFORMS_PROJECTION_FOG_SNIPPET:Lcom/mojang/blaze3d/pipeline/RenderPipeline$Snippet;
    3800: aastore
    3801: invokestatic  #177                // Method com/mojang/blaze3d/pipeline/RenderPipeline.builder:([Lcom/mojang/blaze3d/pipeline/RenderPipeline$Snippet;)Lcom/mojang/blaze3d/pipeline/RenderPipeline$Builder;
    3804: ldc_w         #744                // String pipeline/sky
    3807: invokevirtual #371                // Method com/mojang/blaze3d/pipeline/RenderPipeline$Builder.withLocation:(Ljava/lang/String;)Lcom/mojang/blaze3d/pipeline/RenderPipeline$Builder;
    3810: ldc_w         #746                // String core/sky
    3813: invokevirtual #217                // Method com/mojang/blaze3d/pipeline/RenderPipeline$Builder.withVertexShader:(Ljava/lang/String;)Lcom/mojang/blaze3d/pipeline/RenderPipeline$Builder;
    3816: ldc_w         #746                // String core/sky
    3819: invokevirtual #220                // Method com/mojang/blaze3d/pipeline/RenderPipeline$Builder.withFragmentShader:(Ljava/lang/String;)Lcom/mojang/blaze3d/pipeline/RenderPipeline$Builder;
    3822: iconst_0
    3823: invokevirtual #362                // Method com/mojang/blaze3d/pipeline/RenderPipeline$Builder.withDepthWrite:(Z)Lcom/mojang/blaze3d/pipeline/RenderPipeline$Builder;
    3826: getstatic     #282                // Field net/minecraft/client/render/VertexFormats.POSITION:Lcom/mojang/blaze3d/vertex/VertexFormat;
    3829: getstatic     #706                // Field com/mojang/blaze3d/vertex/VertexFormat$DrawMode.TRIANGLE_FAN:Lcom/mojang/blaze3d/vertex/VertexFormat$DrawMode;
    3832: invokevirtual #241                // Method com/mojang/blaze3d/pipeline/RenderPipeline$Builder.withVertexFormat:(Lcom/mojang/blaze3d/vertex/VertexFormat;Lcom/mojang/blaze3d/vertex/VertexFormat$DrawMode;)Lcom/mojang/blaze3d/pipeline/RenderPipeline$Builder;
    3835: invokevirtual #375                // Method com/mojang/blaze3d/pipeline/RenderPipeline$Builder.build:()Lcom/mojang/blaze3d/pipeline/RenderPipeline;
    3838: invokestatic  #377                // Method register:(Lcom/mojang/blaze3d/pipeline/RenderPipeline;)Lcom/mojang/blaze3d/pipeline/RenderPipeline;
    3841: putstatic     #748                // Field POSITION_SKY:Lcom/mojang/blaze3d/pipeline/RenderPipeline;
    3844: iconst_1
    3845: anewarray     #11                 // class com/mojang/blaze3d/pipeline/RenderPipeline$Snippet
    3848: dup
    3849: iconst_0
    3850: getstatic     #197                // Field TRANSFORMS_AND_PROJECTION_SNIPPET:Lcom/mojang/blaze3d/pipeline/RenderPipeline$Snippet;
    3853: aastore
    3854: invokestatic  #177                // Method com/mojang/blaze3d/pipeline/RenderPipeline.builder:([Lcom/mojang/blaze3d/pipeline/RenderPipeline$Snippet;)Lcom/mojang/blaze3d/pipeline/RenderPipeline$Builder;
    3857: ldc_w         #750                // String pipeline/end_sky
    3860: invokevirtual #371                // Method com/mojang/blaze3d/pipeline/RenderPipeline$Builder.withLocation:(Ljava/lang/String;)Lcom/mojang/blaze3d/pipeline/RenderPipeline$Builder;
    3863: ldc_w         #342                // String core/position_tex_color
    3866: invokevirtual #217                // Method com/mojang/blaze3d/pipeline/RenderPipeline$Builder.withVertexShader:(Ljava/lang/String;)Lcom/mojang/blaze3d/pipeline/RenderPipeline$Builder;
    3869: ldc_w         #342                // String core/position_tex_color
    3872: invokevirtual #220                // Method com/mojang/blaze3d/pipeline/RenderPipeline$Builder.withFragmentShader:(Ljava/lang/String;)Lcom/mojang/blaze3d/pipeline/RenderPipeline$Builder;
    3875: ldc           #222                // String Sampler0
    3877: invokevirtual #225                // Method com/mojang/blaze3d/pipeline/RenderPipeline$Builder.withSampler:(Ljava/lang/String;)Lcom/mojang/blaze3d/pipeline/RenderPipeline$Builder;
    3880: getstatic     #266                // Field com/mojang/blaze3d/pipeline/BlendFunction.TRANSLUCENT:Lcom/mojang/blaze3d/pipeline/BlendFunction;
    3883: invokevirtual #270                // Method com/mojang/blaze3d/pipeline/RenderPipeline$Builder.withBlend:(Lcom/mojang/blaze3d/pipeline/BlendFunction;)Lcom/mojang/blaze3d/pipeline/RenderPipeline$Builder;
    3886: iconst_0
    3887: invokevirtual #362                // Method com/mojang/blaze3d/pipeline/RenderPipeline$Builder.withDepthWrite:(Z)Lcom/mojang/blaze3d/pipeline/RenderPipeline$Builder;
    3890: getstatic     #345                // Field net/minecraft/client/render/VertexFormats.POSITION_TEXTURE_COLOR:Lcom/mojang/blaze3d/vertex/VertexFormat;
    3893: getstatic     #237                // Field com/mojang/blaze3d/vertex/VertexFormat$DrawMode.QUADS:Lcom/mojang/blaze3d/vertex/VertexFormat$DrawMode;
    3896: invokevirtual #241                // Method com/mojang/blaze3d/pipeline/RenderPipeline$Builder.withVertexFormat:(Lcom/mojang/blaze3d/vertex/VertexFormat;Lcom/mojang/blaze3d/vertex/VertexFormat$DrawMode;)Lcom/mojang/blaze3d/pipeline/RenderPipeline$Builder;
    3899: invokevirtual #375                // Method com/mojang/blaze3d/pipeline/RenderPipeline$Builder.build:()Lcom/mojang/blaze3d/pipeline/RenderPipeline;
    3902: invokestatic  #377                // Method register:(Lcom/mojang/blaze3d/pipeline/RenderPipeline;)Lcom/mojang/blaze3d/pipeline/RenderPipeline;
    3905: putstatic     #752                // Field POSITION_TEX_COLOR_END_SKY:Lcom/mojang/blaze3d/pipeline/RenderPipeline;
    3908: iconst_1
    3909: anewarray     #11                 // class com/mojang/blaze3d/pipeline/RenderPipeline$Snippet
    3912: dup
    3913: iconst_0
    3914: getstatic     #197                // Field TRANSFORMS_AND_PROJECTION_SNIPPET:Lcom/mojang/blaze3d/pipeline/RenderPipeline$Snippet;
    3917: aastore
    3918: invokestatic  #177                // Method com/mojang/blaze3d/pipeline/RenderPipeline.builder:([Lcom/mojang/blaze3d/pipeline/RenderPipeline$Snippet;)Lcom/mojang/blaze3d/pipeline/RenderPipeline$Builder;
    3921: ldc_w         #754                // String pipeline/sunrise_sunset
    3924: invokevirtual #371                // Method com/mojang/blaze3d/pipeline/RenderPipeline$Builder.withLocation:(Ljava/lang/String;)Lcom/mojang/blaze3d/pipeline/RenderPipeline$Builder;
    3927: ldc_w         #322                // String core/position_color
    3930: invokevirtual #217                // Method com/mojang/blaze3d/pipeline/RenderPipeline$Builder.withVertexShader:(Ljava/lang/String;)Lcom/mojang/blaze3d/pipeline/RenderPipeline$Builder;
    3933: ldc_w         #322                // String core/position_color
    3936: invokevirtual #220                // Method com/mojang/blaze3d/pipeline/RenderPipeline$Builder.withFragmentShader:(Ljava/lang/String;)Lcom/mojang/blaze3d/pipeline/RenderPipeline$Builder;
    3939: getstatic     #266                // Field com/mojang/blaze3d/pipeline/BlendFunction.TRANSLUCENT:Lcom/mojang/blaze3d/pipeline/BlendFunction;
    3942: invokevirtual #270                // Method com/mojang/blaze3d/pipeline/RenderPipeline$Builder.withBlend:(Lcom/mojang/blaze3d/pipeline/BlendFunction;)Lcom/mojang/blaze3d/pipeline/RenderPipeline$Builder;
    3945: iconst_0
    3946: invokevirtual #362                // Method com/mojang/blaze3d/pipeline/RenderPipeline$Builder.withDepthWrite:(Z)Lcom/mojang/blaze3d/pipeline/RenderPipeline$Builder;
    3949: getstatic     #325                // Field net/minecraft/client/render/VertexFormats.POSITION_COLOR:Lcom/mojang/blaze3d/vertex/VertexFormat;
    3952: getstatic     #706                // Field com/mojang/blaze3d/vertex/VertexFormat$DrawMode.TRIANGLE_FAN:Lcom/mojang/blaze3d/vertex/VertexFormat$DrawMode;
    3955: invokevirtual #241                // Method com/mojang/blaze3d/pipeline/RenderPipeline$Builder.withVertexFormat:(Lcom/mojang/blaze3d/vertex/VertexFormat;Lcom/mojang/blaze3d/vertex/VertexFormat$DrawMode;)Lcom/mojang/blaze3d/pipeline/RenderPipeline$Builder;
    3958: invokevirtual #375                // Method com/mojang/blaze3d/pipeline/RenderPipeline$Builder.build:()Lcom/mojang/blaze3d/pipeline/RenderPipeline;
    3961: invokestatic  #377                // Method register:(Lcom/mojang/blaze3d/pipeline/RenderPipeline;)Lcom/mojang/blaze3d/pipeline/RenderPipeline;
    3964: putstatic     #756                // Field POSITION_COLOR_SUNRISE_SUNSET:Lcom/mojang/blaze3d/pipeline/RenderPipeline;
    3967: iconst_1
    3968: anewarray     #11                 // class com/mojang/blaze3d/pipeline/RenderPipeline$Snippet
    3971: dup
    3972: iconst_0
    3973: getstatic     #197                // Field TRANSFORMS_AND_PROJECTION_SNIPPET:Lcom/mojang/blaze3d/pipeline/RenderPipeline$Snippet;
    3976: aastore
    3977: invokestatic  #177                // Method com/mojang/blaze3d/pipeline/RenderPipeline.builder:([Lcom/mojang/blaze3d/pipeline/RenderPipeline$Snippet;)Lcom/mojang/blaze3d/pipeline/RenderPipeline$Builder;
    3980: ldc_w         #758                // String pipeline/stars
    3983: invokevirtual #371                // Method com/mojang/blaze3d/pipeline/RenderPipeline$Builder.withLocation:(Ljava/lang/String;)Lcom/mojang/blaze3d/pipeline/RenderPipeline$Builder;
    3986: ldc_w         #760                // String core/stars
    3989: invokevirtual #217                // Method com/mojang/blaze3d/pipeline/RenderPipeline$Builder.withVertexShader:(Ljava/lang/String;)Lcom/mojang/blaze3d/pipeline/RenderPipeline$Builder;
    3992: ldc_w         #760                // String core/stars
    3995: invokevirtual #220                // Method com/mojang/blaze3d/pipeline/RenderPipeline$Builder.withFragmentShader:(Ljava/lang/String;)Lcom/mojang/blaze3d/pipeline/RenderPipeline$Builder;
    3998: getstatic     #723                // Field com/mojang/blaze3d/pipeline/BlendFunction.OVERLAY:Lcom/mojang/blaze3d/pipeline/BlendFunction;
    4001: invokevirtual #270                // Method com/mojang/blaze3d/pipeline/RenderPipeline$Builder.withBlend:(Lcom/mojang/blaze3d/pipeline/BlendFunction;)Lcom/mojang/blaze3d/pipeline/RenderPipeline$Builder;
    4004: iconst_0
    4005: invokevirtual #362                // Method com/mojang/blaze3d/pipeline/RenderPipeline$Builder.withDepthWrite:(Z)Lcom/mojang/blaze3d/pipeline/RenderPipeline$Builder;
    4008: getstatic     #282                // Field net/minecraft/client/render/VertexFormats.POSITION:Lcom/mojang/blaze3d/vertex/VertexFormat;
    4011: getstatic     #237                // Field com/mojang/blaze3d/vertex/VertexFormat$DrawMode.QUADS:Lcom/mojang/blaze3d/vertex/VertexFormat$DrawMode;
    4014: invokevirtual #241                // Method com/mojang/blaze3d/pipeline/RenderPipeline$Builder.withVertexFormat:(Lcom/mojang/blaze3d/vertex/VertexFormat;Lcom/mojang/blaze3d/vertex/VertexFormat$DrawMode;)Lcom/mojang/blaze3d/pipeline/RenderPipeline$Builder;
    4017: invokevirtual #375                // Method com/mojang/blaze3d/pipeline/RenderPipeline$Builder.build:()Lcom/mojang/blaze3d/pipeline/RenderPipeline;
    4020: invokestatic  #377                // Method register:(Lcom/mojang/blaze3d/pipeline/RenderPipeline;)Lcom/mojang/blaze3d/pipeline/RenderPipeline;
    4023: putstatic     #762                // Field POSITION_STARS:Lcom/mojang/blaze3d/pipeline/RenderPipeline;
    4026: iconst_1
    4027: anewarray     #11                 // class com/mojang/blaze3d/pipeline/RenderPipeline$Snippet
    4030: dup
    4031: iconst_0
    4032: getstatic     #197                // Field TRANSFORMS_AND_PROJECTION_SNIPPET:Lcom/mojang/blaze3d/pipeline/RenderPipeline$Snippet;
    4035: aastore
    4036: invokestatic  #177                // Method com/mojang/blaze3d/pipeline/RenderPipeline.builder:([Lcom/mojang/blaze3d/pipeline/RenderPipeline$Snippet;)Lcom/mojang/blaze3d/pipeline/RenderPipeline$Builder;
    4039: ldc_w         #764                // String pipeline/celestial
    4042: invokevirtual #371                // Method com/mojang/blaze3d/pipeline/RenderPipeline$Builder.withLocation:(Ljava/lang/String;)Lcom/mojang/blaze3d/pipeline/RenderPipeline$Builder;
    4045: ldc_w         #342                // String core/position_tex_color
    4048: invokevirtual #217                // Method com/mojang/blaze3d/pipeline/RenderPipeline$Builder.withVertexShader:(Ljava/lang/String;)Lcom/mojang/blaze3d/pipeline/RenderPipeline$Builder;
    4051: ldc_w         #342                // String core/position_tex_color
    4054: invokevirtual #220                // Method com/mojang/blaze3d/pipeline/RenderPipeline$Builder.withFragmentShader:(Ljava/lang/String;)Lcom/mojang/blaze3d/pipeline/RenderPipeline$Builder;
    4057: ldc           #222                // String Sampler0
    4059: invokevirtual #225                // Method com/mojang/blaze3d/pipeline/RenderPipeline$Builder.withSampler:(Ljava/lang/String;)Lcom/mojang/blaze3d/pipeline/RenderPipeline$Builder;
    4062: getstatic     #723                // Field com/mojang/blaze3d/pipeline/BlendFunction.OVERLAY:Lcom/mojang/blaze3d/pipeline/BlendFunction;
    4065: invokevirtual #270                // Method com/mojang/blaze3d/pipeline/RenderPipeline$Builder.withBlend:(Lcom/mojang/blaze3d/pipeline/BlendFunction;)Lcom/mojang/blaze3d/pipeline/RenderPipeline$Builder;
    4068: iconst_0
    4069: invokevirtual #362                // Method com/mojang/blaze3d/pipeline/RenderPipeline$Builder.withDepthWrite:(Z)Lcom/mojang/blaze3d/pipeline/RenderPipeline$Builder;
    4072: getstatic     #345                // Field net/minecraft/client/render/VertexFormats.POSITION_TEXTURE_COLOR:Lcom/mojang/blaze3d/vertex/VertexFormat;
    4075: getstatic     #237                // Field com/mojang/blaze3d/vertex/VertexFormat$DrawMode.QUADS:Lcom/mojang/blaze3d/vertex/VertexFormat$DrawMode;
    4078: invokevirtual #241                // Method com/mojang/blaze3d/pipeline/RenderPipeline$Builder.withVertexFormat:(Lcom/mojang/blaze3d/vertex/VertexFormat;Lcom/mojang/blaze3d/vertex/VertexFormat$DrawMode;)Lcom/mojang/blaze3d/pipeline/RenderPipeline$Builder;
    4081: invokevirtual #375                // Method com/mojang/blaze3d/pipeline/RenderPipeline$Builder.build:()Lcom/mojang/blaze3d/pipeline/RenderPipeline;
    4084: invokestatic  #377                // Method register:(Lcom/mojang/blaze3d/pipeline/RenderPipeline;)Lcom/mojang/blaze3d/pipeline/RenderPipeline;
    4087: putstatic     #766                // Field POSITION_TEX_COLOR_CELESTIAL:Lcom/mojang/blaze3d/pipeline/RenderPipeline;
    4090: iconst_1
    4091: anewarray     #11                 // class com/mojang/blaze3d/pipeline/RenderPipeline$Snippet
    4094: dup
    4095: iconst_0
    4096: getstatic     #340                // Field GUI_SNIPPET:Lcom/mojang/blaze3d/pipeline/RenderPipeline$Snippet;
    4099: aastore
    4100: invokestatic  #177                // Method com/mojang/blaze3d/pipeline/RenderPipeline.builder:([Lcom/mojang/blaze3d/pipeline/RenderPipeline$Snippet;)Lcom/mojang/blaze3d/pipeline/RenderPipeline$Builder;
    4103: ldc_w         #768                // String pipeline/gui
    4106: invokevirtual #371                // Method com/mojang/blaze3d/pipeline/RenderPipeline$Builder.withLocation:(Ljava/lang/String;)Lcom/mojang/blaze3d/pipeline/RenderPipeline$Builder;
    4109: invokevirtual #375                // Method com/mojang/blaze3d/pipeline/RenderPipeline$Builder.build:()Lcom/mojang/blaze3d/pipeline/RenderPipeline;
    4112: invokestatic  #377                // Method register:(Lcom/mojang/blaze3d/pipeline/RenderPipeline;)Lcom/mojang/blaze3d/pipeline/RenderPipeline;
    4115: putstatic     #770                // Field GUI:Lcom/mojang/blaze3d/pipeline/RenderPipeline;
    4118: iconst_1
    4119: anewarray     #11                 // class com/mojang/blaze3d/pipeline/RenderPipeline$Snippet
    4122: dup
    4123: iconst_0
    4124: getstatic     #340                // Field GUI_SNIPPET:Lcom/mojang/blaze3d/pipeline/RenderPipeline$Snippet;
    4127: aastore
    4128: invokestatic  #177                // Method com/mojang/blaze3d/pipeline/RenderPipeline.builder:([Lcom/mojang/blaze3d/pipeline/RenderPipeline$Snippet;)Lcom/mojang/blaze3d/pipeline/RenderPipeline$Builder;
    4131: ldc_w         #772                // String pipeline/gui_invert
    4134: invokevirtual #371                // Method com/mojang/blaze3d/pipeline/RenderPipeline$Builder.withLocation:(Ljava/lang/String;)Lcom/mojang/blaze3d/pipeline/RenderPipeline$Builder;
    4137: getstatic     #775                // Field com/mojang/blaze3d/pipeline/BlendFunction.INVERT:Lcom/mojang/blaze3d/pipeline/BlendFunction;
    4140: invokevirtual #270                // Method com/mojang/blaze3d/pipeline/RenderPipeline$Builder.withBlend:(Lcom/mojang/blaze3d/pipeline/BlendFunction;)Lcom/mojang/blaze3d/pipeline/RenderPipeline$Builder;
    4143: invokevirtual #375                // Method com/mojang/blaze3d/pipeline/RenderPipeline$Builder.build:()Lcom/mojang/blaze3d/pipeline/RenderPipeline;
    4146: invokestatic  #377                // Method register:(Lcom/mojang/blaze3d/pipeline/RenderPipeline;)Lcom/mojang/blaze3d/pipeline/RenderPipeline;
    4149: putstatic     #777                // Field GUI_INVERT:Lcom/mojang/blaze3d/pipeline/RenderPipeline;
    4152: iconst_1
    4153: anewarray     #11                 // class com/mojang/blaze3d/pipeline/RenderPipeline$Snippet
    4156: dup
    4157: iconst_0
    4158: getstatic     #340                // Field GUI_SNIPPET:Lcom/mojang/blaze3d/pipeline/RenderPipeline$Snippet;
    4161: aastore
    4162: invokestatic  #177                // Method com/mojang/blaze3d/pipeline/RenderPipeline.builder:([Lcom/mojang/blaze3d/pipeline/RenderPipeline$Snippet;)Lcom/mojang/blaze3d/pipeline/RenderPipeline$Builder;
    4165: ldc_w         #779                // String pipeline/gui_text_highlight
    4168: invokevirtual #371                // Method com/mojang/blaze3d/pipeline/RenderPipeline$Builder.withLocation:(Ljava/lang/String;)Lcom/mojang/blaze3d/pipeline/RenderPipeline$Builder;
    4171: getstatic     #487                // Field com/mojang/blaze3d/pipeline/BlendFunction.ADDITIVE:Lcom/mojang/blaze3d/pipeline/BlendFunction;
    4174: invokevirtual #270                // Method com/mojang/blaze3d/pipeline/RenderPipeline$Builder.withBlend:(Lcom/mojang/blaze3d/pipeline/BlendFunction;)Lcom/mojang/blaze3d/pipeline/RenderPipeline$Builder;
    4177: invokevirtual #375                // Method com/mojang/blaze3d/pipeline/RenderPipeline$Builder.build:()Lcom/mojang/blaze3d/pipeline/RenderPipeline;
    4180: invokestatic  #377                // Method register:(Lcom/mojang/blaze3d/pipeline/RenderPipeline;)Lcom/mojang/blaze3d/pipeline/RenderPipeline;
    4183: putstatic     #781                // Field GUI_TEXT_HIGHLIGHT:Lcom/mojang/blaze3d/pipeline/RenderPipeline;
    4186: iconst_1
    4187: anewarray     #11                 // class com/mojang/blaze3d/pipeline/RenderPipeline$Snippet
    4190: dup
    4191: iconst_0
    4192: getstatic     #347                // Field POSITION_TEX_COLOR_SNIPPET:Lcom/mojang/blaze3d/pipeline/RenderPipeline$Snippet;
    4195: aastore
    4196: invokestatic  #177                // Method com/mojang/blaze3d/pipeline/RenderPipeline.builder:([Lcom/mojang/blaze3d/pipeline/RenderPipeline$Snippet;)Lcom/mojang/blaze3d/pipeline/RenderPipeline$Builder;
    4199: ldc_w         #783                // String pipeline/gui_textured
    4202: invokevirtual #371                // Method com/mojang/blaze3d/pipeline/RenderPipeline$Builder.withLocation:(Ljava/lang/String;)Lcom/mojang/blaze3d/pipeline/RenderPipeline$Builder;
    4205: invokevirtual #375                // Method com/mojang/blaze3d/pipeline/RenderPipeline$Builder.build:()Lcom/mojang/blaze3d/pipeline/RenderPipeline;
    4208: invokestatic  #377                // Method register:(Lcom/mojang/blaze3d/pipeline/RenderPipeline;)Lcom/mojang/blaze3d/pipeline/RenderPipeline;
    4211: putstatic     #785                // Field GUI_TEXTURED:Lcom/mojang/blaze3d/pipeline/RenderPipeline;
    4214: iconst_1
    4215: anewarray     #11                 // class com/mojang/blaze3d/pipeline/RenderPipeline$Snippet
    4218: dup
    4219: iconst_0
    4220: getstatic     #347                // Field POSITION_TEX_COLOR_SNIPPET:Lcom/mojang/blaze3d/pipeline/RenderPipeline$Snippet;
    4223: aastore
    4224: invokestatic  #177                // Method com/mojang/blaze3d/pipeline/RenderPipeline.builder:([Lcom/mojang/blaze3d/pipeline/RenderPipeline$Snippet;)Lcom/mojang/blaze3d/pipeline/RenderPipeline$Builder;
    4227: ldc_w         #787                // String pipeline/gui_textured_premultiplied_alpha
    4230: invokevirtual #371                // Method com/mojang/blaze3d/pipeline/RenderPipeline$Builder.withLocation:(Ljava/lang/String;)Lcom/mojang/blaze3d/pipeline/RenderPipeline$Builder;
    4233: getstatic     #790                // Field com/mojang/blaze3d/pipeline/BlendFunction.TRANSLUCENT_PREMULTIPLIED_ALPHA:Lcom/mojang/blaze3d/pipeline/BlendFunction;
    4236: invokevirtual #270                // Method com/mojang/blaze3d/pipeline/RenderPipeline$Builder.withBlend:(Lcom/mojang/blaze3d/pipeline/BlendFunction;)Lcom/mojang/blaze3d/pipeline/RenderPipeline$Builder;
    4239: invokevirtual #375                // Method com/mojang/blaze3d/pipeline/RenderPipeline$Builder.build:()Lcom/mojang/blaze3d/pipeline/RenderPipeline;
    4242: invokestatic  #377                // Method register:(Lcom/mojang/blaze3d/pipeline/RenderPipeline;)Lcom/mojang/blaze3d/pipeline/RenderPipeline;
    4245: putstatic     #792                // Field GUI_TEXTURED_PREMULTIPLIED_ALPHA:Lcom/mojang/blaze3d/pipeline/RenderPipeline;
    4248: iconst_1
    4249: anewarray     #11                 // class com/mojang/blaze3d/pipeline/RenderPipeline$Snippet
    4252: dup
    4253: iconst_0
    4254: getstatic     #347                // Field POSITION_TEX_COLOR_SNIPPET:Lcom/mojang/blaze3d/pipeline/RenderPipeline$Snippet;
    4257: aastore
    4258: invokestatic  #177                // Method com/mojang/blaze3d/pipeline/RenderPipeline.builder:([Lcom/mojang/blaze3d/pipeline/RenderPipeline$Snippet;)Lcom/mojang/blaze3d/pipeline/RenderPipeline$Builder;
    4261: ldc_w         #794                // String pipeline/block_screen_effect
    4264: invokevirtual #371                // Method com/mojang/blaze3d/pipeline/RenderPipeline$Builder.withLocation:(Ljava/lang/String;)Lcom/mojang/blaze3d/pipeline/RenderPipeline$Builder;
    4267: getstatic     #355                // Field com/mojang/blaze3d/platform/DepthTestFunction.NO_DEPTH_TEST:Lcom/mojang/blaze3d/platform/DepthTestFunction;
    4270: invokevirtual #359                // Method com/mojang/blaze3d/pipeline/RenderPipeline$Builder.withDepthTestFunction:(Lcom/mojang/blaze3d/platform/DepthTestFunction;)Lcom/mojang/blaze3d/pipeline/RenderPipeline$Builder;
    4273: iconst_0
    4274: invokevirtual #362                // Method com/mojang/blaze3d/pipeline/RenderPipeline$Builder.withDepthWrite:(Z)Lcom/mojang/blaze3d/pipeline/RenderPipeline$Builder;
    4277: invokevirtual #375                // Method com/mojang/blaze3d/pipeline/RenderPipeline$Builder.build:()Lcom/mojang/blaze3d/pipeline/RenderPipeline;
    4280: invokestatic  #377                // Method register:(Lcom/mojang/blaze3d/pipeline/RenderPipeline;)Lcom/mojang/blaze3d/pipeline/RenderPipeline;
    4283: putstatic     #796                // Field BLOCK_SCREEN_EFFECT:Lcom/mojang/blaze3d/pipeline/RenderPipeline;
    4286: iconst_1
    4287: anewarray     #11                 // class com/mojang/blaze3d/pipeline/RenderPipeline$Snippet
    4290: dup
    4291: iconst_0
    4292: getstatic     #347                // Field POSITION_TEX_COLOR_SNIPPET:Lcom/mojang/blaze3d/pipeline/RenderPipeline$Snippet;
    4295: aastore
    4296: invokestatic  #177                // Method com/mojang/blaze3d/pipeline/RenderPipeline.builder:([Lcom/mojang/blaze3d/pipeline/RenderPipeline$Snippet;)Lcom/mojang/blaze3d/pipeline/RenderPipeline$Builder;
    4299: ldc_w         #798                // String pipeline/fire_screen_effect
    4302: invokevirtual #371                // Method com/mojang/blaze3d/pipeline/RenderPipeline$Builder.withLocation:(Ljava/lang/String;)Lcom/mojang/blaze3d/pipeline/RenderPipeline$Builder;
    4305: getstatic     #355                // Field com/mojang/blaze3d/platform/DepthTestFunction.NO_DEPTH_TEST:Lcom/mojang/blaze3d/platform/DepthTestFunction;
    4308: invokevirtual #359                // Method com/mojang/blaze3d/pipeline/RenderPipeline$Builder.withDepthTestFunction:(Lcom/mojang/blaze3d/platform/DepthTestFunction;)Lcom/mojang/blaze3d/pipeline/RenderPipeline$Builder;
    4311: iconst_0
    4312: invokevirtual #362                // Method com/mojang/blaze3d/pipeline/RenderPipeline$Builder.withDepthWrite:(Z)Lcom/mojang/blaze3d/pipeline/RenderPipeline$Builder;
    4315: invokevirtual #375                // Method com/mojang/blaze3d/pipeline/RenderPipeline$Builder.build:()Lcom/mojang/blaze3d/pipeline/RenderPipeline;
    4318: invokestatic  #377                // Method register:(Lcom/mojang/blaze3d/pipeline/RenderPipeline;)Lcom/mojang/blaze3d/pipeline/RenderPipeline;
    4321: putstatic     #800                // Field FIRE_SCREEN_EFFECT:Lcom/mojang/blaze3d/pipeline/RenderPipeline;
    4324: iconst_1
    4325: anewarray     #11                 // class com/mojang/blaze3d/pipeline/RenderPipeline$Snippet
    4328: dup
    4329: iconst_0
    4330: getstatic     #347                // Field POSITION_TEX_COLOR_SNIPPET:Lcom/mojang/blaze3d/pipeline/RenderPipeline$Snippet;
    4333: aastore
    4334: invokestatic  #177                // Method com/mojang/blaze3d/pipeline/RenderPipeline.builder:([Lcom/mojang/blaze3d/pipeline/RenderPipeline$Snippet;)Lcom/mojang/blaze3d/pipeline/RenderPipeline$Builder;
    4337: ldc_w         #802                // String pipeline/gui_opaque_textured_background
    4340: invokevirtual #371                // Method com/mojang/blaze3d/pipeline/RenderPipeline$Builder.withLocation:(Ljava/lang/String;)Lcom/mojang/blaze3d/pipeline/RenderPipeline$Builder;
    4343: invokevirtual #806                // Method com/mojang/blaze3d/pipeline/RenderPipeline$Builder.withoutBlend:()Lcom/mojang/blaze3d/pipeline/RenderPipeline$Builder;
    4346: invokevirtual #375                // Method com/mojang/blaze3d/pipeline/RenderPipeline$Builder.build:()Lcom/mojang/blaze3d/pipeline/RenderPipeline;
    4349: invokestatic  #377                // Method register:(Lcom/mojang/blaze3d/pipeline/RenderPipeline;)Lcom/mojang/blaze3d/pipeline/RenderPipeline;
    4352: putstatic     #808                // Field GUI_OPAQUE_TEX_BG:Lcom/mojang/blaze3d/pipeline/RenderPipeline;
    4355: iconst_1
    4356: anewarray     #11                 // class com/mojang/blaze3d/pipeline/RenderPipeline$Snippet
    4359: dup
    4360: iconst_0
    4361: getstatic     #347                // Field POSITION_TEX_COLOR_SNIPPET:Lcom/mojang/blaze3d/pipeline/RenderPipeline$Snippet;
    4364: aastore
    4365: invokestatic  #177                // Method com/mojang/blaze3d/pipeline/RenderPipeline.builder:([Lcom/mojang/blaze3d/pipeline/RenderPipeline$Snippet;)Lcom/mojang/blaze3d/pipeline/RenderPipeline$Builder;
    4368: ldc_w         #810                // String pipeline/gui_nausea_overlay
    4371: invokevirtual #371                // Method com/mojang/blaze3d/pipeline/RenderPipeline$Builder.withLocation:(Ljava/lang/String;)Lcom/mojang/blaze3d/pipeline/RenderPipeline$Builder;
    4374: getstatic     #487                // Field com/mojang/blaze3d/pipeline/BlendFunction.ADDITIVE:Lcom/mojang/blaze3d/pipeline/BlendFunction;
    4377: invokevirtual #270                // Method com/mojang/blaze3d/pipeline/RenderPipeline$Builder.withBlend:(Lcom/mojang/blaze3d/pipeline/BlendFunction;)Lcom/mojang/blaze3d/pipeline/RenderPipeline$Builder;
    4380: invokevirtual #375                // Method com/mojang/blaze3d/pipeline/RenderPipeline$Builder.build:()Lcom/mojang/blaze3d/pipeline/RenderPipeline;
    4383: invokestatic  #377                // Method register:(Lcom/mojang/blaze3d/pipeline/RenderPipeline;)Lcom/mojang/blaze3d/pipeline/RenderPipeline;
    4386: putstatic     #812                // Field GUI_NAUSEA_OVERLAY:Lcom/mojang/blaze3d/pipeline/RenderPipeline;
    4389: iconst_1
    4390: anewarray     #11                 // class com/mojang/blaze3d/pipeline/RenderPipeline$Snippet
    4393: dup
    4394: iconst_0
    4395: getstatic     #347                // Field POSITION_TEX_COLOR_SNIPPET:Lcom/mojang/blaze3d/pipeline/RenderPipeline$Snippet;
    4398: aastore
    4399: invokestatic  #177                // Method com/mojang/blaze3d/pipeline/RenderPipeline.builder:([Lcom/mojang/blaze3d/pipeline/RenderPipeline$Snippet;)Lcom/mojang/blaze3d/pipeline/RenderPipeline$Builder;
    4402: ldc_w         #814                // String pipeline/vignette
    4405: invokevirtual #371                // Method com/mojang/blaze3d/pipeline/RenderPipeline$Builder.withLocation:(Ljava/lang/String;)Lcom/mojang/blaze3d/pipeline/RenderPipeline$Builder;
    4408: new           #263                // class com/mojang/blaze3d/pipeline/BlendFunction
    4411: dup
    4412: getstatic     #816                // Field com/mojang/blaze3d/platform/SourceFactor.ZERO:Lcom/mojang/blaze3d/platform/SourceFactor;
    4415: getstatic     #819                // Field com/mojang/blaze3d/platform/DestFactor.ONE_MINUS_SRC_COLOR:Lcom/mojang/blaze3d/platform/DestFactor;
    4418: invokespecial #822                // Method com/mojang/blaze3d/pipeline/BlendFunction."<init>":(Lcom/mojang/blaze3d/platform/SourceFactor;Lcom/mojang/blaze3d/platform/DestFactor;)V
    4421: invokevirtual #270                // Method com/mojang/blaze3d/pipeline/RenderPipeline$Builder.withBlend:(Lcom/mojang/blaze3d/pipeline/BlendFunction;)Lcom/mojang/blaze3d/pipeline/RenderPipeline$Builder;
    4424: invokevirtual #375                // Method com/mojang/blaze3d/pipeline/RenderPipeline$Builder.build:()Lcom/mojang/blaze3d/pipeline/RenderPipeline;
    4427: invokestatic  #377                // Method register:(Lcom/mojang/blaze3d/pipeline/RenderPipeline;)Lcom/mojang/blaze3d/pipeline/RenderPipeline;
    4430: putstatic     #824                // Field VIGNETTE:Lcom/mojang/blaze3d/pipeline/RenderPipeline;
    4433: iconst_1
    4434: anewarray     #11                 // class com/mojang/blaze3d/pipeline/RenderPipeline$Snippet
    4437: dup
    4438: iconst_0
    4439: getstatic     #347                // Field POSITION_TEX_COLOR_SNIPPET:Lcom/mojang/blaze3d/pipeline/RenderPipeline$Snippet;
    4442: aastore
    4443: invokestatic  #177                // Method com/mojang/blaze3d/pipeline/RenderPipeline.builder:([Lcom/mojang/blaze3d/pipeline/RenderPipeline$Snippet;)Lcom/mojang/blaze3d/pipeline/RenderPipeline$Builder;
    4446: ldc_w         #826                // String pipeline/crosshair
    4449: invokevirtual #371                // Method com/mojang/blaze3d/pipeline/RenderPipeline$Builder.withLocation:(Ljava/lang/String;)Lcom/mojang/blaze3d/pipeline/RenderPipeline$Builder;
    4452: getstatic     #775                // Field com/mojang/blaze3d/pipeline/BlendFunction.INVERT:Lcom/mojang/blaze3d/pipeline/BlendFunction;
    4455: invokevirtual #270                // Method com/mojang/blaze3d/pipeline/RenderPipeline$Builder.withBlend:(Lcom/mojang/blaze3d/pipeline/BlendFunction;)Lcom/mojang/blaze3d/pipeline/RenderPipeline$Builder;
    4458: invokevirtual #375                // Method com/mojang/blaze3d/pipeline/RenderPipeline$Builder.build:()Lcom/mojang/blaze3d/pipeline/RenderPipeline;
    4461: invokestatic  #377                // Method register:(Lcom/mojang/blaze3d/pipeline/RenderPipeline;)Lcom/mojang/blaze3d/pipeline/RenderPipeline;
    4464: putstatic     #828                // Field CROSSHAIR:Lcom/mojang/blaze3d/pipeline/RenderPipeline;
    4467: iconst_1
    4468: anewarray     #11                 // class com/mojang/blaze3d/pipeline/RenderPipeline$Snippet
    4471: dup
    4472: iconst_0
    4473: getstatic     #347                // Field POSITION_TEX_COLOR_SNIPPET:Lcom/mojang/blaze3d/pipeline/RenderPipeline$Snippet;
    4476: aastore
    4477: invokestatic  #177                // Method com/mojang/blaze3d/pipeline/RenderPipeline.builder:([Lcom/mojang/blaze3d/pipeline/RenderPipeline$Snippet;)Lcom/mojang/blaze3d/pipeline/RenderPipeline$Builder;
    4480: ldc_w         #830                // String pipeline/mojang_logo
    4483: invokevirtual #371                // Method com/mojang/blaze3d/pipeline/RenderPipeline$Builder.withLocation:(Ljava/lang/String;)Lcom/mojang/blaze3d/pipeline/RenderPipeline$Builder;
    4486: new           #263                // class com/mojang/blaze3d/pipeline/BlendFunction
    4489: dup
    4490: getstatic     #833                // Field com/mojang/blaze3d/platform/SourceFactor.SRC_ALPHA:Lcom/mojang/blaze3d/platform/SourceFactor;
    4493: getstatic     #835                // Field com/mojang/blaze3d/platform/DestFactor.ONE:Lcom/mojang/blaze3d/platform/DestFactor;
    4496: invokespecial #822                // Method com/mojang/blaze3d/pipeline/BlendFunction."<init>":(Lcom/mojang/blaze3d/platform/SourceFactor;Lcom/mojang/blaze3d/platform/DestFactor;)V
    4499: invokevirtual #270                // Method com/mojang/blaze3d/pipeline/RenderPipeline$Builder.withBlend:(Lcom/mojang/blaze3d/pipeline/BlendFunction;)Lcom/mojang/blaze3d/pipeline/RenderPipeline$Builder;
    4502: invokevirtual #375                // Method com/mojang/blaze3d/pipeline/RenderPipeline$Builder.build:()Lcom/mojang/blaze3d/pipeline/RenderPipeline;
    4505: invokestatic  #377                // Method register:(Lcom/mojang/blaze3d/pipeline/RenderPipeline;)Lcom/mojang/blaze3d/pipeline/RenderPipeline;
    4508: putstatic     #837                // Field MOJANG_LOGO:Lcom/mojang/blaze3d/pipeline/RenderPipeline;
    4511: iconst_0
    4512: anewarray     #11                 // class com/mojang/blaze3d/pipeline/RenderPipeline$Snippet
    4515: invokestatic  #177                // Method com/mojang/blaze3d/pipeline/RenderPipeline.builder:([Lcom/mojang/blaze3d/pipeline/RenderPipeline$Snippet;)Lcom/mojang/blaze3d/pipeline/RenderPipeline$Builder;
    4518: ldc_w         #839                // String pipeline/entity_outline_blit
    4521: invokevirtual #371                // Method com/mojang/blaze3d/pipeline/RenderPipeline$Builder.withLocation:(Ljava/lang/String;)Lcom/mojang/blaze3d/pipeline/RenderPipeline$Builder;
    4524: ldc_w         #841                // String core/blit_screen
    4527: invokevirtual #217                // Method com/mojang/blaze3d/pipeline/RenderPipeline$Builder.withVertexShader:(Ljava/lang/String;)Lcom/mojang/blaze3d/pipeline/RenderPipeline$Builder;
    4530: ldc_w         #841                // String core/blit_screen
    4533: invokevirtual #220                // Method com/mojang/blaze3d/pipeline/RenderPipeline$Builder.withFragmentShader:(Ljava/lang/String;)Lcom/mojang/blaze3d/pipeline/RenderPipeline$Builder;
    4536: ldc_w         #843                // String InSampler
    4539: invokevirtual #225                // Method com/mojang/blaze3d/pipeline/RenderPipeline$Builder.withSampler:(Ljava/lang/String;)Lcom/mojang/blaze3d/pipeline/RenderPipeline$Builder;
    4542: getstatic     #845                // Field com/mojang/blaze3d/pipeline/BlendFunction.ENTITY_OUTLINE_BLIT:Lcom/mojang/blaze3d/pipeline/BlendFunction;
    4545: invokevirtual #270                // Method com/mojang/blaze3d/pipeline/RenderPipeline$Builder.withBlend:(Lcom/mojang/blaze3d/pipeline/BlendFunction;)Lcom/mojang/blaze3d/pipeline/RenderPipeline$Builder;
    4548: iconst_0
    4549: invokevirtual #362                // Method com/mojang/blaze3d/pipeline/RenderPipeline$Builder.withDepthWrite:(Z)Lcom/mojang/blaze3d/pipeline/RenderPipeline$Builder;
    4552: getstatic     #355                // Field com/mojang/blaze3d/platform/DepthTestFunction.NO_DEPTH_TEST:Lcom/mojang/blaze3d/platform/DepthTestFunction;
    4555: invokevirtual #359                // Method com/mojang/blaze3d/pipeline/RenderPipeline$Builder.withDepthTestFunction:(Lcom/mojang/blaze3d/platform/DepthTestFunction;)Lcom/mojang/blaze3d/pipeline/RenderPipeline$Builder;
    4558: iconst_1
    4559: iconst_0
    4560: invokevirtual #848                // Method com/mojang/blaze3d/pipeline/RenderPipeline$Builder.withColorWrite:(ZZ)Lcom/mojang/blaze3d/pipeline/RenderPipeline$Builder;
    4563: getstatic     #282                // Field net/minecraft/client/render/VertexFormats.POSITION:Lcom/mojang/blaze3d/vertex/VertexFormat;
    4566: getstatic     #237                // Field com/mojang/blaze3d/vertex/VertexFormat$DrawMode.QUADS:Lcom/mojang/blaze3d/vertex/VertexFormat$DrawMode;
    4569: invokevirtual #241                // Method com/mojang/blaze3d/pipeline/RenderPipeline$Builder.withVertexFormat:(Lcom/mojang/blaze3d/vertex/VertexFormat;Lcom/mojang/blaze3d/vertex/VertexFormat$DrawMode;)Lcom/mojang/blaze3d/pipeline/RenderPipeline$Builder;
    4572: invokevirtual #375                // Method com/mojang/blaze3d/pipeline/RenderPipeline$Builder.build:()Lcom/mojang/blaze3d/pipeline/RenderPipeline;
    4575: invokestatic  #377                // Method register:(Lcom/mojang/blaze3d/pipeline/RenderPipeline;)Lcom/mojang/blaze3d/pipeline/RenderPipeline;
    4578: putstatic     #850                // Field ENTITY_OUTLINE_BLIT:Lcom/mojang/blaze3d/pipeline/RenderPipeline;
    4581: iconst_0
    4582: anewarray     #11                 // class com/mojang/blaze3d/pipeline/RenderPipeline$Snippet
    4585: invokestatic  #177                // Method com/mojang/blaze3d/pipeline/RenderPipeline.builder:([Lcom/mojang/blaze3d/pipeline/RenderPipeline$Snippet;)Lcom/mojang/blaze3d/pipeline/RenderPipeline$Builder;
    4588: ldc_w         #852                // String pipeline/tracy_blit
    4591: invokevirtual #371                // Method com/mojang/blaze3d/pipeline/RenderPipeline$Builder.withLocation:(Ljava/lang/String;)Lcom/mojang/blaze3d/pipeline/RenderPipeline$Builder;
    4594: ldc_w         #841                // String core/blit_screen
    4597: invokevirtual #217                // Method com/mojang/blaze3d/pipeline/RenderPipeline$Builder.withVertexShader:(Ljava/lang/String;)Lcom/mojang/blaze3d/pipeline/RenderPipeline$Builder;
    4600: ldc_w         #841                // String core/blit_screen
    4603: invokevirtual #220                // Method com/mojang/blaze3d/pipeline/RenderPipeline$Builder.withFragmentShader:(Ljava/lang/String;)Lcom/mojang/blaze3d/pipeline/RenderPipeline$Builder;
    4606: ldc_w         #843                // String InSampler
    4609: invokevirtual #225                // Method com/mojang/blaze3d/pipeline/RenderPipeline$Builder.withSampler:(Ljava/lang/String;)Lcom/mojang/blaze3d/pipeline/RenderPipeline$Builder;
    4612: iconst_0
    4613: invokevirtual #362                // Method com/mojang/blaze3d/pipeline/RenderPipeline$Builder.withDepthWrite:(Z)Lcom/mojang/blaze3d/pipeline/RenderPipeline$Builder;
    4616: getstatic     #355                // Field com/mojang/blaze3d/platform/DepthTestFunction.NO_DEPTH_TEST:Lcom/mojang/blaze3d/platform/DepthTestFunction;
    4619: invokevirtual #359                // Method com/mojang/blaze3d/pipeline/RenderPipeline$Builder.withDepthTestFunction:(Lcom/mojang/blaze3d/platform/DepthTestFunction;)Lcom/mojang/blaze3d/pipeline/RenderPipeline$Builder;
    4622: getstatic     #282                // Field net/minecraft/client/render/VertexFormats.POSITION:Lcom/mojang/blaze3d/vertex/VertexFormat;
    4625: getstatic     #237                // Field com/mojang/blaze3d/vertex/VertexFormat$DrawMode.QUADS:Lcom/mojang/blaze3d/vertex/VertexFormat$DrawMode;
    4628: invokevirtual #241                // Method com/mojang/blaze3d/pipeline/RenderPipeline$Builder.withVertexFormat:(Lcom/mojang/blaze3d/vertex/VertexFormat;Lcom/mojang/blaze3d/vertex/VertexFormat$DrawMode;)Lcom/mojang/blaze3d/pipeline/RenderPipeline$Builder;
    4631: invokevirtual #375                // Method com/mojang/blaze3d/pipeline/RenderPipeline$Builder.build:()Lcom/mojang/blaze3d/pipeline/RenderPipeline;
    4634: invokestatic  #377                // Method register:(Lcom/mojang/blaze3d/pipeline/RenderPipeline;)Lcom/mojang/blaze3d/pipeline/RenderPipeline;
    4637: putstatic     #854                // Field TRACY_BLIT:Lcom/mojang/blaze3d/pipeline/RenderPipeline;
    4640: iconst_1
    4641: anewarray     #11                 // class com/mojang/blaze3d/pipeline/RenderPipeline$Snippet
    4644: dup
    4645: iconst_0
    4646: getstatic     #197                // Field TRANSFORMS_AND_PROJECTION_SNIPPET:Lcom/mojang/blaze3d/pipeline/RenderPipeline$Snippet;
    4649: aastore
    4650: invokestatic  #177                // Method com/mojang/blaze3d/pipeline/RenderPipeline.builder:([Lcom/mojang/blaze3d/pipeline/RenderPipeline$Snippet;)Lcom/mojang/blaze3d/pipeline/RenderPipeline$Builder;
    4653: ldc_w         #856                // String pipeline/panorama
    4656: invokevirtual #371                // Method com/mojang/blaze3d/pipeline/RenderPipeline$Builder.withLocation:(Ljava/lang/String;)Lcom/mojang/blaze3d/pipeline/RenderPipeline$Builder;
    4659: ldc_w         #858                // String core/panorama
    4662: invokevirtual #217                // Method com/mojang/blaze3d/pipeline/RenderPipeline$Builder.withVertexShader:(Ljava/lang/String;)Lcom/mojang/blaze3d/pipeline/RenderPipeline$Builder;
    4665: ldc_w         #858                // String core/panorama
    4668: invokevirtual #220                // Method com/mojang/blaze3d/pipeline/RenderPipeline$Builder.withFragmentShader:(Ljava/lang/String;)Lcom/mojang/blaze3d/pipeline/RenderPipeline$Builder;
    4671: ldc           #222                // String Sampler0
    4673: invokevirtual #225                // Method com/mojang/blaze3d/pipeline/RenderPipeline$Builder.withSampler:(Ljava/lang/String;)Lcom/mojang/blaze3d/pipeline/RenderPipeline$Builder;
    4676: iconst_0
    4677: invokevirtual #362                // Method com/mojang/blaze3d/pipeline/RenderPipeline$Builder.withDepthWrite:(Z)Lcom/mojang/blaze3d/pipeline/RenderPipeline$Builder;
    4680: iconst_1
    4681: iconst_0
    4682: invokevirtual #848                // Method com/mojang/blaze3d/pipeline/RenderPipeline$Builder.withColorWrite:(ZZ)Lcom/mojang/blaze3d/pipeline/RenderPipeline$Builder;
    4685: getstatic     #282                // Field net/minecraft/client/render/VertexFormats.POSITION:Lcom/mojang/blaze3d/vertex/VertexFormat;
    4688: getstatic     #237                // Field com/mojang/blaze3d/vertex/VertexFormat$DrawMode.QUADS:Lcom/mojang/blaze3d/vertex/VertexFormat$DrawMode;
    4691: invokevirtual #241                // Method com/mojang/blaze3d/pipeline/RenderPipeline$Builder.withVertexFormat:(Lcom/mojang/blaze3d/vertex/VertexFormat;Lcom/mojang/blaze3d/vertex/VertexFormat$DrawMode;)Lcom/mojang/blaze3d/pipeline/RenderPipeline$Builder;
    4694: invokevirtual #375                // Method com/mojang/blaze3d/pipeline/RenderPipeline$Builder.build:()Lcom/mojang/blaze3d/pipeline/RenderPipeline;
    4697: invokestatic  #377                // Method register:(Lcom/mojang/blaze3d/pipeline/RenderPipeline;)Lcom/mojang/blaze3d/pipeline/RenderPipeline;
    4700: putstatic     #860                // Field POSITION_TEX_PANORAMA:Lcom/mojang/blaze3d/pipeline/RenderPipeline;
    4703: iconst_1
    4704: anewarray     #11                 // class com/mojang/blaze3d/pipeline/RenderPipeline$Snippet
    4707: dup
    4708: iconst_0
    4709: getstatic     #364                // Field RENDERTYPE_OUTLINE_SNIPPET:Lcom/mojang/blaze3d/pipeline/RenderPipeline$Snippet;
    4712: aastore
    4713: invokestatic  #177                // Method com/mojang/blaze3d/pipeline/RenderPipeline.builder:([Lcom/mojang/blaze3d/pipeline/RenderPipeline$Snippet;)Lcom/mojang/blaze3d/pipeline/RenderPipeline$Builder;
    4716: ldc_w         #862                // String pipeline/outline_cull
    4719: invokevirtual #371                // Method com/mojang/blaze3d/pipeline/RenderPipeline$Builder.withLocation:(Ljava/lang/String;)Lcom/mojang/blaze3d/pipeline/RenderPipeline$Builder;
    4722: invokevirtual #375                // Method com/mojang/blaze3d/pipeline/RenderPipeline$Builder.build:()Lcom/mojang/blaze3d/pipeline/RenderPipeline;
    4725: invokestatic  #377                // Method register:(Lcom/mojang/blaze3d/pipeline/RenderPipeline;)Lcom/mojang/blaze3d/pipeline/RenderPipeline;
    4728: putstatic     #864                // Field OUTLINE_CULL:Lcom/mojang/blaze3d/pipeline/RenderPipeline;
    4731: iconst_1
    4732: anewarray     #11                 // class com/mojang/blaze3d/pipeline/RenderPipeline$Snippet
    4735: dup
    4736: iconst_0
    4737: getstatic     #364                // Field RENDERTYPE_OUTLINE_SNIPPET:Lcom/mojang/blaze3d/pipeline/RenderPipeline$Snippet;
    4740: aastore
    4741: invokestatic  #177                // Method com/mojang/blaze3d/pipeline/RenderPipeline.builder:([Lcom/mojang/blaze3d/pipeline/RenderPipeline$Snippet;)Lcom/mojang/blaze3d/pipeline/RenderPipeline$Builder;
    4744: ldc_w         #866                // String pipeline/outline_no_cull
    4747: invokevirtual #371                // Method com/mojang/blaze3d/pipeline/RenderPipeline$Builder.withLocation:(Ljava/lang/String;)Lcom/mojang/blaze3d/pipeline/RenderPipeline$Builder;
    4750: iconst_0
    4751: invokevirtual #313                // Method com/mojang/blaze3d/pipeline/RenderPipeline$Builder.withCull:(Z)Lcom/mojang/blaze3d/pipeline/RenderPipeline$Builder;
    4754: invokevirtual #375                // Method com/mojang/blaze3d/pipeline/RenderPipeline$Builder.build:()Lcom/mojang/blaze3d/pipeline/RenderPipeline;
    4757: invokestatic  #377                // Method register:(Lcom/mojang/blaze3d/pipeline/RenderPipeline;)Lcom/mojang/blaze3d/pipeline/RenderPipeline;
    4760: putstatic     #868                // Field OUTLINE_NO_CULL:Lcom/mojang/blaze3d/pipeline/RenderPipeline;
    4763: iconst_0
    4764: anewarray     #11                 // class com/mojang/blaze3d/pipeline/RenderPipeline$Snippet
    4767: invokestatic  #177                // Method com/mojang/blaze3d/pipeline/RenderPipeline.builder:([Lcom/mojang/blaze3d/pipeline/RenderPipeline$Snippet;)Lcom/mojang/blaze3d/pipeline/RenderPipeline$Builder;
    4770: ldc_w         #870                // String pipeline/lightmap
    4773: invokevirtual #371                // Method com/mojang/blaze3d/pipeline/RenderPipeline$Builder.withLocation:(Ljava/lang/String;)Lcom/mojang/blaze3d/pipeline/RenderPipeline$Builder;
    4776: ldc_w         #841                // String core/blit_screen
    4779: invokevirtual #217                // Method com/mojang/blaze3d/pipeline/RenderPipeline$Builder.withVertexShader:(Ljava/lang/String;)Lcom/mojang/blaze3d/pipeline/RenderPipeline$Builder;
    4782: ldc_w         #872                // String core/lightmap
    4785: invokevirtual #220                // Method com/mojang/blaze3d/pipeline/RenderPipeline$Builder.withFragmentShader:(Ljava/lang/String;)Lcom/mojang/blaze3d/pipeline/RenderPipeline$Builder;
    4788: ldc_w         #874                // String LightmapInfo
    4791: getstatic     #185                // Field net/minecraft/client/gl/UniformType.UNIFORM_BUFFER:Lnet/minecraft/client/gl/UniformType;
    4794: invokevirtual #189                // Method com/mojang/blaze3d/pipeline/RenderPipeline$Builder.withUniform:(Ljava/lang/String;Lnet/minecraft/client/gl/UniformType;)Lcom/mojang/blaze3d/pipeline/RenderPipeline$Builder;
    4797: getstatic     #282                // Field net/minecraft/client/render/VertexFormats.POSITION:Lcom/mojang/blaze3d/vertex/VertexFormat;
    4800: getstatic     #237                // Field com/mojang/blaze3d/vertex/VertexFormat$DrawMode.QUADS:Lcom/mojang/blaze3d/vertex/VertexFormat$DrawMode;
    4803: invokevirtual #241                // Method com/mojang/blaze3d/pipeline/RenderPipeline$Builder.withVertexFormat:(Lcom/mojang/blaze3d/vertex/VertexFormat;Lcom/mojang/blaze3d/vertex/VertexFormat$DrawMode;)Lcom/mojang/blaze3d/pipeline/RenderPipeline$Builder;
    4806: iconst_0
    4807: invokevirtual #362                // Method com/mojang/blaze3d/pipeline/RenderPipeline$Builder.withDepthWrite:(Z)Lcom/mojang/blaze3d/pipeline/RenderPipeline$Builder;
    4810: getstatic     #355                // Field com/mojang/blaze3d/platform/DepthTestFunction.NO_DEPTH_TEST:Lcom/mojang/blaze3d/platform/DepthTestFunction;
    4813: invokevirtual #359                // Method com/mojang/blaze3d/pipeline/RenderPipeline$Builder.withDepthTestFunction:(Lcom/mojang/blaze3d/platform/DepthTestFunction;)Lcom/mojang/blaze3d/pipeline/RenderPipeline$Builder;
    4816: invokevirtual #375                // Method com/mojang/blaze3d/pipeline/RenderPipeline$Builder.build:()Lcom/mojang/blaze3d/pipeline/RenderPipeline;
    4819: invokestatic  #377                // Method register:(Lcom/mojang/blaze3d/pipeline/RenderPipeline;)Lcom/mojang/blaze3d/pipeline/RenderPipeline;
    4822: putstatic     #876                // Field BILT_SCREEN_LIGHTMAP:Lcom/mojang/blaze3d/pipeline/RenderPipeline;
    4825: return
}
